Workbook
Name ACTION: #REF!
Name ACTION: #REF!

Sheet Cover
B2: TEST REPORT DOCUMENT
A4: Project Name | B4: Online Learning Platform – SkillUp | E4: Creator | F4: TuanCM
A5: Project Code | B5: OLP-SkillUp | E5: Issue Date | F5: 45978
A6: Document Code | B6: =B5&"_"&"Integration_Test_Report"&"" -> OLP-SkillUp_Integration_Test_Report | E6: Version | F6: 1.0
A9: Record of change
A10: Effective Date | B10: Version | C10: Change Item | D10: *A,D,M | E10: Change description | F10: Reference
A11: 45978 | B11: 1.0 | D11: A | E11: Initialize Integration Test
A12: 45978 | B12: 1.0 | C12: Test Cases, Test Statistics | D12: A | E12: Implement test cases for Iteration 1.
A13: 45978 | B13: 1.0 | C13: Test Cases, Test Statistics | D13: M | E13: Implement test cases for Iteration 2.
A14: 45978 | B14: 1.0 | C14: Test Cases, Test Statistics | D14: M | E14: Implement test cases for Iteration 3.

Sheet Test Cases
D1: TEST CASE LIST
B3: Project Name | D3: Online Learning Platform – SkillUp
B4: Project Code | D4: OLP-SkillUp
B5: Test Environment Setup Description | D5: 1. Server 2. SQLServer 3.Google Chrome, Microsoft Edge 4. Microsoft Visual Studio
B8: No | C8: Function Name | D8: Sheet Name | E8: Description | F8: Pre-Condition
B9: 1 | C9: =Register!B2 -> Register | D9: Register
B10: 2 | C10: Login by account | D10: Login by account
B11: 3 | C11: Login by google | D11: Login by google
B12: 4 | C12: Forgot password | D12: Forgot password
B13: 5 | C13: Logout | D13: Logout
B14: 6 | C14: View profile | D14: View profile
B15: 7 | C15: Update profile | D15: Update profile
B16: 8 | C16: Change password | D16: Change password
B17: 9 | C17: View purchase history | D17: View purchase history
B18: 10 | C18: View cart | D18: View cart
B19: 11 | C19: Add to cart | D19: Add to cart
B20: 12 | C20: Remove from cart | D20: Remove from cart
B21: 13 | C21: Add course | D21: Add course
... B42: 34 | C42: Email notification | D42: Email notification

Sheet Test Statistics
B1: TEST STATISTICS
B3: Project Name | C3: Online Learning Platform – SkillUp | E3: Creator | H3: TuanCM
B4: Project Code | C4: OLP-SkillUp | E4: Reviewer/Approver
B5: Document Code | C5: =C4&"_"&"System_Test_Report"&"" -> OLP-SkillUp_System_Test_Report | E5: Issue Date | H5: 45964
B6: Notes
B10: No | C10: Module code | D10: Passed | E10: Failed | F10: Pending | G10: N/A | H10: Number of test cases
B11: 1 | C11: Register | D11: =Register!B6 -> 3 | E11: =Register!C6 -> 0 | F11: =Register!D6 -> 0 | G11: =Register!E6 -> 0 | H11: =Register!B4 -> 3
B12: 2 | C12: Login by account | D12: ='Login by account'!B6 -> 3 | E12: ='Login by account'!C6 -> 0 | F12: ='Login by account'!D6 -> 0 | G12: ='Login by account'!E6 -> 0 | H12: ='Login by account'!B4 -> 3
B13: 3 | C13: Login by google | D13: ='Login by Google'!B6 -> 1 | E13: ='Login by Google'!C6 -> 0 | F13: ='Login by Google'!D6 -> 0 | G13: ='Login by Google'!E6 -> 0 | H13: ='Login by Google'!B4 -> 1
B14: 4 | C14: Forgot password | D14: ='Forgot password'!B6 -> 2 | E14: ='Forgot password'!C6 -> 0 | F14: ='Forgot password'!D6 -> 0 | G14: ='Forgot password'!E6 -> 0 | H14: ='Forgot password'!B4 -> 2
B15: 5 | C15: Logout | D15: =Logout!B6 -> 3 | E15: =Logout!C6 -> 0 | F15: =Logout!D6 -> 0 | G15: =Logout!E6 -> 0 | H15: =Logout!B4 -> 3
B16: 6 | C16: View profile | D16: ='View user profile'!B6 -> 1 | E16: ='View user profile'!C6 -> 0 | F16: ='View user profile'!D6 -> 0 | G16: ='View user profile'!E6 -> 0 | H16: ='View user profile'!B4 -> 1
B17: 7 | C17: Update profile | D17: ='Update user profile'!B6 -> 2 | E17: ='Update user profile'!C6 -> 0 | F17: ='Update user profile'!D6 -> 0 | G17: ='Update user profile'!E6 -> 0 | H17: ='Update user profile'!B4 -> 2
B18: 8 | C18: Change password | D18: ='Change password'!B6 -> 4 | E18: ='Change password'!C6 -> 0 | F18: ='Change password'!D6 -> 0 | G18: ='Change password'!E6 -> 0 | H18: ='Change password'!B4 -> 4
B19: 9 | C19: View purchase history | D19: ='View purchase history'!B6 -> 2 | E19: ='View purchase history'!C6 -> 0 | F19: ='View purchase history'!D6 -> 0 | G19: ='View purchase history'!E6 -> 0 | H19: ='View purchase history'!B4 -> 2
B20: 10 | C20: View cart | D20: ='View cart'!B6 -> 2 | E20: ='View cart'!C6 -> 0 | F20: ='View cart'!D6 -> 0 | G20: ='View cart'!E6 -> 0 | H20: ='View cart'!B4 -> 2
B21: 11 | C21: Add to cart | D21: ='Add to cart'!B6 -> 3 | E21: ='Add to cart'!C6 -> 0 | F21: ='Add to cart'!D6 -> 0 | G21: ='Add to cart'!E6 -> 0 | H21: ='Add to cart'!B4 -> 3
B22: 12 | C22: Remove from cart | D22: ='Remove item from cart'!B6 -> 2 | E22: ='Remove item from cart'!C6 -> 0 | F22: ='Remove item from cart'!D6 -> 0 | G22: ='Remove item from cart'!E6 -> 0 | H22: ='Remove item from cart'!B4 -> 2
B23: 13 | C23: Add course | D23: ='Add course'!B6 -> 2 | E23: ='Add course'!C6 -> 0 | F23: ='Add course'!D6 -> 0 | G23: ='Add course'!E6 -> 0 | H23: ='Add course'!B4 -> 2
B24: 14 | C24: Hide course | D24: ='Hide course'!B6 -> 1 | E24: ='Hide course'!C6 -> 0 | F24: ='Hide course'!D6 -> 0 | G24: ='Hide course'!E6 -> 0 | H24: ='Hide course'!B4 -> 1
B25: 15 | C25: Update course - general | D25: ='Update course - general'!B6 -> 9 | E25: ='Update course - general'!C6 -> 0 | F25: ='Update course - general'!D6 -> 0 | G25: ='Update course - general'!E6 -> 0 | H25: ='Update course - general'!B4 -> 9
B26: 16 | C26: View section | D26: ='View sections'!B6 -> 2 | E26: ='View sections'!C6 -> 0 | F26: ='View sections'!D6 -> 0 | G26: ='View sections'!E6 -> 0 | H26: ='View sections'!B4 -> 2
B27: 17 | C27: Add section | D27: ='Add sections'!B6 -> 4 | E27: ='Add sections'!C6 -> 0 | F27: ='Add sections'!D6 -> 0 | G27: ='Add sections'!E6 -> 0 | H27: ='Add sections'!B4 -> 4
B28: 18 | C28: Edit section | D28: ='Update sections'!B6 -> 3 | E28: ='Update sections'!C6 -> 0 | F28: ='Update sections'!D6 -> 0 | G28: ='Update sections'!E6 -> 0 | H28: ='Update sections'!B4 -> 3
B29: 19 | C29: Delete section | D29: ='Delete sections'!B6 -> 1 | E29: ='Delete sections'!C6 -> 0 | F29: ='Delete sections'!C6 -> 0 | G29: ='Delete sections'!E6 -> 0 | H29: ='Delete sections'!B4 -> 1
B30: 20 | C30: Create lesson | D30: ='Create lesson'!B6 -> 6 | E30: ='Create lesson'!C6 -> 0 | F30: ='Create lesson'!D6 -> 0 | G30: ='Create lesson'!E6 -> 0 | H30: ='Create lesson'!B4 -> 6
B31: 21 | C31: Create question | D31: ='Create question'!B6 -> 4 | E31: ='Create question'!C6 -> 0 | F31: ='Create question'!D6 -> 0 | G31: ='Create question'!E6 -> 0 | H31: ='Create question'!B4 -> 4
B32: 22 | C32: Add from bank | D32: ='Add question from bank'!B6 -> 2 | E32: ='Add question from bank'!C6 -> 0 | F32: ='Add question from bank'!D6 -> 0 | G32: ='Add question from bank'!E6 -> 0 | H32: ='Add question from bank'!B4 -> 2
B33: 23 | C33: View question | D33: ='View question'!B6 -> 2 | E33: ='View question'!C6 -> 0 | F33: ='View question'!D6 -> 0 | G33: ='View question'!E6 -> 0 | H33: ='View question'!B4 -> 2
B34: 24 | C34: Edit question | D34: ='Edit question'!B6 -> 3 | E34: ='Edit question'!C6 -> 0 | F34: ='Edit question'!D6 -> 0 | G34: ='Edit question'!E6 -> 0 | H34: ='Edit question'!B4 -> 3
B35: 25 | C35: Delete question | D35: ='Delete question'!B6 -> 2 | E35: ='Delete question'!C6 -> 0 | F35: ='Delete question'!D6 -> 0 | G35: ='Delete question'!E6 -> 0 | H35: ='Delete question'!B4 -> 2
B36: 26 | C36: Enroll course | D36: ='Enroll course'!B6 -> 3 | E36: ='Enroll course'!C6 -> 0 | F36: ='Enroll course'!D6 -> 0 | G36: ='Enroll course'!E6 -> 0 | H36: ='Enroll course'!B4 -> 3
B37: 27 | C37: Learning course | D37: ='Learning course'!B6 -> 3 | E37: ='Learning course'!C6 -> 0 | F37: ='Learning course'!D6 -> 0 | G37: ='Learning course'!E6 -> 0 | H37: ='Learning course'!B4 -> 3
B38: 28 | C38: Progress tracking | D38: ='Progress tracking'!B6 -> 1 | E38: ='Progress tracking'!C6 -> 0 | F38: ='Progress tracking'!D6 -> 0 | G38: ='Progress tracking'!E6 -> 0 | H38: ='Progress tracking'!B4 -> 1
B39: 29 | C39: Checkout | D39: ='Apply voucher'!B6 -> 5 | E39: ='Apply voucher'!C6 -> 0 | F39: ='Apply voucher'!D6 -> 0 | G39: ='Apply voucher'!E6 -> 0 | H39: ='Apply voucher'!B4 -> 5
B40: 30 | C40: Apply voucher | D40: =Checkout!B6 -> 5 | E40: ='Apply voucher'!C7 -> 0 | F40: ='Apply voucher'!D7 -> 0 | G40: ='Apply voucher'!E7 -> 0 | H40: ='Apply voucher'!B4 -> 5
B41: 31 | C41: Take quiz | D41: ='Take quiz'!B6 -> 6 | E41: ='Take quiz'!C6 -> 0 | F41: ='Take quiz'!D6 -> 0 | G41: ='Take quiz'!E6 -> 0 | H41: ='Take quiz'!B4 -> 6
B42: 32 | C42: View result | D42: ='View result'!B6 -> 6 | E42: ='View result'!C6 -> 0 | F42: ='View result'!D6 -> 0 | G42: ='View result'!E6 -> 0 | H42: ='View result'!B4 -> 6
B43: 33 | C43: Rating | D43: =Rating!B6 -> 2 | E43: =Rating!C6 -> 0 | F43: =Rating!D6 -> 0 | G43: =Rating!E6 -> 0 | H43: =Rating!B4 -> 2
B44: 34 | C44: Email notification | D44: ='Email notification'!B6 -> 4 | E44: ='Email notification'!C6 -> 0 | F44: ='Email notification'!D6 -> 0 | G44: ='Email notification'!E6 -> 0 | H44: ='Email notification'!B4 -> 4
C45: Sub total | D45: =SUM(D9:D44) -> 104 | E45: =SUM(E9:E38) -> 0 | F45: =SUM(F9:F38) -> 0 | G45: =SUM(G9:G38) -> 0 | H45: =SUM(H9:H44) -> 104
C47: Test coverage | E47: =(D45+E45)*100/(H45-G45) -> 100 | F47: %
C48: Test successful coverage | E48: =D45*100/(H45-G45) -> 100 | F48: %

Sheet Register
A2: Feature | B2: Register | R2: Passed
A3: Test requirement | B3: <Brief description about requirements which are tested in this sheet> | R3: Failed
A4: Number of TCs | B4: =COUNTA(A12:A867) -> 3 | R4: Pending
A5: Testing Round | B5: Passed | C5: Failed | D5: Pending | E5: N/A | R5: N/A
A6: Round 1 | B6: =COUNTIF($F10:$F865,B5) -> 3 | C6: =COUNTIF($F10:$F865,C5) -> 0 | D6: =COUNTIF($F10:$F865,D5) -> 0 | E6: =COUNTIF($F10:$F865,E5) -> 0
A7: Round 2 | B7: =COUNTIF($F10:$F865,B5) -> 3 | C7: =COUNTIF($F10:$F865,C5) -> 0 | D7: =COUNTIF($F10:$F865,D5) -> 0 | E7: =COUNTIF($F10:$F865,E5) -> 0
A8: Round 3 | B8: =COUNTIF($F10:$F865,B5) -> 3 | C8: =COUNTIF($F10:$F865,C5) -> 0 | D8: =COUNTIF($F10:$F865,D5) -> 0 | E8: =COUNTIF($F10:$F865,E5) -> 0
A10: Test Case ID | B10: Test Case Description | C10: Test Case Procedure | D10: Expected Results | E10: Pre-conditions | F10: Round 1 | G10: Test date | H10: Tester | I10: Round 2 | J10: Test date | K10: Tester | L10: Round 3 | M10: Test date | N10: Tester | O10: Note
A11: Register
A12: [Register - 1] | B12: Test registration with valid input : - Email - Password - Confirm Password - Full name | C12: 1. Enter "http://localhost:5173/" to navigate to the website. (Top-right corner of the screen) 2. Guest user click the “Đăng ký” button. 3. The site displays the registration form. 4. Guest user select a registration role: “Student” or “Lecturer.” 5. Enter the following valid information: - Email: student@gmail.com - Password: Student@123 - RePassword: Student@123 - Full Name: Nguyen Van A 6. Guest user click the “Đăng ký” button. 7. Guest user ou are redirected to the “Đăng nhập” screen. | D12: - The guest user successfully registered, is redirected to the login page and the user details are stored in the database. - Notification display system "Đăng ký thành công! Vui lòng kiểm tra email để xác thực tài khoản." - The system sends authentication to the registered user's email. | E12: Server must be work Guest user is not logged in and wants to create an account. | F12: Passed | G12: 45978 | H12: TuanCM | I12: Passed | J12: 45980 | K12: TuanCM | L12: Passed | M12: 45981 | N12: TuanCM
A13: [Register - 2] | B13: Test registration with invalid input : - Email - Password - Confirm Password - Full name | C13: 1. Enter "http://localhost:5173/" to navigate to the website. (Top-right corner of the screen) 2. Guest user clicks the “Đăng ký” button. 3. The site displays the registration form. 4. Guest user selects a registration role: “Student” or “Lecturer.” 5.Guest user enter invalid email form(e.g., quatbt.com) 6. Guest user clicks the “Đăng ký” button. 7. Website displays an error message for invaild email format 8. Guest user corrects the mail format and resubmits the form. | D13: System displays an error message for the empty fields and prevents registration until corrected. | E13: Server must be work Guest user is not logged in and wants to create an account. | F13: Passed | G13: 45978 | H13: TuanCM | I13: Passed | J13: 45980 | K13: TuanCM | L13: Passed | M13: 45981 | N13: TuanCM
A14: [Register - 3] | B14: Test registration with empty required fields: - Email - Password - Confirm Password - Full name | C14: 1. Enter "http://localhost:5173/" to navigate to the website. (Top-right corner of the screen) 2. Guest user click the “Đăng ký” button. 3. The site displays the registration form. 4. Guest user select a registration role: “Student” or “Lecturer.” 5. Enter the following valid information: - Email: empty - Password: empty - RePassword: empty - Full Name: empty 6. The registration form displays the message "vui lòng điền vào trường này". 7. The guest user corrects the inputs so no field is left blank and the format is valid, then submits the form. | D14: System displays an error message for the empty fields and prevents registration until corrected. | E14: Server must be work Guest user is not logged in and wants to create an account. | F14: Passed | G14: 45978 | H14: TuanCM | I14: Passed | J14: 45980 | K14: TuanCM | L14: Passed | M14: 45981 | N14: TuanCM

Sheet Login by account
A2: Feature | B2: Login by account | R2: Passed
A3: Test requirement | B3: <Brief description about requirements which are tested in this sheet> | R3: Failed
A4: Number of TCs | B4: =COUNTA(A12:A867) -> 3 | R4: Pending
A5: Testing Round | B5: Passed | C5: Failed | D5: Pending | E5: N/A | R5: N/A
A6: Round 1 | B6: =COUNTIF($F10:$F865,B5) -> 3 | C6: =COUNTIF($F10:$F865,C5) -> 0 | D6: =COUNTIF($F10:$F865,D5) -> 0 | E6: =COUNTIF($F10:$F865,E5) -> 0
A7: Round 2 | B7: =COUNTIF($F10:$F865,B5) -> 3 | C7: =COUNTIF($F10:$F865,C5) -> 0 | D7: =COUNTIF($F10:$F865,D5) -> 0 | E7: =COUNTIF($F10:$F865,E5) -> 0
A8: Round 3 | B8: =COUNTIF($F10:$F865,B5) -> 3 | C8: =COUNTIF($F10:$F865,C5) -> 0 | D8: =COUNTIF($F10:$F865,D5) -> 0 | E8: =COUNTIF($F10:$F865,E5) -> 0
A10: Test Case ID | B10: Test Case Description | C10: Test Case Procedure | D10: Expected Results | E10: Pre-conditions | F10: Round 1 | G10: Test date | H10: Tester | I10: Round 2 | J10: Test date | K10: Tester | L10: Round 3 | M10: Test date | N10: Tester | O10: Note
A11: Login by account
A12: [Login by account - 1] | B12: Check if the user can successfully log in with a valid email and password. | C12: 1. Enter "http://localhost:5173/" to go to website 2. Location in the right corner of the screen: - Click on "Đăng nhập" button 3. Fill in information including: - Email: user@example.com - Password: String 4. Click "Đăng nhập" button | D12: System displays message "Đăng nhập thành công!" | E12: Server must be work Guest user is not logged in and wants to create an account. | F12: Passed | G12: 45978 | H12: TuanCM | I12: Passed | J12: 45980 | K12: TuanCM | L12: Passed | M12: 45981 | N12: TuanCM
A13: [Login by account - 2] | B13: Check if the website handles an incorrect password. | C13: 1. Enter "http://localhost:5173/" to go to website 2. Location in the right corner of the screen: - Click on "Đăng nhập" button 3. Fill in information including: - Email: user@example.com - Password: String1111 4. Click "Đăng nhập" button | D13: System displays message "Email hoặc mật khẩu không đúng" | E13: Server must be work Guest user is not logged in and wants to create an account. | F13: Passed | G13: 45978 | H13: TuanCM | I13: Passed | J13: 45980 | K13: TuanCM | L13: Passed | M13: 45981 | N13: TuanCM
A14: [Login by account - 3] | B14: Check if the website handles an unregistered email address. | C14: 1. Enter "http://localhost:5173/" to go to website 2. Location in the right corner of the screen: - Click on "Đăng nhập" button 3. Fill in information including: - Email: user11@example.com - Password: String 4. Click "Đăng nhập" button | D14: System displays message "Email hoặc mật khẩu không đúng" | E14: Server must be work Guest user is not logged in and wants to create an account. | F14: Passed | G14: 45978 | H14: TuanCM | I14: Passed | J14: 45980 | K14: TuanCM | L14: Passed | M14: 45981 | N14: TuanCM

Sheet Login by Google
A2: Feature | B2: Login by Google | R2: Passed
A3: Test requirement | B3: <Brief description about requirements which are tested in this sheet> | R3: Failed
A4: Number of TCs | B4: =COUNTA(A12:A993) -> 1 | R4: Pending
A5: Testing Round | B5: Passed | C5: Failed | D5: Pending | E5: N/A | R5: N/A
A6: Round 1 | B6: =COUNTIF($F10:$F991,B5) -> 1 | C6: =COUNTIF($F10:$F991,C5) -> 0 | D6: =COUNTIF($F10:$F991,D5) -> 0 | E6: =COUNTIF($F10:$F991,E5) -> 0
A7: Round 2 | B7: =COUNTIF($F10:$F991,B5) -> 1 | C7: =COUNTIF($F10:$F991,C5) -> 0 | D7: =COUNTIF($F10:$F991,D5) -> 0 | E7: =COUNTIF($F10:$F991,E5) -> 0
A8: Round 3 | B8: =COUNTIF($F10:$F991,B5) -> 1 | C8: =COUNTIF($F10:$F991,C5) -> 0 | D8: =COUNTIF($F10:$F991,D5) -> 0 | E8: =COUNTIF($F10:$F991,E5) -> 0
A10: Test Case ID | B10: Test Case Description | C10: Test Case Procedure | D10: Expected Results | E10: Pre-conditions | F10: Round 1 | G10: Test date | H10: Tester | I10: Round 2 | J10: Test date | K10: Tester | L10: Round 3 | M10: Test date | N10: Tester | O10: Note
A11: Login by google
A12: [Login by Google- 1] | B12: Check if the user can successfully log in using a valid Google account. | C12: 1. Enter "http://localhost:5173/" to navigate to the website. (Top-right corner of the screen) 2. Guest user click the “Đăng nhập” button. 3. Click on the "Tiếp tục sử dụng dịch vụ bằng google" button. 4. The system redirects to Google’s login page. 5. The system redirects back to the application, showing the user's dashboard or homepage". | D12: System displays message "Đăng nhập Google thành công" | E12: 1.Server must be work 2..Account must be in system | F12: Passed | G12: 45978 | H12: TuanCM | I12: Passed | J12: 45980 | K12: TuanCM | L12: Passed | M12: 45981 | N12: TuanCM

Sheet Forgot password
A2: Feature | B2: Forgot password | R2: Passed
A3: Test requirement | B3: <Brief description about requirements which are tested in this sheet> | R3: Failed
A4: Number of TCs | B4: =COUNTA(A12:A866) -> 2 | R4: Pending
A5: Testing Round | B5: Passed | C5: Failed | D5: Pending | E5: N/A | R5: N/A
A6: Round 1 | B6: =COUNTIF($F10:$F864,B5) -> 2 | C6: =COUNTIF($F10:$F864,C5) -> 0 | D6: =COUNTIF($F10:$F864,D5) -> 0 | E6: =COUNTIF($F10:$F864,E5) -> 0
A7: Round 2 | B7: =COUNTIF($F10:$F864,B5) -> 2 | C7: =COUNTIF($F10:$F864,C5) -> 0 | D7: =COUNTIF($F10:$F864,D5) -> 0 | E7: =COUNTIF($F10:$F864,E5) -> 0
A8: Round 3 | B8: =COUNTIF($F10:$F864,B5) -> 2 | C8: =COUNTIF($F10:$F864,C5) -> 0 | D8: =COUNTIF($F10:$F864,D5) -> 0 | E8: =COUNTIF($F10:$F864,E5) -> 0
A10: Test Case ID | B10: Test Case Description | C10: Test Case Procedure | D10: Expected Results | E10: Pre-conditions | F10: Round 1 | G10: Test date | H10: Tester | I10: Round 2 | J10: Test date | K10: Tester | L10: Round 3 | M10: Test date | N10: Tester | O10: Note
A11: Forgot password
A12: [Forgot password- 1] | B12: Verify if the user can request a password reset by entering a valid registered email address. | C12: 1. Enter "http://localhost:5173/" to navigate to the website. (Top-right corner of the screen) 2. Guest user click the “Đăng nhập” button. 3. Guest user clicks on link "Quên mật khẩu?". 4. The system displays a form asking the user to enter their registered email address. 5. The user enters their email address and clicks the "Gửi email khôi phục" button. 6. The system sends a password reset email with a reset link to the user’s registered email address. 7. Redirect to "Đặt lại mật khẩu" screen 6. User enter the following valid information: - Mật khẩu mới: Student@123 - Xác nhận mật khẩu mới: Student@123 7. Click on "Đặt lại mật khẩu" button | D12: System displays message "Đặt lại mật khẩu thành công" | E12: 1.Server must be work 2..Account must be in system | F12: Passed | G12: 45978 | H12: TuanCM | I12: Passed | J12: 45980 | K12: TuanCM | L12: Passed | M12: 45981 | N12: TuanCM
A13: [Forgot password- 2] | B13: Enter non-existent email | C13: 1. Enter "http://localhost:5173/" to navigate to the website. (Top-right corner of the screen) 2. Guest user click the “Đăng nhập” button. 3. Guest user clicks on link "Quên mật khẩu?". 4. The system displays a form asking the user to enter their registered email address. 5. User enters an email that is not registered in the system (e.g., nanhnanh07@gmail.com). 6. Clicks the "Gửi email khôi phục" button. | D13: System displays message "Email không tồn tại hoặc chưa xác thực" | E13: 1.Server must be work 2..Account must be in system | F13: Passed | G13: 45978 | H13: TuanCM | I13: Passed | J13: 45980 | K13: TuanCM | L13: Passed | M13: 45981 | N13: TuanCM

Sheet Logout
A2: Feature | B2: Logout | R2: Passed
A3: Test requirement | B3: <Brief description about requirements which are tested in this sheet> | R3: Failed
A4: Number of TCs | B4: =COUNTA(A12:A995) -> 3 | R4: Pending
A5: Testing Round | B5: Passed | C5: Failed | D5: Pending | E5: N/A | R5: N/A
A6: Round 1 | B6: =COUNTIF($F10:$F993,B5) -> 3 | C6: =COUNTIF($F10:$F993,C5) -> 0 | D6: =COUNTIF($F10:$F993,D5) -> 0 | E6: =COUNTIF($F10:$F993,E5) -> 0
A7: Round 2 | B7: =COUNTIF($F10:$F993,B5) -> 3 | C7: =COUNTIF($F10:$F993,C5) -> 0 | D7: =COUNTIF($F10:$F993,D5) -> 0 | E7: =COUNTIF($F10:$F993,E5) -> 0
A8: Round 3 | B8: =COUNTIF($F10:$F993,B5) -> 3 | C8: =COUNTIF($F10:$F993,C5) -> 0 | D8: =COUNTIF($F10:$F993,D5) -> 0 | E8: =COUNTIF($F10:$F993,E5) -> 0
A10: Test Case ID | B10: Test Case Description | C10: Test Case Procedure | D10: Expected Results | E10: Pre-conditions | F10: Round 1 | G10: Test date | H10: Tester | I10: Round 2 | J10: Test date | K10: Tester | L10: Round 3 | M10: Test date | N10: Tester | O10: Note
A11: Logout
A12: [Logout- 1] | B12: Check if the user can successfully log out from the website. | C12: 1. Enter "http://localhost:5173/" to go to website 2. Guest user login with system. 3.Click the avatar icon in top-right of website. 4. Click "Đăng xuất" button. | D12: - User is logged out and redirect home page. No user-specific data is accessible until the user logs in again. - Show message "Đăng xuất thành công!" | E12: 1.Server must be work 2..Account must be in system | F12: Passed | G12: 45978 | H12: TuanCM | I12: Passed | J12: 45980 | K12: TuanCM | L12: Passed | M12: 45981 | N12: TuanCM
A13: [Logout- 2] | B13: Check if a logged-out user is restricted from accessing pages meant for logged-in users. | C13: 1. Enter "http://localhost:5173/" to go to website 2. Guest user login with system. 3.Click the avatar icon in top-right of website. 4. Click "Đăng xuất" button. 5. After logging out, try to directly access the restricted page by entering the URL in the browser. | D13: The system redirects the user to the homepage when they try to access the restricted page. | E13: 1.Server must be work 2..Account must be in system | F13: Passed | G13: 45978 | H13: TuanCM | I13: Passed | J13: 45980 | K13: TuanCM | L13: Passed | M13: 45981 | N13: TuanCM
A14: [Logout- 3] | B14: Register to become a lecturer | C14: 1. Enter "http://localhost:5173/" to navigate to the website. (Top-right corner of the screen) 2. Guest user click the “Đăng ký” button. 3. The site displays the registration form. 4. Guest user select a registration role: “Student” or “Lecturer.” 5. Enter the following valid information: - Email: lecturer@gmail.com - Password: Lecturer@123 - RePassword: Lecturer@123 - Full Name: Nguyen Van A 6. Guest user click the “Đăng ký” button. 7. Guest user ou are redirected to the “Đăng nhập” screen. 8. The guest user logs into the system using the newly registered account. 9. The system redirects to the Lecturer Application submission page. 10. Enter the following valid information: - Chức danh: Senior - Chuyên môn: Web Developer - Mô tả kinh nghiệm: 5 years as a software engineer - Tải lên CV: PDF file - Tải lên ảnh bằng cấp: Image file (e.g., .png, .jpg...). 11. The user clicks the “Nộp đơn ứng tuyển” button. | D14: System displays message "Nộp CV thành công! Chúng tôi sẽ liên hệ với bạn sớm." | E14: 1.Server must be work 2..Account must be in system | F14: Passed | G14: 45978 | H14: TuanCM | I14: Passed | J14: 45980 | K14: TuanCM | L14: Passed | M14: 45981 | N14: TuanCM

Sheet View user profile
A2: Feature | B2: View user profile | R2: Passed
A3: Test requirement | B3: <Brief description about requirements which are tested in this sheet> | R3: Failed
A4: Number of TCs | B4: =COUNTA(A12:A865) -> 1 | R4: Pending
A5: Testing Round | B5: Passed | C5: Failed | D5: Pending | E5: N/A | R5: N/A
A6: Round 1 | B6: =COUNTIF($F10:$F863,B5) -> 1 | C6: =COUNTIF($F10:$F863,C5) -> 0 | D6: =COUNTIF($F10:$F863,D5) -> 0 | E6: =COUNTIF($F10:$F863,E5) -> 0
A7: Round 2 | B7: =COUNTIF($F10:$F863,B5) -> 1 | C7: =COUNTIF($F10:$F863,C5) -> 0 | D7: =COUNTIF($F10:$F863,D5) -> 0 | E7: =COUNTIF($F10:$F863,E5) -> 0
A8: Round 3 | B8: =COUNTIF($F10:$F863,B5) -> 1 | C8: =COUNTIF($F10:$F863,C5) -> 0 | D8: =COUNTIF($F10:$F863,D5) -> 0 | E8: =COUNTIF($F10:$F863,E5) -> 0
A10: Test Case ID | B10: Test Case Description | C10: Test Case Procedure | D10: Expected Results | E10: Pre-conditions | F10: Round 1 | G10: Test date | H10: Tester | I10: Round 2 | J10: Test date | K10: Tester | L10: Round 3 | M10: Test date | N10: Tester | O10: Note
A11: View user profile
A12: <View Profile - 1> | B12: Test the UI display of the User Profile | C12: 1. Login system 2. Click on user profile icon right of dashboard screen | D12: 1.Home Screen is displayed 2.The UI display of the User Detail is displayed include : "Name", "Phone", "Email", "Sex", "Password", "Old Password", "New Password", Save Change Button Logout | E12: 1. Device with Internet connection | F12: Passed | G12: 45978 | H12: TuanCM | I12: Passed | J12: 45980 | K12: TuanCM | L12: Passed | M12: 45981 | N12: TuanCM

Sheet Update user profile
A2: Feature | B2: Update user profile | R2: Passed
A3: Test requirement | B3: <Brief description about requirements which are tested in this sheet> | R3: Failed
A4: Number of TCs | B4: =COUNTA(A12:A866) -> 2 | R4: Pending
A5: Testing Round | B5: Passed | C5: Failed | D5: Pending | E5: N/A | R5: N/A
A6: Round 1 | B6: =COUNTIF($F10:$F864,B5) -> 2 | C6: =COUNTIF($F10:$F864,C5) -> 0 | D6: =COUNTIF($F10:$F864,D5) -> 0 | E6: =COUNTIF($F10:$F864,E5) -> 0
A7: Round 2 | B7: =COUNTIF($F10:$F864,B5) -> 2 | C7: =COUNTIF($F10:$F864,C5) -> 0 | D7: =COUNTIF($F10:$F864,D5) -> 0 | E7: =COUNTIF($F10:$F864,E5) -> 0
A8: Round 3 | B8: =COUNTIF($F10:$F864,B5) -> 2 | C8: =COUNTIF($F10:$F864,C5) -> 0 | D8: =COUNTIF($F10:$F864,D5) -> 0 | E8: =COUNTIF($F10:$F864,E5) -> 0
A10: Test Case ID | B10: Test Case Description | C10: Test Case Procedure | D10: Expected Results | E10: Pre-conditions | F10: Round 1 | G10: Test date | H10: Tester | I10: Round 2 | J10: Test date | K10: Tester | L10: Round 3 | M10: Test date | N10: Tester | O10: Note
A11: Update user profile
A12: [Update user profile - 1] | B12: Update user profile with valid data | C12: 1. Navigate to "Thông tin cơ bản" tab 2. Update phone number to "0911178086" 3. Update name to "testgiaovien@gmail.com" 4. Update birthday to "12/12/2025" 5. Update biography field with "11111111" 6. Click "Lưu thay đổi" button | D12: - Profile is successfully updated - Success message displayed - Updated information reflects in sidebar - All fields retain new values | E12: - User is logged in - User has access to profile page | F12: Passed | G12: 45978 | H12: TuanCM | I12: Passed | J12: 45980 | K12: TuanCM | L12: Passed | M12: 45981 | N12: TuanCM
A13: [Update user profile - 2] | B13: Update profile with invalid phone number | C13: 1. Navigate to "Thông tin cơ bản" tab 2. Enter invalid phone number (e.g., "abc123") 3. Click "Lưu thay đổi" button | D13: - Validation error message appears - Profile is not updated - Invalid data is not saved to database | E13: - User is logged in - User has access to profile page | F13: Passed | G13: 45978 | H13: TuanCM | I13: Passed | J13: 45980 | K13: TuanCM | L13: Passed | M13: 45981 | N13: TuanCM

Sheet Change password
A2: Feature | B2: Change password | R2: Passed
A3: Test requirement | B3: <Brief description about requirements which are tested in this sheet> | R3: Failed
A4: Number of TCs | B4: =COUNTA(A12:A868) -> 4 | R4: Pending
A5: Testing Round | B5: Passed | C5: Failed | D5: Pending | E5: N/A | R5: N/A
A6: Round 1 | B6: =COUNTIF($F10:$F866,B5) -> 4 | C6: =COUNTIF($F10:$F866,C5) -> 0 | D6: =COUNTIF($F10:$F866,D5) -> 0 | E6: =COUNTIF($F10:$F866,E5) -> 0
A7: Round 2 | B7: =COUNTIF($F10:$F866,B5) -> 4 | C7: =COUNTIF($F10:$F866,C5) -> 0 | D7: =COUNTIF($F10:$F866,D5) -> 0 | E7: =COUNTIF($F10:$F866,E5) -> 0
A8: Round 3 | B8: =COUNTIF($F10:$F866,B5) -> 4 | C8: =COUNTIF($F10:$F866,C5) -> 0 | D8: =COUNTIF($F10:$F866,D5) -> 0 | E8: =COUNTIF($F10:$F866,E5) -> 0
A10: Test Case ID | B10: Test Case Description | C10: Test Case Procedure | D10: Expected Results | E10: Pre-conditions | F10: Round 1 | G10: Test date | H10: Tester | I10: Round 2 | J10: Test date | K10: Tester | L10: Round 3 | M10: Test date | N10: Tester | O10: Note
A11: Change password
A12: [Change password - 1] | B12: Update user profile with valid data | C12: 1. Navigate to "Đổi mật khẩu" tab 2. Enter current password in "Mật khẩu cũ" field 3. Enter new password (min 6 characters) in "Mật khẩu mới" field 4. Re-enter new password in "Xác nhận mật khẩu mới" field 5. Click "Cập nhật mật khẩu" button 6. Logout 7. Login with new password | D12: - Password updated successfully - Success message displayed - User can login with new password - Old password no longer works | E12: - User is logged in - User knows current password | F12: Passed | G12: 45978 | H12: TuanCM | I12: Passed | J12: 45980 | K12: TuanCM | L12: Passed | M12: 45981 | N12: TuanCM
A13: [Change password - 2] | B13: Change password with incorrect current password | C13: 1. Navigate to "Đổi mật khẩu" tab 2. Enter incorrect current password 3. Enter valid new password and confirmation 4. Click "Cập nhật mật khẩu" button | D13: - Error message displays: "Current password is incorrect" - Password is not changed - User can still login with old password | E13: - User is logged in | F13: Passed | G13: 45978 | H13: TuanCM | I13: Passed | J13: 45980 | K13: TuanCM | L13: Passed | M13: 45981 | N13: TuanCM
A14: [Change password - 3] | B14: Change password with mismatched confirmation | C14: 1. Navigate to "Đổi mật khẩu" tab 2. Enter correct current password 3. Enter new password in "Mật khẩu mới" 4. Enter different password in "Xác nhận mật khẩu mới" 5. Click "Cập nhật mật khẩu" button | D14: - Error message: "Passwords do not match" - Password is not changed - Form highlights mismatched fields | E14: - User is logged in | F14: Passed | G14: 45978 | H14: TuanCM | I14: Passed | J14: 45980 | K14: TuanCM | L14: Passed | M14: 45981 | N14: TuanCM
A15: [Change password - 4] | B15: Change password with less than 6 characters | C15: 1. Navigate to "Đổi mật khẩu" tab 2. Enter correct current password 3. Enter password with less than 6 characters (e.g., "12345") 4. Confirm the short password 5. Click "Cập nhật mật khẩu" button | D15: - Validation error: "Password must be at least 6 characters" - Password is not changed | E15: - User is logged in | F15: Passed | G15: 45978 | H15: TuanCM | I15: Passed | J15: 45980 | K15: TuanCM | L15: Passed | M15: 45981 | N15: TuanCM

Sheet View purchase history
A2: Feature | B2: View purchase history | R2: Passed
A3: Test requirement | B3: <Brief description about requirements which are tested in this sheet> | R3: Failed
A4: Number of TCs | B4: =COUNTA(A12:A866) -> 2 | R4: Pending
A5: Testing Round | B5: Passed | C5: Failed | D5: Pending | E5: N/A | R5: N/A
A6: Round 1 | B6: =COUNTIF($F10:$F864,B5) -> 2 | C6: =COUNTIF($F10:$F864,C5) -> 0 | D6: =COUNTIF($F10:$F864,D5) -> 0 | E6: =COUNTIF($F10:$F864,E5) -> 0
A7: Round 2 | B7: =COUNTIF($F10:$F864,B5) -> 2 | C7: =COUNTIF($F10:$F864,C5) -> 0 | D7: =COUNTIF($F10:$F864,D5) -> 0 | E7: =COUNTIF($F10:$F864,E5) -> 0
A8: Round 3 | B8: =COUNTIF($F10:$F864,B5) -> 2 | C8: =COUNTIF($F10:$F864,C5) -> 0 | D8: =COUNTIF($F10:$F864,D5) -> 0 | E8: =COUNTIF($F10:$F864,E5) -> 0
A10: Test Case ID | B10: Test Case Description | C10: Test Case Procedure | D10: Expected Results | E10: Pre-conditions | F10: Round 1 | G10: Test date | H10: Tester | I10: Round 2 | J10: Test date | K10: Tester | L10: Round 3 | M10: Test date | N10: Tester | O10: Note
A11: View purchase history
A12: [View purchase history - 1] | B12: View purchase history with multiple orders | C12: 1. Navigate to "Lịch Sử Mua Hàng" page 2. Verify page title "Lịch Sử Mua Hàng" displays 3. Verify subtitle "Xem lại các giao dịch và khoá học bạn đã mua" 4. Count number of orders displayed 5. Verify orders sorted by date (newest first) | D12: - All purchase orders display - Orders in chronological order - Each order shows date/time - Course count visible - Price and payment method shown | E12: - User is logged in - User has purchase history | F12: Passed | G12: 45978 | H12: TuanCM | I12: Passed | J12: 45980 | K12: TuanCM | L12: Passed | M12: 45981 | N12: TuanCM
A13: [View purchase history - 2] | B13: Expand order to view full details | C13: 1. Navigate to purchase history 2. Click on collapsed order (default state) 3. Verify order expands 4. Check "Thông tin giao dịch" section displays 5. Verify transaction time shown 6. Verify order code (Mã đơn hàng) displays 7. Verify "Tổng thanh toán" displays | D13: - Order expands smoothly with animation - Transaction info section visible - Order code complete - Total payment shows "10.000 đ" - Expand icon changes to collapse icon | E13: - User is logged in - User has purchases | F13: Passed | G13: 45978 | H13: TuanCM | I13: Passed | J13: 45980 | K13: TuanCM | L13: Passed | M13: 45981 | N13: TuanCM

Sheet View cart
A2: Feature | B2: View cart | R2: Passed
A3: Test requirement | B3: <Brief description about requirements which are tested in this sheet> | R3: Failed
A4: Number of TCs | B4: =COUNTA(A12:A866) -> 2 | R4: Pending
A5: Testing Round | B5: Passed | C5: Failed | D5: Pending | E5: N/A | R5: N/A
A6: Round 1 | B6: =COUNTIF($F10:$F864,B5) -> 2 | C6: =COUNTIF($F10:$F864,C5) -> 0 | D6: =COUNTIF($F10:$F864,D5) -> 0 | E6: =COUNTIF($F10:$F864,E5) -> 0
A7: Round 2 | B7: =COUNTIF($F10:$F864,B5) -> 2 | C7: =COUNTIF($F10:$F864,C5) -> 0 | D7: =COUNTIF($F10:$F864,D5) -> 0 | E7: =COUNTIF($F10:$F864,E5) -> 0
A8: Round 3 | B8: =COUNTIF($F10:$F864,B5) -> 2 | C8: =COUNTIF($F10:$F864,C5) -> 0 | D8: =COUNTIF($F10:$F864,D5) -> 0 | E8: =COUNTIF($F10:$F864,E5) -> 0
A10: Test Case ID | B10: Test Case Description | C10: Test Case Procedure | D10: Expected Results | E10: Pre-conditions | F10: Round 1 | G10: Test date | H10: Tester | I10: Round 2 | J10: Test date | K10: Tester | L10: Round 3 | M10: Test date | N10: Tester | O10: Note
A11: View cart
A12: [View cart - 1] | B12: View cart with multiple items | C12: 1. Add 3 different courses to cart 2. Navigate to cart page 3. Verify all items displayed 4. Verify total count shows "3 khóa học trong giỏ hàng" 5. Verify total price is sum of all items | D12: - All items listed separately - Each item shows complete info - Count accurate - Total calculation correct - Scrollable if needed | E12: - User is logged in - Multiple courses available | F12: Passed | G12: 45978 | H12: TuanCM | I12: Passed | J12: 45980 | K12: TuanCM | L12: Passed | M12: 45981 | N12: TuanCM
A13: [View cart - 1] | B13: View empty cart | C13: 1. Navigate to "Giỏ hàng" page 2. Verify empty state displays | D13: - Empty cart message shown - No items displayed - Suggestion to browse courses - Checkout button hidden/disabled - Cart badge shows "0" or hidden | E13: - User is logged in - Cart is empty | F13: Passed | G13: 45978 | H13: TuanCM | I13: Passed | J13: 45980 | K13: TuanCM | L13: Passed | M13: 45981 | N13: TuanCM

Sheet Add to cart
A2: Feature | B2: Add to cart | R2: Passed
A3: Test requirement | B3: <Brief description about requirements which are tested in this sheet> | R3: Failed
A4: Number of TCs | B4: =COUNTA(A12:A867) -> 3 | R4: Pending
A5: Testing Round | B5: Passed | C5: Failed | D5: Pending | E5: N/A | R5: N/A
A6: Round 1 | B6: =COUNTIF($F10:$F865,B5) -> 3 | C6: =COUNTIF($F10:$F865,C5) -> 0 | D6: =COUNTIF($F10:$F865,D5) -> 0 | E6: =COUNTIF($F10:$F865,E5) -> 0
A7: Round 2 | B7: =COUNTIF($F10:$F865,B5) -> 3 | C7: =COUNTIF($F10:$F865,C5) -> 0 | D7: =COUNTIF($F10:$F865,D5) -> 0 | E7: =COUNTIF($F10:$F865,E5) -> 0
A8: Round 3 | B8: =COUNTIF($F10:$F865,B5) -> 3 | C8: =COUNTIF($F10:$F865,C5) -> 0 | D8: =COUNTIF($F10:$F865,D5) -> 0 | E8: =COUNTIF($F10:$F865,E5) -> 0
A10: Test Case ID | B10: Test Case Description | C10: Test Case Procedure | D10: Expected Results | E10: Pre-conditions | F10: Round 1 | G10: Test date | H10: Tester | I10: Round 2 | J10: Test date | K10: Tester | L10: Round 3 | M10: Test date | N10: Tester | O10: Note
A11: Add to cart
A12: [Add to cart - 1] | B12: Add course to cart from course page | C12: 1. Navigate to course detail page 2. Verify "Add to Cart" button visible 3. Click "Add to Cart" button 4. Verify success notification 5. Check cart icon badge increments 6. Navigate to cart to verify item added | D12: - Success message: "Course added to cart" - Cart badge increments by 1 - Item appears in cart - Course details correct in cart - Price matches course price | E12: - User is logged in - Course not in cart - Course not already owned | F12: Passed | G12: 45978 | H12: TuanCM | I12: Passed | J12: 45980 | K12: TuanCM | L12: Passed | M12: 45981 | N12: TuanCM
A13: [Add to cart - 2] | B13: Add multiple different courses to cart | C13: 1. Add first course to cart 2. Navigate to different course 3. Add second course to cart 4. Navigate to third course 5. Add third course to cart 6. Verify cart count shows "3" | D13: - Each course added successfully - Cart badge increments each time - All courses visible in cart - No duplicates - Total price = sum of all courses | E13: - User is logged in - Multiple courses available - Courses not owned | F13: Passed | G13: 45978 | H13: TuanCM | I13: Passed | J13: 45980 | K13: TuanCM | L13: Passed | M13: 45981 | N13: TuanCM
A14: [Add to cart - 3] | B14: Attempt to add already owned course | C14: 1. Navigate to course user already purchased 2. Verify "Add to Cart" button status 3. Attempt to add to cart | D14: - Button shows disabled - Course cannot be added - Cart not modified | E14: - User is logged in - User owns the course | F14: Passed | G14: 45978 | H14: TuanCM | I14: Passed | J14: 45980 | K14: TuanCM | L14: Passed | M14: 45981 | N14: TuanCM

Sheet Remove item from cart
A2: Feature | B2: Remove item from cart | R2: Passed
A3: Test requirement | B3: <Brief description about requirements which are tested in this sheet> | R3: Failed
A4: Number of TCs | B4: =COUNTA(A12:A866) -> 2 | R4: Pending
A5: Testing Round | B5: Passed | C5: Failed | D5: Pending | E5: N/A | R5: N/A
A6: Round 1 | B6: =COUNTIF($F10:$F864,B5) -> 2 | C6: =COUNTIF($F10:$F864,C5) -> 0 | D6: =COUNTIF($F10:$F864,D5) -> 0 | E6: =COUNTIF($F10:$F864,E5) -> 0
A7: Round 2 | B7: =COUNTIF($F10:$F864,B5) -> 2 | C7: =COUNTIF($F10:$F864,C5) -> 0 | D7: =COUNTIF($F10:$F864,D5) -> 0 | E7: =COUNTIF($F10:$F864,E5) -> 0
A8: Round 3 | B8: =COUNTIF($F10:$F864,B5) -> 2 | C8: =COUNTIF($F10:$F864,C5) -> 0 | D8: =COUNTIF($F10:$F864,D5) -> 0 | E8: =COUNTIF($F10:$F864,E5) -> 0
A10: Test Case ID | B10: Test Case Description | C10: Test Case Procedure | D10: Expected Results | E10: Pre-conditions | F10: Round 1 | G10: Test date | H10: Tester | I10: Round 2 | J10: Test date | K10: Tester | L10: Round 3 | M10: Test date | N10: Tester | O10: Note
A11: Remove item from cart
A12: [Remove item from cart - 1] | B12: Remove single item from cart | C12: 1. Navigate to cart with 1 item 2. Click "Xóa" button on course 3. Confirm removal if prompted 4. Verify item removed | D12: - Confirmation dialog appears - Item removed from cart - Cart badge decrements to "0" - Total price updates to "0 đ" - Empty cart message displays | E12: - User is logged in - Cart has 1 item | F12: Passed | G12: 45978 | H12: TuanCM | I12: Passed | J12: 45980 | K12: TuanCM | L12: Passed | M12: 45981 | N12: TuanCM
A13: [Remove item from cart - 1] | B13: Remove last item in cart | C13: 1. Navigate to cart with 1 item 2. Click "Xóa" button 3. Confirm removal 4. Verify cart becomes empty | D13: - Item removed - Cart badge shows "0" | E13: - User is logged in - Cart has exactly 1 item | F13: Passed | G13: 45978 | H13: TuanCM | I13: Passed | J13: 45980 | K13: TuanCM | L13: Passed | M13: 45981 | N13: TuanCM

Sheet Add course
A2: Feature | B2: Add course | R2: Passed
A3: Test requirement | B3: <Brief description about requirements which are tested in this sheet> | R3: Failed
A4: Number of TCs | B4: =COUNTA(A12:A866) -> 2 | R4: Pending
A5: Testing Round | B5: Passed | C5: Failed | D5: Pending | E5: N/A | R5: N/A
A6: Round 1 | B6: =COUNTIF($F10:$F864,B5) -> 2 | C6: =COUNTIF($F10:$F864,C5) -> 0 | D6: =COUNTIF($F10:$F864,D5) -> 0 | E6: =COUNTIF($F10:$F864,E5) -> 0
A7: Round 2 | B7: =COUNTIF($F10:$F864,B5) -> 2 | C7: =COUNTIF($F10:$F864,C5) -> 0 | D7: =COUNTIF($F10:$F864,D5) -> 0 | E7: =COUNTIF($F10:$F864,E5) -> 0
A8: Round 3 | B8: =COUNTIF($F10:$F864,B5) -> 2 | C8: =COUNTIF($F10:$F864,C5) -> 0 | D8: =COUNTIF($F10:$F864,D5) -> 0 | E8: =COUNTIF($F10:$F864,E5) -> 0
A10: Test Case ID | B10: Test Case Description | C10: Test Case Procedure | D10: Expected Results | E10: Pre-conditions | F10: Round 1 | G10: Test date | H10: Tester | I10: Round 2 | J10: Test date | K10: Tester | L10: Round 3 | M10: Test date | N10: Tester | O10: Note
A11: Add course
A12: [Add course - 1] | B12: Create course with all required fields | C12: 1. Click "Tạo khóa học mới" button 2. Enter course name: "React Advanced Patterns" in "Tên khóa học" field 3. Enter description in "Mô tả khóa học" field 4. Select category from "Danh mục" dropdown 5. Select subcategory from "Danh mục con" dropdown 6. Toggle "AI hỗ trợ học viên" if needed 7. Upload course image via "Chọn ảnh" 8. Click "Tạo khóa học" button | D12: - Course created successfully - Success notification displayed - Modal closes - New course appears in course list with "Nháp" (Draft) status - Course saved in database - Creator can see the course in list | E12: - User is logged in - User has permissions | F12: Passed | G12: 45978 | H12: TuanCM | I12: Passed | J12: 45980 | K12: TuanCM | L12: Passed | M12: 45981 | N12: TuanCM
A13: [Add course - 2] | B13: Create course with missing required fields | C13: 1. Click "Tạo khóa học mới" button 2. Enter course name 3. Leave "Mô tả khóa học" field empty (required field marked with *) 4. Fill other fields 5. Click "Tạo khóa học" button | D13: - Validation error displays - Description field highlighted - Error message shown - Form not submitted - Modal remains open | E13: - User is logged in - User has permissions | F13: Passed | G13: 45978 | H13: TuanCM | I13: Passed | J13: 45980 | K13: TuanCM | L13: Passed | M13: 45981 | N13: TuanCM

Sheet Hide course
A2: Feature | B2: Hide course | R2: Passed
A3: Test requirement | B3: <Brief description about requirements which are tested in this sheet> | R3: Failed
A4: Number of TCs | B4: =COUNTA(A12:A865) -> 1 | R4: Pending
A5: Testing Round | B5: Passed | C5: Failed | D5: Pending | E5: N/A | R5: N/A
A6: Round 1 | B6: =COUNTIF($F10:$F863,B5) -> 1 | C6: =COUNTIF($F10:$F863,C5) -> 0 | D6: =COUNTIF($F10:$F863,D5) -> 0 | E6: =COUNTIF($F10:$F863,E5) -> 0
A7: Round 2 | B7: =COUNTIF($F10:$F863,B5) -> 1 | C7: =COUNTIF($F10:$F863,C5) -> 0 | D7: =COUNTIF($F10:$F863,D5) -> 0 | E7: =COUNTIF($F10:$F863,E5) -> 0
A8: Round 3 | B8: =COUNTIF($F10:$F863,B5) -> 1 | C8: =COUNTIF($F10:$F863,C5) -> 0 | D8: =COUNTIF($F10:$F863,D5) -> 0 | E8: =COUNTIF($F10:$F863,E5) -> 0
A10: Test Case ID | B10: Test Case Description | C10: Test Case Procedure | D10: Expected Results | E10: Pre-conditions | F10: Round 1 | G10: Test date | H10: Tester | I10: Round 2 | J10: Test date | K10: Tester | L10: Round 3 | M10: Test date | N10: Tester | O10: Note
A11: Hide course
A12: [Hide course - 1] | B12: Hide a published course | C12: 1. Navigate to course list 2. Locate published course "Khoá học test 12" 3. Click hide button (eye-slash icon in red) 4. Confirm action if prompted 5. Verify course hidden | D12: - Confirmation dialog appears - Course status changes from "Xuất bản" to "Đã ẩn" - Status badge updates - Course moves to "Đã ẩn" tab - "Đã xuất bản" count decreases by 1 (29 → 28) - "Đã ẩn" count increases by 1 (7 → 8) | E12: - User is logged in - User has permissions | F12: Passed | G12: 45978 | H12: TuanCM | I12: Passed | J12: 45980 | K12: TuanCM | L12: Passed | M12: 45981 | N12: TuanCM

Sheet Update course - general
A2: Feature | B2: Update course | R2: Passed
A3: Test requirement | B3: <Brief description about requirements which are tested in this sheet> | R3: Failed
A4: Number of TCs | B4: =COUNTA(A12:A873) -> 9 | R4: Pending
A5: Testing Round | B5: Passed | C5: Failed | D5: Pending | E5: N/A | R5: N/A
A6: Round 1 | B6: =COUNTIF($F10:$F871,B5) -> 9 | C6: =COUNTIF($F10:$F871,C5) -> 0 | D6: =COUNTIF($F10:$F871,D5) -> 0 | E6: =COUNTIF($F10:$F871,E5) -> 0
A7: Round 2 | B7: =COUNTIF($F10:$F871,B5) -> 9 | C7: =COUNTIF($F10:$F871,C5) -> 0 | D7: =COUNTIF($F10:$F871,D5) -> 0 | E7: =COUNTIF($F10:$F871,E5) -> 0
A8: Round 3 | B8: =COUNTIF($F10:$F871,B5) -> 9 | C8: =COUNTIF($F10:$F871,C5) -> 0 | D8: =COUNTIF($F10:$F871,D5) -> 0 | E8: =COUNTIF($F10:$F871,E5) -> 0
A10: Test Case ID | B10: Test Case Description | C10: Test Case Procedure | D10: Expected Results | E10: Pre-conditions | F10: Round 1 | G10: Test date | H10: Tester | I10: Round 2 | J10: Test date | K10: Tester | L10: Round 3 | M10: Test date | N10: Tester | O10: Note
A11: Update course
A12: [Update course - 1] | B12: View course basic information form fields | C12: 1. Navigate to course edit page 2. Verify all fields display with current values | D12: - All fields are filled - All fields editable | E12: - User is logged in - Course exists - On edit page | F12: Passed | G12: 45978 | H12: TuanCM | I12: Passed | J12: 45980 | K12: TuanCM | L12: Passed | M12: 45981 | N12: TuanCM
A13: [Update course - 2] | B13: Update multiple fields simultaneously | C13: 1. Navigate to course edit page 2. Update title to "New Course Title" 3. Update description to "New detailed description" 4. Change category 5. Change parent category 6. Upload new image 7. Click "Lưu thay đổi" button | D13: - All fields accept changes - All updates save successfully - Success notification displays - All changes persist in database - Course list reflects all changes - No data loss | E13: - User is logged in - Course exists - On edit page | F13: Passed | G13: 45978 | H13: TuanCM | I13: Passed | J13: 45980 | K13: TuanCM | L13: Passed | M13: 45981 | N13: TuanCM
A14: [Update course - 3] | B14: View current course price | C14: 1. Navigate to pricing page 2. Locate current price section 3. Verify display | D14: - "Giá hiện tại" section displays with green background - Shows "100.000đ" - Dollar icon in green circle - Note text: "Học viên cần thanh toán để đăng ký" - Price formatted with đ currency symbol - Prominent display | E14: - User is logged in - On pricing page - Course has price set | F14: Passed | G14: 45978 | H14: TuanCM | I14: Passed | J14: 45980 | K14: TuanCM | L14: Passed | M14: 45981 | N14: TuanCM
A15: [Update course - 4] | B15: View price type options (Free vs Paid) | C15: 1. Navigate to pricing page 2. Locate "Loại giá" section 3. Verify radio button options | D15: - Two radio button options visible - Option 1: "Miễn phí" with subtitle "Không yêu cầu thanh toán" - Option 2: "Trả phí" with subtitle "Yêu cầu thanh toán" - "Trả phí" currently selected - Radio buttons functional - Can toggle between options | E15: - User is logged in - On pricing page | F15: Passed | G15: 45978 | H15: TuanCM | I15: Passed | J15: 45980 | K15: TuanCM | L15: Passed | M15: 45981 | N15: TuanCM
A16: [Update course - 5] | B16: Change course from paid to free | C16: 1. Navigate to pricing page 2. Current price is "100.000đ" (paid) 3. Select "Miễn phí" radio button 4. Click "Lưu thay đổi" button 5. Verify update | D16: - "Miễn phí" radio button selected - Price field disabled or hidden - Success notification displays - Course price updates to 0đ in database - Current price section updates to show "Miễn phí" - Students can enroll without payment - Changes persist | E16: - User is logged in - On pricing page - Course currently paid | F16: Passed | G16: 45978 | H16: TuanCM | I16: Passed | J16: 45980 | K16: TuanCM | L16: Passed | M16: 45981 | N16: TuanCM
A17: [Update course - 6] | B17: Change course from free to paid | C17: 1. Navigate to pricing page with free course 2. Select "Trả phí" radio button 3. Enter price in "Giá khóa học (VNĐ)" field 4. Click "Lưu thay đổi" button 5. Verify update | D17: - "Trả phí" radio button selected - Price input field becomes enabled - Can enter price value - Success notification displays - Course requires payment - Current price updates - Students must pay to enroll - Changes persist | E17: - User is logged in - On pricing page - Course currently free | F17: Passed | G17: 45978 | H17: TuanCM | I17: Passed | J17: 45980 | K17: TuanCM | L17: Passed | M17: 45981 | N17: TuanCM
A18: [Update course - 7] | B18: Update course price value | C18: 1. Navigate to pricing page 2. Ensure "Trả phí" selected 3. Click in "Giá khóa học (VNĐ)" field (currently 100000) 4. Clear value and enter "150000" 5. Click "Lưu thay đổi" button 6. Verify price updates | D18: - Price field accepts numeric input - Old value cleared - New value "150000" entered - Display shows "Giá hiện thi: 100.000đ" updates to "150. 000đ" - Success notification - Price updated in database - Course shows new price - Changes persist | E18: - User is logged in - On pricing page - "Trả phí" selected | F18: Passed | G18: 45978 | H18: TuanCM | I18: Passed | J18: 45980 | K18: TuanCM | L18: Passed | M18: 45981 | N18: TuanCM
A19: [Update course - 8] | B19: Enter invalid price (negative number) | C19: 1. Navigate to pricing page 2. Select "Trả phí" 3. Enter negative price "-50000" 4. Click "Lưu thay đổi" button | D19: - Validation error displays - Error message: "Price must be positive" or similar - Field highlighted - Form not submitted - Price not updated - Clear error feedback | E19: - User is logged in - On pricing page | F19: Passed | G19: 45978 | H19: TuanCM | I19: Passed | J19: 45980 | K19: TuanCM | L19: Passed | M19: 45981 | N19: TuanCM
A20: [Update course - 9] | B20: Enter invalid price (non-numeric) | C20: 1. Navigate to pricing page 2. Select "Trả phí" 3. Enter text "abc" or special chars 4. Attempt to save | D20: - Validation error displays - Field may prevent non-numeric input - Form not submitted - Price not updated | E20: - User is logged in - On pricing page | F20: Passed | G20: 45978 | H20: TuanCM | I20: Passed | J20: 45980 | K20: TuanCM | L20: Passed | M20: 45981 | N20: TuanCM

Sheet View sections
A2: Feature | B2: View sections | R2: Passed
A3: Test requirement | B3: <Brief description about requirements which are tested in this sheet> | R3: Failed
A4: Number of TCs | B4: =COUNTA(A12:A866) -> 2 | R4: Pending
A5: Testing Round | B5: Passed | C5: Failed | D5: Pending | E5: N/A | R5: N/A
A6: Round 1 | B6: =COUNTIF($F10:$F864,B5) -> 2 | C6: =COUNTIF($F10:$F864,C5) -> 0 | D6: =COUNTIF($F10:$F864,D5) -> 0 | E6: =COUNTIF($F10:$F864,E5) -> 0
A7: Round 2 | B7: =COUNTIF($F10:$F864,B5) -> 2 | C7: =COUNTIF($F10:$F864,C5) -> 0 | D7: =COUNTIF($F10:$F864,D5) -> 0 | E7: =COUNTIF($F10:$F864,E5) -> 0
A8: Round 3 | B8: =COUNTIF($F10:$F864,B5) -> 2 | C8: =COUNTIF($F10:$F864,C5) -> 0 | D8: =COUNTIF($F10:$F864,D5) -> 0 | E8: =COUNTIF($F10:$F864,E5) -> 0
A10: Test Case ID | B10: Test Case Description | C10: Test Case Procedure | D10: Expected Results | E10: Pre-conditions | F10: Round 1 | G10: Test date | H10: Tester | I10: Round 2 | J10: Test date | K10: Tester | L10: Round 3 | M10: Test date | N10: Tester | O10: Note
A11: View sections
A12: [View sections - 1] | B12: View section list with multiple sections | C12: 1. Navigate to "Nội dung khóa học" page 2. Verify sections display 3. Check section count | D12: - Two sections display: "Chương 1" and "Chương 2" - Section count at top shows "2 chương" - Each section has numbered circle (1, 2) - Section names visible - Item counts show "4 mục" and "2 mục" - Edit, delete, and expand icons visible on each section | E12: - User is logged in - On sections page | F12: Passed | G12: 45978 | H12: TuanCM | I12: Passed | J12: 45980 | K12: TuanCM | L12: Passed | M12: 45981 | N12: TuanCM
A13: [View sections - 2] | B13: View empty sections page | C13: 1. Navigate to sections page for course with no sections 2. Verify empty state | D13: - Empty state message displays - Message suggests creating first section - "Chương mới" button visible - Section count shows "0 chương" | E13: - User is logged in - On sections page | F13: Passed | G13: 45978 | H13: TuanCM | I13: Passed | J13: 45980 | K13: TuanCM | L13: Passed | M13: 45981 | N13: TuanCM

Sheet Add sections
A2: Feature | B2: Add sections | R2: Passed
A3: Test requirement | B3: <Brief description about requirements which are tested in this sheet> | R3: Failed
A4: Number of TCs | B4: =COUNTA(A12:A868) -> 4 | R4: Pending
A5: Testing Round | B5: Passed | C5: Failed | D5: Pending | E5: N/A | R5: N/A
A6: Round 1 | B6: =COUNTIF($F10:$F866,B5) -> 4 | C6: =COUNTIF($F10:$F866,C5) -> 0 | D6: =COUNTIF($F10:$F866,D5) -> 0 | E6: =COUNTIF($F10:$F866,E5) -> 0
A7: Round 2 | B7: =COUNTIF($F10:$F866,B5) -> 4 | C7: =COUNTIF($F10:$F866,C5) -> 0 | D7: =COUNTIF($F10:$F866,D5) -> 0 | E7: =COUNTIF($F10:$F866,E5) -> 0
A8: Round 3 | B8: =COUNTIF($F10:$F866,B5) -> 4 | C8: =COUNTIF($F10:$F866,C5) -> 0 | D8: =COUNTIF($F10:$F866,D5) -> 0 | E8: =COUNTIF($F10:$F866,E5) -> 0
A10: Test Case ID | B10: Test Case Description | C10: Test Case Procedure | D10: Expected Results | E10: Pre-conditions | F10: Round 1 | G10: Test date | H10: Tester | I10: Round 2 | J10: Test date | K10: Tester | L10: Round 3 | M10: Test date | N10: Tester | O10: Note
A11: Add sections
A12: [Add sections - 1] | B12: Create section with title and description | C12: 1. Click "Chương mới" button 2. Enter title "Advanced Topics" 3. Enter description "This chapter covers advanced programming concepts" 4. Click "Lưu" button 5. Verify section created | D12: - Both fields accept input - Success notification displays - Section created successfully - Title and description saved - New section appears in list - Description accessible when expanded - Changes persist | E12: - User is logged in - On sections page | F12: Passed | G12: 45978 | H12: TuanCM | I12: Passed | J12: 45980 | K12: TuanCM | L12: Passed | M12: 45981 | N12: TuanCM
A13: [Add sections - 2] | B13: Create section with empty title | C13: 1. Click "Chương mới" button 2. Leave title field empty 3. Enter or leave description empty 4. Click "Lưu" button | D13: - Validation error displays - Error message near title field - Title field highlighted - Form not submitted - Section not created - Must enter title to proceed | E13: - User is logged in - Add section form open | F13: Passed | G13: 45978 | H13: TuanCM | I13: Passed | J13: 45980 | K13: TuanCM | L13: Passed | M13: 45981 | N13: TuanCM
A14: [Add sections - 3] | B14: Create section with very long title | C14: 1. Click "Chương mới" button 2. Enter very long title (e.g., 500 characters) 3. Click "Lưu" button | D14: - Validation error | E14: - User is logged in - Add section form open | F14: Passed | G14: 45978 | H14: TuanCM | I14: Passed | J14: 45980 | K14: TuanCM | L14: Passed | M14: 45981 | N14: TuanCM
A15: [Add sections - 4] | B15: Create section with special characters in title | C15: 1. Click "Chương mới" button 2. Enter title with special characters "Chương 1: C++ & Data Structures!" 3. Click "Lưu" button | D15: - Special characters accepted - No encoding issues - Section created successfully - Title displays correctly - No system errors | E15: - User is logged in - Add section form open | F15: Passed | G15: 45978 | H15: TuanCM | I15: Passed | J15: 45980 | K15: TuanCM | L15: Passed | M15: 45981 | N15: TuanCM

Sheet Update sections
A2: Feature | B2: Update sections | R2: Passed
A3: Test requirement | B3: <Brief description about requirements which are tested in this sheet> | R3: Failed
A4: Number of TCs | B4: =COUNTA(A12:A867) -> 3 | R4: Pending
A5: Testing Round | B5: Passed | C5: Failed | D5: Pending | E5: N/A | R5: N/A
A6: Round 1 | B6: =COUNTIF($F10:$F865,B5) -> 3 | C6: =COUNTIF($F10:$F865,C5) -> 0 | D6: =COUNTIF($F10:$F865,D5) -> 0 | E6: =COUNTIF($F10:$F865,E5) -> 0
A7: Round 2 | B7: =COUNTIF($F10:$F865,B5) -> 3 | C7: =COUNTIF($F10:$F865,C5) -> 0 | D7: =COUNTIF($F10:$F865,D5) -> 0 | E7: =COUNTIF($F10:$F865,E5) -> 0
A8: Round 3 | B8: =COUNTIF($F10:$F865,B5) -> 3 | C8: =COUNTIF($F10:$F865,C5) -> 0 | D8: =COUNTIF($F10:$F865,D5) -> 0 | E8: =COUNTIF($F10:$F865,E5) -> 0
A10: Test Case ID | B10: Test Case Description | C10: Test Case Procedure | D10: Expected Results | E10: Pre-conditions | F10: Round 1 | G10: Test date | H10: Tester | I10: Round 2 | J10: Test date | K10: Tester | L10: Round 3 | M10: Test date | N10: Tester | O10: Note
A11: Update sections
A12: [Update sections - 1] | B12: Update section title | C12: 1. Click edit on section 2. Change title from "Chương 1" to "Chương 1: Introduction to Programming" 3. Click "Lưu" button 4. Verify update | D12: - Title field accepts new text - Success notification displays - Section title updates in list - Shows new title "Chương 1: Introduction to Programming" - Database updated - Changes persist after refresh | E12: - User is logged in - On sections page | F12: Passed | G12: 45978 | H12: TuanCM | I12: Passed | J12: 45980 | K12: TuanCM | L12: Passed | M12: 45981 | N12: TuanCM
A13: [Update sections - 2] | B13: Update section description | C13: 1. Click edit on section 2. Click in description field 3. Enter or update description text 4. Click "Lưu" button 5. Verify update | D13: - Description field accepts input - Multi-line text supported - Success notification displays - Description updated - Can view updated description when section expanded - Changes persist | E13: - User is logged in - On sections page | F13: Passed | G13: 45978 | H13: TuanCM | I13: Passed | J13: 45980 | K13: TuanCM | L13: Passed | M13: 45981 | N13: TuanCM
A14: [Update sections - 3] | B14: Update both title and description | C14: 1. Click edit on section 2. Change title to "Updated Chapter 1" 3. Change description to "New description text" 4. Click "Lưu" button 5. Verify both updates | D14: - Both fields accept changes - Success notification displays - Both title and description updated - Changes reflected in list - Database updated for both - Changes persist | E14: - User is logged in - On sections page | F14: Passed | G14: 45978 | H14: TuanCM | I14: Passed | J14: 45980 | K14: TuanCM | L14: Passed | M14: 45981 | N14: TuanCM

Sheet Delete sections
A2: Feature | B2: Delete sections | R2: Passed
A3: Test requirement | B3: <Brief description about requirements which are tested in this sheet> | R3: Failed
A4: Number of TCs | B4: =COUNTA(A12:A865) -> 1 | R4: Pending
A5: Testing Round | B5: Passed | C5: Failed | D5: Pending | E5: N/A | R5: N/A
A6: Round 1 | B6: =COUNTIF($F10:$F863,B5) -> 1 | C6: =COUNTIF($F10:$F863,C5) -> 0 | D6: =COUNTIF($F10:$F863,D5) -> 0 | E6: =COUNTIF($F10:$F863,E5) -> 0
A7: Round 2 | B7: =COUNTIF($F10:$F863,B5) -> 1 | C7: =COUNTIF($F10:$F863,C5) -> 0 | D7: =COUNTIF($F10:$F863,D5) -> 0 | E7: =COUNTIF($F10:$F863,E5) -> 0
A8: Round 3 | B8: =COUNTIF($F10:$F863,B5) -> 1 | C8: =COUNTIF($F10:$F863,C5) -> 0 | D8: =COUNTIF($F10:$F863,D5) -> 0 | E8: =COUNTIF($F10:$F863,E5) -> 0
A10: Test Case ID | B10: Test Case Description | C10: Test Case Procedure | D10: Expected Results | E10: Pre-conditions | F10: Round 1 | G10: Test date | H10: Tester | I10: Round 2 | J10: Test date | K10: Tester | L10: Round 3 | M10: Test date | N10: Tester | O10: Note
A11: Delete sections
A12: [Delete sections - 1] | B12: Confirm section deletion (section with items) | C12: 1. Locate section "Chương 1" with "4 mục" 2. Click delete button 3. Confirmation dialog appears 4. Confirm deletion 5. Verify deletion | D12: Warning about deleting items - Success notification displays - Section removed from list - All 4 items also deleted - Section deleted from database - Section count decrements - Other sections unaffected - Permanent deletion | E12: - User is logged in - On sections page | F12: Passed | G12: 45978 | H12: TuanCM | I12: Passed | J12: 45980 | K12: TuanCM | L12: Passed | M12: 45981 | N12: TuanCM

Sheet Create lesson
A2: Feature | B2: Create lesson | R2: Passed
A3: Test requirement | B3: <Brief description about requirements which are tested in this sheet> | R3: Failed
A4: Number of TCs | B4: =COUNTA(A12:A870) -> 6 | R4: Pending
A5: Testing Round | B5: Passed | C5: Failed | D5: Pending | E5: N/A | R5: N/A
A6: Round 1 | B6: =COUNTIF($F10:$F868,B5) -> 6 | C6: =COUNTIF($F10:$F868,C5) -> 0 | D6: =COUNTIF($F10:$F868,D5) -> 0 | E6: =COUNTIF($F10:$F868,E5) -> 0
A7: Round 2 | B7: =COUNTIF($F10:$F868,B5) -> 6 | C7: =COUNTIF($F10:$F868,C5) -> 0 | D7: =COUNTIF($F10:$F868,D5) -> 0 | E7: =COUNTIF($F10:$F868,E5) -> 0
A8: Round 3 | B8: =COUNTIF($F10:$F868,B5) -> 6 | C8: =COUNTIF($F10:$F868,C5) -> 0 | D8: =COUNTIF($F10:$F868,D5) -> 0 | E8: =COUNTIF($F10:$F868,E5) -> 0
A10: Test Case ID | B10: Test Case Description | C10: Test Case Procedure | D10: Expected Results | E10: Pre-conditions | F10: Round 1 | G10: Test date | H10: Tester | I10: Round 2 | J10: Test date | K10: Tester | L10: Round 3 | M10: Test date | N10: Tester | O10: Note
A11: Create lesson
A12: [Create lesson - 1] | B12: Create video lesson with all required fields | C12: 1. Navigate to "Khung chương trình" 2. Expand a section 3. Click "+ Thêm nội dung" button 4. Select "Bài học" card 5. Enter "Tên bài học": "Video Lesson 1: Introduction" 6. Enter "Mô tả bài học": "Introduction to the course" 7. Keep "Video" selected in content type 8. Upload valid video file 9. Click "Thêm bài học" button | D12: - Form validates successfully - Video lesson is created - Success toast notification appears - Lesson appears in section list - Section item count increases by 1 - Video lesson shows video icon - Lesson is visible in expanded section - Changes persist after refresh | E12: - User is logged in - At least one section exists - Valid video file available | F12: Passed | G12: 45978 | H12: TuanCM | I12: Passed | J12: 45980 | K12: TuanCM | L12: Passed | M12: 45981 | N12: TuanCM
A13: [Create lesson - 2] | B13: Create multiple video lessons in same section | C13: 1. Create first video lesson: "Lesson 1" 2. Verify lesson 1 created 3. Click "+ Thêm nội dung" again 4. Create second video lesson: "Lesson 2" 5. Verify lesson 2 created 6. Check section item count | D13: - First video lesson created successfully - Can immediately add another lesson - Second video lesson created successfully - Both lessons visible in section list - Lessons appear in order of creation - Section item count shows "2 mục" - Both lessons accessible - No data conflicts | E13: - User is logged in - Section exists - Multiple video files available | F13: Passed | G13: 45978 | H13: TuanCM | I13: Passed | J13: 45980 | K13: TuanCM | L13: Passed | M13: 45981 | N13: TuanCM
A14: [Create lesson - 3] | B14: Create text lesson with formatted content | C14: 1. Navigate to section 2. Click "+ Thêm nội dung" 3. Select "Bài học" card 4. Enter "Tên bài học": "Text Lesson 1: Theory" 5. Enter "Mô tả bài học": "Theoretical concepts" 6. Select "Văn bản" in content type dropdown 7. In rich text editor, enter formatted content 8. Click "Thêm bài học" button | D14: - Text lesson created successfully - All formatting preserved - Success notification appears - Lesson appears in section with document icon - Rich content displays correctly - Section item count increases - Formatting visible in lesson view - Changes persist | E14: - User is logged in - Section exists | F14: Passed | G14: 45978 | H14: TuanCM | I14: Passed | J14: 45980 | K14: TuanCM | L14: Passed | M14: 45981 | N14: TuanCM
A15: [Create lesson - 4] | B15: Create quiz with all required fields | C15: 1. Navigate to section 2. Click "+ Thêm nội dung" 3. Select "Quiz" card 4. Enter "Tên quiz": "Quiz 1: Introduction Test" 5. Enter "Mô tả quiz": "Test your understanding" 6. Enter "Điểm đạt (%)": "70" 7. Enter "Thời gian (phút)": "30" 8. Click "Tạo quiz" button | D15: - Form validates successfully - Quiz is created - Success notification appears - Quiz appears in section with question icon - Section item count increases - Quiz shows quiz icon and details - Pass score: 70% - Time limit: 30 minutes - Changes persist | E15: - User is logged in - Section exists | F15: Passed | G15: 45978 | H15: TuanCM | I15: Passed | J15: 45980 | K15: TuanCM | L15: Passed | M15: 45981 | N15: TuanCM
A16: [Create lesson - 5] | B16: Create multiple quizzes in same section | C16: 1. Create first quiz: "Quiz 1: Basics" with 70% pass, 20 min 2. Verify quiz 1 created 3. Click "+ Thêm nội dung" again 4. Create second quiz: "Quiz 2: Advanced" with 80% pass, 30 min 5. Verify quiz 2 created 6. Check section item count | D16: - First quiz created successfully - Can immediately add another quiz - Second quiz created successfully - Both quizzes visible in section - Each quiz has correct settings - Section item count shows "2 mục" - Both quizzes accessible - No data conflicts | E16: - User is logged in - Section exists | F16: Passed | G16: 45978 | H16: TuanCM | I16: Passed | J16: 45980 | K16: TuanCM | L16: Passed | M16: 45981 | N16: TuanCM
A17: [Create lesson - 6] | B17: Create video, text, and quiz in same section | C17: 1. Navigate to section 2. Add video lesson: "Lesson 1: Video Introduction" 3. Verify video lesson created 4. Add text lesson: "Lesson 2: Reading Material" 5. Verify text lesson created 6. Add quiz: "Quiz 1: Chapter Test" 7. Verify quiz created 8. Check section item count | D17: - All three content types created successfully - Each appears with appropriate icon - Section item count shows "3 mục" - Items appear in order of creation - All items accessible - Mix of content types works correctly - Section displays all items properly - Changes persist | E17: - User is logged in - Section exists | F17: Passed | G17: 45978 | H17: TuanCM | I17: Passed | J17: 45980 | K17: TuanCM | L17: Passed | M17: 45981 | N17: TuanCM

Sheet Create question
A2: Feature | B2: Create question | R2: Passed
A3: Test requirement | B3: <Brief description about requirements which are tested in this sheet> | R3: Failed
A4: Number of TCs | B4: =COUNTA(A12:A868) -> 4 | R4: Pending
A5: Testing Round | B5: Passed | C5: Failed | D5: Pending | E5: N/A | R5: N/A
A6: Round 1 | B6: =COUNTIF($F10:$F866,B5) -> 4 | C6: =COUNTIF($F10:$F866,C5) -> 0 | D6: =COUNTIF($F10:$F866,D5) -> 0 | E6: =COUNTIF($F10:$F866,E5) -> 0
A7: Round 2 | B7: =COUNTIF($F10:$F866,B5) -> 4 | C7: =COUNTIF($F10:$F866,C5) -> 0 | D7: =COUNTIF($F10:$F866,D5) -> 0 | E7: =COUNTIF($F10:$F866,E5) -> 0
A8: Round 3 | B8: =COUNTIF($F10:$F866,B5) -> 4 | C8: =COUNTIF($F10:$F866,C5) -> 0 | D8: =COUNTIF($F10:$F866,D5) -> 0 | E8: =COUNTIF($F10:$F866,E5) -> 0
A10: Test Case ID | B10: Test Case Description | C10: Test Case Procedure | D10: Expected Results | E10: Pre-conditions | F10: Round 1 | G10: Test date | H10: Tester | I10: Round 2 | J10: Test date | K10: Tester | L10: Round 3 | M10: Test date | N10: Tester | O10: Note
A11: Create question
A12: [Create question - 1] | B12: Create single choice question | C12: 1. Enter question text in editor: "What is 2+2?" 2. Select "Một đáp án đúng" 3. Enter answer A: "3" 4. Enter answer B: "4" 5. Select answer B as correct (mark checkbox) 6. Click "Tạo câu hỏi" | D12: - Form validates successfully - Question is created - Success toast appears: "Thêm câu hỏi thành công" - Second toast: "Câu hỏi đã được thêm!" - Form closes - Question appears in question bank - Question is automatically added to current quiz - Quiz question count increases | E12: - All required fields filled correctly - At least 2 answers provided - Exactly 1 answer marked correct | F12: Passed | G12: 45978 | H12: TuanCM | I12: Passed | J12: 45980 | K12: TuanCM | L12: Passed | M12: 45981 | N12: TuanCM
A13: [Create question - 2] | B13: Create multiple choice question | C13: 1. Open manual creation form 2. Enter question text: "Which are programming languages?" 3. Select "Nhiều đáp án đúng" 4. Enter answer A: "Python" 5. Enter answer B: "HTML" 6. Enter answer C: "Java" 7. Enter answer D: "CSS" 8. Mark A and C as correct 9. Click "Tạo câu hỏi" | D13: - Form validates successfully - Question is created - Success toast: "Thêm câu hỏi thành công" - Second toast: "Câu hỏi đã được thêm!" - Form closes - Question added to question bank - Question added to current quiz - Quiz count updates | E13: - Multiple choice with 2+ correct answers - All fields filled | F13: Passed | G13: 45978 | H13: TuanCM | I13: Passed | J13: 45980 | K13: TuanCM | L13: Passed | M13: 45981 | N13: TuanCM
A14: [Create question- 3] | B14: Create multiple choice question with all correct answers | C14: 1. Open manual creation form 2. Enter question text: "Select all valid options" 3. Select "Nhiều đáp án đúng" 4. Enter 4 answers 5. Mark all 4 answers as correct 6. Click "Tạo câu hỏi" | D14: - Form validates successfully - Question created with all answers correct - Success notifications appear - Question added to bank and quiz - All answers marked as correct - Quiz count updates - Edge case handled correctly | E14: - Form open - All answers marked correct | F14: Passed | G14: 45978 | H14: TuanCM | I14: Passed | J14: 45980 | K14: TuanCM | L14: Passed | M14: 45981 | N14: TuanCM
A15: [Create question- 4] | B15: Create quiz with all required fields | C15: 1. Navigate to section 2. Click "+ Thêm nội dung" 3. Select "Quiz" card 4. Enter "Tên quiz": "Quiz 1: Introduction Test" 5. Enter "Mô tả quiz": "Test your understanding" 6. Enter "Điểm đạt (%)": "70" 7. Enter "Thời gian (phút)": "30" 8. Click "Tạo quiz" button | D15: - Form validates successfully - Quiz is created - Success notification appears - Quiz appears in section with question icon - Section item count increases - Quiz shows quiz icon and details - Pass score: 70% - Time limit: 30 minutes - Changes persist | E15: - User is logged in - Section exists | F15: Passed | G15: 45978 | H15: TuanCM | I15: Passed | J15: 45980 | K15: TuanCM | L15: Passed | M15: 45981 | N15: TuanCM

Sheet Add question from bank
A2: Feature | B2: Add question from bank | R2: Passed
A3: Test requirement | B3: <Brief description about requirements which are tested in this sheet> | R3: Failed
A4: Number of TCs | B4: =COUNTA(A12:A866) -> 2 | R4: Pending
A5: Testing Round | B5: Passed | C5: Failed | D5: Pending | E5: N/A | R5: N/A
A6: Round 1 | B6: =COUNTIF($F10:$F864,B5) -> 2 | C6: =COUNTIF($F10:$F864,C5) -> 0 | D6: =COUNTIF($F10:$F864,D5) -> 0 | E6: =COUNTIF($F10:$F864,E5) -> 0
A7: Round 2 | B7: =COUNTIF($F10:$F864,B5) -> 2 | C7: =COUNTIF($F10:$F864,C5) -> 0 | D7: =COUNTIF($F10:$F864,D5) -> 0 | E7: =COUNTIF($F10:$F864,E5) -> 0
A8: Round 3 | B8: =COUNTIF($F10:$F864,B5) -> 2 | C8: =COUNTIF($F10:$F864,C5) -> 0 | D8: =COUNTIF($F10:$F864,D5) -> 0 | E8: =COUNTIF($F10:$F864,E5) -> 0
A10: Test Case ID | B10: Test Case Description | C10: Test Case Procedure | D10: Expected Results | E10: Pre-conditions | F10: Round 1 | G10: Test date | H10: Tester | I10: Round 2 | J10: Test date | K10: Tester | L10: Round 3 | M10: Test date | N10: Tester | O10: Note
A11: Add question from bank
A12: [Add question - 1] | B12: Add existing question from bank to quiz | C12: 1. Open question bank drawer 2. Browse existing questions 3. Locate question not yet in current quiz 4. Click "+ Add" or similar button on question card 5. Verify addition | D12: - Question can be selected from bank - Add action executes - Success notification appears - Question appears in current quiz - Quiz question count increases - Question remains in bank | E12: - Question bank has questions - Questions not already in current quiz | F12: Passed | G12: 45978 | H12: TuanCM | I12: Passed | J12: 45980 | K12: TuanCM | L12: Passed | M12: 45981 | N12: TuanCM
A13: [Add question - 2] | B13: Add multiple questions from bank to quiz | C13: 1. Open question bank drawer 2. Select first question and add to quiz 3. Select second question and add to quiz 4. Select third question and add to quiz 5. Verify all additions | D13: - All three questions added successfully - Success notification for each - All questions appear in quiz - Quiz count increases by 3 - Questions remain in bank - Order preserved or as expected | E13: - Question bank has multiple questions | F13: Passed | G13: 45978 | H13: TuanCM | I13: Passed | J13: 45980 | K13: TuanCM | L13: Passed | M13: 45981 | N13: TuanCM

Sheet View question
A2: Feature | B2: View question | R2: Passed
A3: Test requirement | B3: <Brief description about requirements which are tested in this sheet> | R3: Failed
A4: Number of TCs | B4: =COUNTA(A12:A866) -> 2 | R4: Pending
A5: Testing Round | B5: Passed | C5: Failed | D5: Pending | E5: N/A | R5: N/A
A6: Round 1 | B6: =COUNTIF($F10:$F864,B5) -> 2 | C6: =COUNTIF($F10:$F864,C5) -> 0 | D6: =COUNTIF($F10:$F864,D5) -> 0 | E6: =COUNTIF($F10:$F864,E5) -> 0
A7: Round 2 | B7: =COUNTIF($F10:$F864,B5) -> 2 | C7: =COUNTIF($F10:$F864,C5) -> 0 | D7: =COUNTIF($F10:$F864,D5) -> 0 | E7: =COUNTIF($F10:$F864,E5) -> 0
A8: Round 3 | B8: =COUNTIF($F10:$F864,B5) -> 2 | C8: =COUNTIF($F10:$F864,C5) -> 0 | D8: =COUNTIF($F10:$F864,D5) -> 0 | E8: =COUNTIF($F10:$F864,E5) -> 0
A10: Test Case ID | B10: Test Case Description | C10: Test Case Procedure | D10: Expected Results | E10: Pre-conditions | F10: Round 1 | G10: Test date | H10: Tester | I10: Round 2 | J10: Test date | K10: Tester | L10: Round 3 | M10: Test date | N10: Tester | O10: Note
A11: View question
A12: [View question - 1] | B12: View question details in quiz | C12: 1. Have quiz with added questions 2. Locate a question card 3. Click eye icon | D12: - View/preview modal opens - Shows complete question details - Displays question text - Shows all answers - Indicates correct answer(s) - Can close preview - Read-only view - No editing in view mode | E12: - Questions exist in quiz | F12: Passed | G12: 45978 | H12: TuanCM | I12: Passed | J12: 45980 | K12: TuanCM | L12: Passed | M12: 45981 | N12: TuanCM
A13: [View question - 2] | B13: View multiple questions in quiz list | C13: 1. Navigate to quiz with multiple questions 2. Observe quiz question list 3. Verify all questions display | D13: - All questions visible in list - Questions in order - Count matches actual number | E13: - Quiz has multiple questions | F13: Passed | G13: 45978 | H13: TuanCM | I13: Passed | J13: 45980 | K13: TuanCM | L13: Passed | M13: 45981 | N13: TuanCM

Sheet Edit question
A2: Feature | B2: Edit question | R2: Passed
A3: Test requirement | B3: <Brief description about requirements which are tested in this sheet> | R3: Failed
A4: Number of TCs | B4: =COUNTA(A12:A867) -> 3 | R4: Pending
A5: Testing Round | B5: Passed | C5: Failed | D5: Pending | E5: N/A | R5: N/A
A6: Round 1 | B6: =COUNTIF($F10:$F865,B5) -> 3 | C6: =COUNTIF($F10:$F865,C5) -> 0 | D6: =COUNTIF($F10:$F865,D5) -> 0 | E6: =COUNTIF($F10:$F865,E5) -> 0
A7: Round 2 | B7: =COUNTIF($F10:$F865,B5) -> 3 | C7: =COUNTIF($F10:$F865,C5) -> 0 | D7: =COUNTIF($F10:$F865,D5) -> 0 | E7: =COUNTIF($F10:$F865,E5) -> 0
A8: Round 3 | B8: =COUNTIF($F10:$F865,B5) -> 3 | C8: =COUNTIF($F10:$F865,C5) -> 0 | D8: =COUNTIF($F10:$F865,D5) -> 0 | E8: =COUNTIF($F10:$F865,E5) -> 0
A10: Test Case ID | B10: Test Case Description | C10: Test Case Procedure | D10: Expected Results | E10: Pre-conditions | F10: Round 1 | G10: Test date | H10: Tester | I10: Round 2 | J10: Test date | K10: Tester | L10: Round 3 | M10: Test date | N10: Tester | O10: Note
A11: Edit question
A12: [Edit question - 1] | B12: Edit question from quiz | C12: 1. Have quiz with questions 2. Click edit (pencil) icon on a question 3. Modify question text to "Updated question?" 4. Modify one answer 5. Save changes | D12: - Edit form opens with question data - All fields are editable - Question text can be modified - Answers can be modified - Correct answer selection can be changed - Changes can be saved - Success notification appears - Updated question displays in quiz - Changes reflect in question bank - Quiz functions correctly with updated question | E12: - Questions exist in quiz | F12: Passed | G12: 45978 | H12: TuanCM | I12: Passed | J12: 45980 | K12: TuanCM | L12: Passed | M12: 45981 | N12: TuanCM
A13: [Edit question - 2] | B13: Change correct answer in single choice question | C13: 1. Locate single choice question 2. Click edit icon 3. Change correct answer from A to B 4. Save changes | D13: - Edit form opens - Can deselect current correct answer - Can select different correct answer - Only one answer can be correct - Changes save successfully - Success notification - Updated correct answer reflected - Previous answer no longer correct | E13: - Single choice question exists in quiz | F13: Passed | G13: 45978 | H13: TuanCM | I13: Passed | J13: 45980 | K13: TuanCM | L13: Passed | M13: 45981 | N13: TuanCM
A14: [Edit question - 3] | B14: Edit multiple choice question correct answers | C14: 1. Locate multiple choice question 2. Click edit icon 3. Change correct answers 4. Save changes | D14: - Edit form opens - Can modify correct answer selections - Can add more correct answers - Can remove correct answers - At least 2 correct answers required - Changes save successfully - Success notification - Updated correct answers reflected | E14: - Multiple choice question exists in quiz | F14: Passed | G14: 45978 | H14: TuanCM | I14: Passed | J14: 45980 | K14: TuanCM | L14: Passed | M14: 45981 | N14: TuanCM

Sheet Delete question
A2: Feature | B2: Delete question | R2: Passed
A3: Test requirement | B3: <Brief description about requirements which are tested in this sheet> | R3: Failed
A4: Number of TCs | B4: =COUNTA(A12:A866) -> 2 | R4: Pending
A5: Testing Round | B5: Passed | C5: Failed | D5: Pending | E5: N/A | R5: N/A
A6: Round 1 | B6: =COUNTIF($F10:$F864,B5) -> 2 | C6: =COUNTIF($F10:$F864,C5) -> 0 | D6: =COUNTIF($F10:$F864,D5) -> 0 | E6: =COUNTIF($F10:$F864,E5) -> 0
A7: Round 2 | B7: =COUNTIF($F10:$F864,B5) -> 2 | C7: =COUNTIF($F10:$F864,C5) -> 0 | D7: =COUNTIF($F10:$F864,D5) -> 0 | E7: =COUNTIF($F10:$F864,E5) -> 0
A8: Round 3 | B8: =COUNTIF($F10:$F864,B5) -> 2 | C8: =COUNTIF($F10:$F864,C5) -> 0 | D8: =COUNTIF($F10:$F864,D5) -> 0 | E8: =COUNTIF($F10:$F864,E5) -> 0
A10: Test Case ID | B10: Test Case Description | C10: Test Case Procedure | D10: Expected Results | E10: Pre-conditions | F10: Round 1 | G10: Test date | H10: Tester | I10: Round 2 | J10: Test date | K10: Tester | L10: Round 3 | M10: Test date | N10: Tester | O10: Note
A11: Delete question
A12: [Delete question - 1] | B12: Delete question from quiz | C12: 1. Have quiz with questions 2. Click delete (trash) icon on a question 3. Confirm deletion in dialog | D12: - Confirmation dialog appears - Warning about removing question - Dialog shows question details - Can confirm or cancel - Question removed from quiz after confirmation - Quiz question count decreases - Success notification appears - Question may remain in question bank - Quiz still functional | E12: - Questions exist in quiz | F12: Passed | G12: 45978 | H12: TuanCM | I12: Passed | J12: 45980 | K12: TuanCM | L12: Passed | M12: 45981 | N12: TuanCM
A13: [Delete question - 2] | B13: Delete multiple questions from quiz | C13: 1. Have quiz with 5 questions 2. Delete first question and confirm 3. Delete second question and confirm 4. Verify deletions | D13: - Each deletion succeeds - Confirmation for each - Success notification for each - Question count decreases: 5 → 4 → 3 - Remaining questions intact - Quiz functional with fewer questions | E13: - Quiz has multiple questions | F13: Passed | G13: 45978 | H13: TuanCM | I13: Passed | J13: 45980 | K13: TuanCM | L13: Passed | M13: 45981 | N13: TuanCM

Sheet Enroll course
A2: Feature | B2: Enroll course | R2: Passed
A3: Test requirement | B3: <Brief description about requirements which are tested in this sheet> | R3: Failed
A4: Number of TCs | B4: =COUNTA(A12:A867) -> 3 | R4: Pending
A5: Testing Round | B5: Passed | C5: Failed | D5: Pending | E5: N/A | R5: N/A
A6: Round 1 | B6: =COUNTIF($F10:$F865,B5) -> 3 | C6: =COUNTIF($F10:$F865,C5) -> 0 | D6: =COUNTIF($F10:$F865,D5) -> 0 | E6: =COUNTIF($F10:$F865,E5) -> 0
A7: Round 2 | B7: =COUNTIF($F10:$F865,B5) -> 3 | C7: =COUNTIF($F10:$F865,C5) -> 0 | D7: =COUNTIF($F10:$F865,D5) -> 0 | E7: =COUNTIF($F10:$F865,E5) -> 0
A8: Round 3 | B8: =COUNTIF($F10:$F865,B5) -> 3 | C8: =COUNTIF($F10:$F865,C5) -> 0 | D8: =COUNTIF($F10:$F865,D5) -> 0 | E8: =COUNTIF($F10:$F865,E5) -> 0
A10: Test Case ID | B10: Test Case Description | C10: Test Case Procedure | D10: Expected Results | E10: Pre-conditions | F10: Round 1 | G10: Test date | H10: Tester | I10: Round 2 | J10: Test date | K10: Tester | L10: Round 3 | M10: Test date | N10: Tester | O10: Note
A11: Enroll course
A12: [Enroll course - 1] | B12: Enroll in free course instantly | C12: 1. Login as Student 2. Navigate to free course detail page 3. Click "Đăng ký miễn phí" button 4. Verify enrollment status | D12: - Success message: Course enrolled successfully - Course appears in "My Courses" page - No payment required - Instant access granted - Student can start learning immediately | E12: - Student logged in - Course price = 0 - Course is published and approved | F12: Passed | G12: 45978 | H12: TuanCM | I12: Passed | J12: 45980 | K12: TuanCM | L12: Passed | M12: 45981 | N12: TuanCM
A13: [Enroll course - 2] | B13: System prevents buying already enrolled course | C13: 1. Login as Student 2. Navigate to already enrolled course 3. Check button state on course detail | D13: - "Học ngay" button displayed instead of "Mua ngay" - Add to cart button disabled - Clicking redirects to learning page - No duplicate enrollment possible | E13: - Student already enrolled in course | F13: Passed | G13: 45978 | H13: TuanCM | I13: Passed | J13: 45980 | K13: TuanCM | L13: Passed | M13: 45981 | N13: TuanCM
A14: [Enroll course - 3] | B14: Purchase single paid course via "Mua ngay" | C14: 1. Login as Student 2. Navigate to paid course detail 3. Click "Mua ngay" button 4. Wait for PayOS redirect 5. Complete payment on PayOS gateway 6. Return to platform | D14: - PayOS payment page opens - After successful payment: redirect to success page - Course enrolled automatically - Transaction recorded in payment history - Success notification appears - Course appears in "My Courses" | E14: - Valid PayOS configuration - Student has sufficient balance - Course price > 0 | F14: Passed | G14: 45978 | H14: TuanCM | I14: Passed | J14: 45980 | K14: TuanCM | L14: Passed | M14: 45981 | N14: TuanCM

Sheet Learning course
A2: Feature | B2: Learning course | R2: Passed
A3: Test requirement | B3: <Brief description about requirements which are tested in this sheet> | R3: Failed
A4: Number of TCs | B4: =COUNTA(A12:A867) -> 3 | R4: Pending
A5: Testing Round | B5: Passed | C5: Failed | D5: Pending | E5: N/A | R5: N/A
A6: Round 1 | B6: =COUNTIF($F10:$F865,B5) -> 3 | C6: =COUNTIF($F10:$F865,C5) -> 0 | D6: =COUNTIF($F10:$F865,D5) -> 0 | E6: =COUNTIF($F10:$F865,E5) -> 0
A7: Round 2 | B7: =COUNTIF($F10:$F865,B5) -> 3 | C7: =COUNTIF($F10:$F865,C5) -> 0 | D7: =COUNTIF($F10:$F865,D5) -> 0 | E7: =COUNTIF($F10:$F865,E5) -> 0
A8: Round 3 | B8: =COUNTIF($F10:$F865,B5) -> 3 | C8: =COUNTIF($F10:$F865,C5) -> 0 | D8: =COUNTIF($F10:$F865,D5) -> 0 | E8: =COUNTIF($F10:$F865,E5) -> 0
A10: Test Case ID | B10: Test Case Description | C10: Test Case Procedure | D10: Expected Results | E10: Pre-conditions | F10: Round 1 | G10: Test date | H10: Tester | I10: Round 2 | J10: Test date | K10: Tester | L10: Round 3 | M10: Test date | N10: Tester | O10: Note
A11: Learning course
A12: [Learning course - 1] | B12: Play video lesson | C12: 1. Navigate to course learning 2. Click on video lesson 3. Wait for video player to load 4. Play video 5. Verify tracking | D12: - Video player loads - Video plays without errors - Video controls available - Progress tracked - Can seek through video | E12: - Student enrolled | F12: Passed | G12: 45978 | H12: TuanCM | I12: Passed | J12: 45980 | K12: TuanCM | L12: Passed | M12: 45981 | N12: TuanCM
A13: [Learning course - 2] | B13: View text content lesson | C13: 1. Access text-based lesson 2. Scroll through content 3. Verify formatting | D13: - Content renders correctly - Text is readable and formatted - Lesson marked as viewed - Formatting preserved | E13: - Content exists | F13: Passed | G13: 45978 | H13: TuanCM | I13: Passed | J13: 45980 | K13: TuanCM | L13: Passed | M13: 45981 | N13: TuanCM
A14: [Learning course - 3] | B14: Take and pass quiz | C14: 1. Navigate to quiz item 2. Click "Start Quiz" 3. Answer all questions correctly 4. Submit quiz 5. View results | D14: - Timer displays and counts down - Can select answers - Submit enabled only when all answered - Score calculated: must pass passPercent threshold - Success message if passed - Quiz marked as completed | E14: - Student enrolled in course | F14: Passed | G14: 45978 | H14: TuanCM | I14: Passed | J14: 45980 | K14: TuanCM | L14: Passed | M14: 45981 | N14: TuanCM

Sheet Progress tracking
A2: Feature | B2: Progress tracking | R2: Passed
A3: Test requirement | B3: <Brief description about requirements which are tested in this sheet> | R3: Failed
A4: Number of TCs | B4: =COUNTA(A12:A865) -> 1 | R4: Pending
A5: Testing Round | B5: Passed | C5: Failed | D5: Pending | E5: N/A | R5: N/A
A6: Round 1 | B6: =COUNTIF($F10:$F863,B5) -> 1 | C6: =COUNTIF($F10:$F863,C5) -> 0 | D6: =COUNTIF($F10:$F863,D5) -> 0 | E6: =COUNTIF($F10:$F863,E5) -> 0
A7: Round 2 | B7: =COUNTIF($F10:$F863,B5) -> 1 | C7: =COUNTIF($F10:$F863,C5) -> 0 | D7: =COUNTIF($F10:$F863,D5) -> 0 | E7: =COUNTIF($F10:$F863,E5) -> 0
A8: Round 3 | B8: =COUNTIF($F10:$F863,B5) -> 1 | C8: =COUNTIF($F10:$F863,C5) -> 0 | D8: =COUNTIF($F10:$F863,D5) -> 0 | E8: =COUNTIF($F10:$F863,E5) -> 0
A10: Test Case ID | B10: Test Case Description | C10: Test Case Procedure | D10: Expected Results | E10: Pre-conditions | F10: Round 1 | G10: Test date | H10: Tester | I10: Round 2 | J10: Test date | K10: Tester | L10: Round 3 | M10: Test date | N10: Tester | O10: Note
A11: Progress tracking
A12: [Progress tracking - 1] | B12: Verify progress calculation accuracy | C12: 1. Start new course (0% progress) 2. Complete 1 lesson 3. Check progress percentage 4. Complete entire section 5. Verify progress updates | D12: - Progress bar updates in real-time - CourseSidebar shows percentage - Calculation accurate: completed/total items - Progress persists after refresh - Progress visible in "My Courses" list | E12: - Course has countable items - Student enrolled | F12: Passed | G12: 45978 | H12: TuanCM | I12: Passed | J12: 45980 | K12: TuanCM | L12: Passed | M12: 45981 | N12: TuanCM

Sheet Checkout
A2: Feature | B2: Checkout | R2: Passed
A3: Test requirement | B3: <Brief description about requirements which are tested in this sheet> | R3: Failed
A4: Number of TCs | B4: =COUNTA(A12:A869) -> 5 | R4: Pending
A5: Testing Round | B5: Passed | C5: Failed | D5: Pending | E5: N/A | R5: N/A
A6: Round 1 | B6: =COUNTIF($F10:$F867,B5) -> 5 | C6: =COUNTIF($F10:$F867,C5) -> 0 | D6: =COUNTIF($F10:$F867,D5) -> 0 | E6: =COUNTIF($F10:$F867,E5) -> 0
A7: Round 2 | B7: =COUNTIF($F10:$F867,B5) -> 5 | C7: =COUNTIF($F10:$F867,C5) -> 0 | D7: =COUNTIF($F10:$F867,D5) -> 0 | E7: =COUNTIF($F10:$F867,E5) -> 0
A8: Round 3 | B8: =COUNTIF($F10:$F867,B5) -> 5 | C8: =COUNTIF($F10:$F867,C5) -> 0 | D8: =COUNTIF($F10:$F867,D5) -> 0 | E8: =COUNTIF($F10:$F867,E5) -> 0
A10: Test Case ID | B10: Test Case Description | C10: Test Case Procedure | D10: Expected Results | E10: Pre-conditions | F10: Round 1 | G10: Test date | H10: Tester | I10: Round 2 | J10: Test date | K10: Tester | L10: Round 3 | M10: Test date | N10: Tester | O10: Note
A11: Checkout
A12: [Checkout- 1] | B12: Buy Course - Successful purchase via PayOS QR | C12: 1. Login as Student 2. Navigate to Course Detail page 3. Click "Mua ngay" (Buy Now) 4. Verify checkout screen displays correct course and price 5. Select PayOS payment method 6. Click "Thanh toán" (Pay) 7. QR code displayed 8. Scan QR with banking app 9. Complete payment in banking app 10. Return to platform | D12: - QR code generated and displayed - Payment instructions shown - After payment: "Thanh toán thành công!" message - Course appears in "My Courses" - Transaction record created with status "Success" - Enrollment confirmation shown - Can access course learning page - PayOS webhook received successfully | E12: - Student logged in - Course published and available - NOT already enrolled - PayOS configured correctly | F12: Passed | G12: 45978 | H12: TuanCM | I12: Passed | J12: 45980 | K12: TuanCM | L12: Passed | M12: 45981 | N12: TuanCM
A13: [Checkout- 2] | B13: Buy Course - Payment cancelled by user at PayOS | C13: 1. Login as Student 2. Click "Mua ngay" 3. Click "Thanh toán" 4. QR code displayed 5. User closes payment window/cancels payment 6. Return to platform without completing payment | D13: - Payment status: "Cancelled" - Course NOT enrolled - Message: "Thanh toán đã bị hủy. Bạn có thể thử lại." - Transaction record: Status "Cancelled" or "Failed" - "Thử lại" button displayed - Can retry payment - Cart preserved | E13: - Student logged in - Course in cart - Payment initiated but not completed | F13: Passed | G13: 45978 | H13: TuanCM | I13: Passed | J13: 45980 | K13: TuanCM | L13: Passed | M13: 45981 | N13: TuanCM
A14: [Checkout- 3] | B14: Buy Course - Already enrolled (duplicate prevention) | C14: 1. Login as Student (already enrolled in Course A) 2. Navigate to Course A detail page 3. Verify button state | D14: - "Mua ngay" button NOT displayed - Instead shows "Vào học ngay" (Start Learning) button - Message: "Bạn đã đăng ký khóa học này" - Cannot add to cart - Cannot purchase again - Clicking button redirects to learning page | E14: - Student logged in - Already enrolled in target course | F14: Passed | G14: 45978 | H14: TuanCM | I14: Passed | J14: 45980 | K14: TuanCM | L14: Passed | M14: 45981 | N14: TuanCM
A15: [Checkout- 4] | B15: Buy Course - PayOS gateway timeout/unavailable | C15: 1. Login as Student 2. Click "Mua ngay" 3. Click "Thanh toán" 4. Wait for response | D15: - Loading spinner: "Đang kết nối đến cổng thanh toán..."< - After timeout (30s): Error "Không thể kết nối đến cổng thanh toán PayOS. Vui lòng thử lại sau." - QR code NOT displayed - Payment NOT initiated - Retry button shown - Course NOT enrolled - Can retry when PayOS available | E15: - Student logged in - PayOS service unavailable - Sufficient funds in bank | F15: Passed | G15: 45978 | H15: TuanCM | I15: Passed | J15: 45980 | K15: TuanCM | L15: Passed | M15: 45981 | N15: TuanCM
A16: [Checkout- 5] | B16: Buy Course - Not logged in (guest user) | C16: 1. As guest (not logged in) 2. Navigate to Course Detail page 3. Click "Mua ngay" button | D16: - Redirected to Login page - Message: "Vui lòng đăng nhập để mua khóa học" - After login: Redirected back to Course Detail - Can add to cart and complete purchase after authentication - Cart preserved across login | E16: - User NOT logged in - Course available | F16: Passed | G16: 45978 | H16: TuanCM | I16: Passed | J16: 45980 | K16: TuanCM | L16: Passed | M16: 45981 | N16: TuanCM

Sheet Apply voucher
A2: Feature | B2: Apply voucher | R2: Passed
A3: Test requirement | B3: <Brief description about requirements which are tested in this sheet> | R3: Failed
A4: Number of TCs | B4: =COUNTA(A12:A869) -> 5 | R4: Pending
A5: Testing Round | B5: Passed | C5: Failed | D5: Pending | E5: N/A | R5: N/A
A6: Round 1 | B6: =COUNTIF($F10:$F867,B5) -> 5 | C6: =COUNTIF($F10:$F867,C5) -> 0 | D6: =COUNTIF($F10:$F867,D5) -> 0 | E6: =COUNTIF($F10:$F867,E5) -> 0
A7: Round 2 | B7: =COUNTIF($F10:$F867,B5) -> 5 | C7: =COUNTIF($F10:$F867,C5) -> 0 | D7: =COUNTIF($F10:$F867,D5) -> 0 | E7: =COUNTIF($F10:$F867,E5) -> 0
A8: Round 3 | B8: =COUNTIF($F10:$F867,B5) -> 5 | C8: =COUNTIF($F10:$F867,C5) -> 0 | D8: =COUNTIF($F10:$F867,D5) -> 0 | E8: =COUNTIF($F10:$F867,E5) -> 0
A10: Test Case ID | B10: Test Case Description | C10: Test Case Procedure | D10: Expected Results | E10: Pre-conditions | F10: Round 1 | G10: Test date | H10: Tester | I10: Round 2 | J10: Test date | K10: Tester | L10: Round 3 | M10: Test date | N10: Tester | O10: Note
A11: Apply voucher
A12: [Apply voucher 1] | B12: Apply Voucher - Valid code successfully applied | C12: 1. Login as Student 2. Add Course (200,000đ) to cart 3. Go to cart 4. Enter voucher code "SKILLUP20" (20% off) 5. Click "Áp dụng" | D12: - Success message: "Áp dụng mã giảm giá thành công!" - Total updated: 160,000đ - Voucher tag shown with "X" remove option - Cart counter unchanged | E12: - Student logged in - Valid voucher "SKILLUP20" exists - Voucher not expired - Course in cart | F12: Passed | G12: 45978 | H12: TuanCM | I12: Passed | J12: 45980 | K12: TuanCM | L12: Passed | M12: 45981 | N12: TuanCM
A13: [Apply voucher 2] | B13: Apply Voucher - Invalid code | C13: 1. Login as Student 2. Add course to cart 3. Go to cart 4. Enter voucher code "INVALID123" 5. Click "Áp dụng" | D13: - Error message: "Mã giảm giá không hợp lệ hoặc không tồn tại." - Voucher NOT applied - Total price unchanged - Input field shows error styling - Can try different code | E13: - Student logged in - Course in cart - Voucher code does not exist | F13: Passed | G13: 45978 | H13: TuanCM | I13: Passed | J13: 45980 | K13: TuanCM | L13: Passed | M13: 45981 | N13: TuanCM
A14: [Apply voucher 3] | B14: Apply Voucher - Already used (single-use restriction) | C14: 1. Login as Student 2. Note: Student previously used voucher "FIRSTBUY" 3. Add course to cart 4. Enter "FIRSTBUY" again 5. Click "Áp dụng" | D14: - Error message: "Bạn đã sử dụng mã giảm giá này rồi. Mỗi mã chỉ được dùng một lần." - Voucher NOT applied - Total unchanged - Student must use different voucher | E14: - Student logged in - Voucher usage limit: 1 per user - Student already used this voucher before | F14: Passed | G14: 45978 | H14: TuanCM | I14: Passed | J14: 45980 | K14: TuanCM | L14: Passed | M14: 45981 | N14: TuanCM
A15: [Apply voucher 4] | B15: Apply Voucher - Remove applied voucher | C15: 1. Login as Student 2. Add course (200,000đ) to cart 3. Apply valid voucher (discount: 40,000đ) 4. Verify total: 160,000đ 5. Click "X" on voucher tag to remove | D15: - Voucher removed - Discount row disappears - Total recalculated back to: 200,000đ - Can apply different voucher - No error message (normal action) | E15: - Student logged in - Voucher already applied to cart - Cart has items | F15: Passed | G15: 45978 | H15: TuanCM | I15: Passed | J15: 45980 | K15: TuanCM | L15: Passed | M15: 45981 | N15: TuanCM
A16: [Apply voucher 5] | B16: Apply Voucher - Multiple voucher attempt (only 1 allowed) | C16: 1. Login as Student 2. Add course to cart 3. Apply voucher "VOUCHER1" successfully 4. Attempt to apply another voucher "VOUCHER2" | D16: - Error message: "Chỉ có thể áp dụng một mã giảm giá cho mỗi đơn hàng. Vui lòng xóa mã hiện tại trước khi áp dụng mã mới." - Shows currently applied voucher: "Đang dùng: VOUCHER1" - Remove button provided - Second voucher NOT applied | E16: - Student logged in - One voucher already applied - System allows only 1 voucher per order | F16: Passed | G16: 45978 | H16: TuanCM | I16: Passed | J16: 45980 | K16: TuanCM | L16: Passed | M16: 45981 | N16: TuanCM

Sheet Take quiz
A2: Feature | B2: Take quiz | R2: Passed
A3: Test requirement | B3: <Brief description about requirements which are tested in this sheet> | R3: Failed
A4: Number of TCs | B4: =COUNTA(A12:A870) -> 6 | R4: Pending
A5: Testing Round | B5: Passed | C5: Failed | D5: Pending | E5: N/A | R5: N/A
A6: Round 1 | B6: =COUNTIF($F10:$F868,B5) -> 6 | C6: =COUNTIF($F10:$F868,C5) -> 0 | D6: =COUNTIF($F10:$F868,D5) -> 0 | E6: =COUNTIF($F10:$F868,E5) -> 0
A7: Round 2 | B7: =COUNTIF($F10:$F868,B5) -> 6 | C7: =COUNTIF($F10:$F868,C5) -> 0 | D7: =COUNTIF($F10:$F868,D5) -> 0 | E7: =COUNTIF($F10:$F868,E5) -> 0
A8: Round 3 | B8: =COUNTIF($F10:$F868,B5) -> 6 | C8: =COUNTIF($F10:$F868,C5) -> 0 | D8: =COUNTIF($F10:$F868,D5) -> 0 | E8: =COUNTIF($F10:$F868,E5) -> 0
A10: Test Case ID | B10: Test Case Description | C10: Test Case Procedure | D10: Expected Results | E10: Pre-conditions | F10: Round 1 | G10: Test date | H10: Tester | I10: Round 2 | J10: Test date | K10: Tester | L10: Round 3 | M10: Test date | N10: Tester | O10: Note
A11: Take quiz
A12: [Take quiz 1] | B12: Take Quiz - Complete and submit successfully | C12: 1. Login as Student 2. Navigate to enrolled course 3. Open quiz section 4. Click "Bắt đầu làm bài" 5. Answer all questions 6. Click "Nộp bài" | D12: - Quiz loads correctly - Timer starts (if timed) - Can select/change answers - Submit confirmation dialog appears - After confirm: "Nộp bài thành công!" - Redirected to results page - Attempt recorded | E12: - Student logged in - Enrolled in course - Quiz published and available - Attempts remaining > 0 | F12: Passed | G12: 45978 | H12: TuanCM | I12: Passed | J12: 45980 | K12: TuanCM | L12: Passed | M12: 45981 | N12: TuanCM
A13: [Take quiz 2] | B13: Take Quiz - Timer expires (auto-submit) | C13: 1. Login as Student 2. Start quiz with 5-minute timer 3. Answer some questions 4. Wait for timer to reach 0:00 5. Observe auto-submit behavior | D13: - Timer countdown visible - Warning at 1 minute remaining - At 0:00: Auto-submit triggered - Message: "Hết giờ làm bài. Bài làm đã được nộp tự động." - Cannot continue answering - Redirected to results - Partial answers saved | E13: - Student logged in - Quiz has time limit configured - Student enrolled | F13: Passed | G13: 45978 | H13: TuanCM | I13: Passed | J13: 45980 | K13: TuanCM | L13: Passed | M13: 45981 | N13: TuanCM
A14: [Take quiz 3] | B14: Take Quiz - Browser refresh during quiz (state preserved) | C14: 1. Login as Student 2. Start quiz 3. Answer 3 questions 4. Refresh browser (F5) 5. Verify quiz state | D14: - After refresh: Quiz reloads - Previously selected answers preserved - Timer continues from where it was (not reset) - Question navigation position maintained - Message: "Bài làm của bạn đã được lưu." - Can continue quiz normally | E14: - Student logged in - Quiz in progress | F14: Passed | G14: 45978 | H14: TuanCM | I14: Passed | J14: 45980 | K14: TuanCM | L14: Passed | M14: 45981 | N14: TuanCM
A15: [Take quiz 4] | B15: Take Quiz - Session expires during quiz | C15: 1. Login as Student 2. Start quiz 3. Wait for session to expire (or manually clear token) 4. Try to submit or navigate | D15: - Toast: "Phiên đăng nhập đã hết hạn. Vui lòng đăng nhập lại." - Quiz answers auto-saved (if possible) - Redirected to login - After re-login: Option to resume quiz - Answers restored if saved | E15: - Student logged in - Quiz in progress | F15: Passed | G15: 45978 | H15: TuanCM | I15: Passed | J15: 45980 | K15: TuanCM | L15: Passed | M15: 45981 | N15: TuanCM
A16: [Take quiz 5] | B16: Apply Voucher - Multiple voucher attempt (only 1 allowed) | C16: 1. Login as Student 2. Add course to cart 3. Apply voucher "VOUCHER1" successfully 4. Attempt to apply another voucher "VOUCHER2" | D16: - Error message: "Chỉ có thể áp dụng một mã giảm giá cho mỗi đơn hàng. Vui lòng xóa mã hiện tại trước khi áp dụng mã mới." - Shows currently applied voucher: "Đang dùng: VOUCHER1" - Remove button provided - Second voucher NOT applied | E16: - Student logged in - One voucher already applied - System allows only 1 voucher per order | F16: Passed | G16: 45978 | H16: TuanCM | I16: Passed | J16: 45980 | K16: TuanCM | L16: Passed | M16: 45981 | N16: TuanCM
A17: [Take quiz 6] | B17: Take Quiz - Not enrolled (unauthorized access) | C17: 1. Login as Student 2. NOT enrolled in Course A 3. Try to access Course A quiz via direct URL manipulation | D17: - Access blocked - Redirected to course detail page - Cannot bypass enrollment requirement | E17: - Student logged in - NOT enrolled in target course - Quiz exists | F17: Passed | G17: 45978 | H17: TuanCM | I17: Passed | J17: 45980 | K17: TuanCM | L17: Passed | M17: 45981 | N17: TuanCM

Sheet View result
A2: Feature | B2: View result | R2: Passed
A3: Test requirement | B3: <Brief description about requirements which are tested in this sheet> | R3: Failed
A4: Number of TCs | B4: =COUNTA(A12:A870) -> 6 | R4: Pending
A5: Testing Round | B5: Passed | C5: Failed | D5: Pending | E5: N/A | R5: N/A
A6: Round 1 | B6: =COUNTIF($F10:$F868,B5) -> 6 | C6: =COUNTIF($F10:$F868,C5) -> 0 | D6: =COUNTIF($F10:$F868,D5) -> 0 | E6: =COUNTIF($F10:$F868,E5) -> 0
A7: Round 2 | B7: =COUNTIF($F10:$F868,B5) -> 6 | C7: =COUNTIF($F10:$F868,C5) -> 0 | D7: =COUNTIF($F10:$F868,D5) -> 0 | E7: =COUNTIF($F10:$F868,E5) -> 0
A8: Round 3 | B8: =COUNTIF($F10:$F868,B5) -> 6 | C8: =COUNTIF($F10:$F868,C5) -> 0 | D8: =COUNTIF($F10:$F868,D5) -> 0 | E8: =COUNTIF($F10:$F868,E5) -> 0
A10: Test Case ID | B10: Test Case Description | C10: Test Case Procedure | D10: Expected Results | E10: Pre-conditions | F10: Round 1 | G10: Test date | H10: Tester | I10: Round 2 | J10: Test date | K10: Tester | L10: Round 3 | M10: Test date | N10: Tester | O10: Note
A11: View result
A12: [View result 1] | B12: View Results - Display after submission | C12: 1. Login as Student 2. Complete and submit quiz 3. Verify results page automatically loads | D12: - Results page displays immediately after submission - Overall score shown (e.g., "75%") - Pass/fail status clearly indicated (green/red badge) - Statistics: Correct answers, Wrong answers, Total questions - Question map displayed (green = correct, red = wrong) - Can navigate questions to review | E12: - Student logged in - Quiz submitted - Grading complete | F12: Passed | G12: 45978 | H12: TuanCM | I12: Passed | J12: 45980 | K12: TuanCM | L12: Passed | M12: 45981 | N12: TuanCM
A13: [View result 2] | B13: View Results - Score calculated correctly | C13: 1. Login as Student 2. Complete quiz: 3. Submit quiz 4. Verify score calculation | D13: - Score displayed: 70% - Statistics show - Calculation accurate - Each question marked correctly - Formula verified: (Correct / Total) × 100 | E13: - Student logged in - Quiz has 10 question - Known correct answer count | F13: Passed | G13: 45978 | H13: TuanCM | I13: Passed | J13: 45980 | K13: TuanCM | L13: Passed | M13: 45981 | N13: TuanCM
A14: [View result -3 ] | B14: View Results - Pass/fail status correct | C14: 1. Login as Student 2. Submit quiz with 80% score 3. Quiz pass threshold: 70% 4. Verify pass status | D14: - Status badge: "Đã vượt qua" (Passed) in GREEN - Score: 80% displayed prominently - Pass threshold shown: "Yêu cầu: 70%" - Congratulations message - Logic: 80% ≥ 70% = Passed | E14: - Student logged in - Quiz pass threshold: 70% - Student scored 80% | F14: Passed | G14: 45978 | H14: TuanCM | I14: Passed | J14: 45980 | K14: TuanCM | L14: Passed | M14: 45981 | N14: TuanCM
A15: [View result - 4] | B15: View Results - View correct answers and explanations | C15: 1. Login as Student 2. View quiz results 3. Click on question #3 (answered incorrectly) 4. Review answer details | D15: - Question text - Student's selected answer (marked in RED with X) - Correct answer (marked in GREEN with ✓) - Explanation/rationale shown (if provided by instructor) - Can learn from mistakes - Navigation to next/previous question works | E15: - Student logged in - Quiz results available - Instructor provided answer explanations | F15: Passed | G15: 45978 | H15: TuanCM | I15: Passed | J15: 45980 | K15: TuanCM | L15: Passed | M15: 45981 | N15: TuanCM
A16: [View result - 5] | B16: View Results - Retry quiz | C16: 1. Login as Student (used 1/3 attempts, failed with 50%) 2. View results page 3. Verify "Làm lại" (Retry) button 4. Click "Làm lại" | D16: - "Làm lại" button displayed prominently - Shows attempts remaining: "Còn 2/3 lần làm bài" - Click "Làm lại": Quiz resets - Redirected to fresh quiz attempt - Previous answers NOT pre-filled - New attempt recorded | E16: - Student logged in - Quiz allows 3 attempts - Student used 1 attempt - Failed quiz (< passing score) | F16: Passed | G16: 45978 | H16: TuanCM | I16: Passed | J16: 45980 | K16: TuanCM | L16: Passed | M16: 45981 | N16: TuanCM
A17: [View result - 6] | B17: View Results - Unauthorized (other student's results) | C17: 1. Login as Student A 2. Obtain result URL of Student B (via URL manipulation) 3. Try to access Student B's quiz results | D17: - Error: "Bạn không có quyền xem kết quả này." - Access blocked (403 Forbidden) - Redirected to own quiz results or course page - Cannot view other students' results - Security enforced - Access attempt logged | E17: - Student A logged in - Student B's result exists - URL manipulation attempted | F17: Passed | G17: 45978 | H17: TuanCM | I17: Passed | J17: 45980 | K17: TuanCM | L17: Passed | M17: 45981 | N17: TuanCM

Sheet Rating
A2: Feature | B2: Rating | R2: Passed
A3: Test requirement | B3: <Brief description about requirements which are tested in this sheet> | R3: Failed
A4: Number of TCs | B4: =COUNTA(A12:A866) -> 2 | R4: Pending
A5: Testing Round | B5: Passed | C5: Failed | D5: Pending | E5: N/A | R5: N/A
A6: Round 1 | B6: =COUNTIF($F10:$F864,B5) -> 2 | C6: =COUNTIF($F10:$F864,C5) -> 0 | D6: =COUNTIF($F10:$F864,D5) -> 0 | E6: =COUNTIF($F10:$F864,E5) -> 0
A7: Round 2 | B7: =COUNTIF($F10:$F864,B5) -> 2 | C7: =COUNTIF($F10:$F864,C5) -> 0 | D7: =COUNTIF($F10:$F864,D5) -> 0 | E7: =COUNTIF($F10:$F864,E5) -> 0
A8: Round 3 | B8: =COUNTIF($F10:$F864,B5) -> 2 | C8: =COUNTIF($F10:$F864,C5) -> 0 | D8: =COUNTIF($F10:$F864,D5) -> 0 | E8: =COUNTIF($F10:$F864,E5) -> 0
A10: Test Case ID | B10: Test Case Description | C10: Test Case Procedure | D10: Expected Results | E10: Pre-conditions | F10: Round 1 | G10: Test date | H10: Tester | I10: Round 2 | J10: Test date | K10: Tester | L10: Round 3 | M10: Test date | N10: Tester | O10: Note
A11: Rating
A12: [Rating -1] | B12: Success with rating | C12: 1. Login as Student 2. Navigate to enrolled course 3. Click "Đánh giá khóa học" 4. Select 5 stars 5. Enter comment: "Khóa học rất hay!" 6. Click "Gửi đánh giá" | D12: - Success message: "Cảm ơn bạn đã đánh giá!" - Review saved to database - Rating appears on course detail page - Average rating recalculated - Review count incremented - Modal closes | E12: - Student logged in - Enrolled in course | F12: Passed | G12: 45978 | H12: TuanCM | I12: Passed | J12: 45980 | K12: TuanCM | L12: Passed | M12: 45981 | N12: TuanCM
A13: [Rating -2] | B13: Missing rating | C13: 1. Login as Student 2. Click "Đánh giá" 3. Enter comment 4. Don't select any stars 5. Click "Gửi đánh giá" | D13: - Error: "Vui lòng chọn số sao đánh giá." - Star rating field highlighted - Review NOT submitted - Rating is required - Validation works | E13: - Student logged in - Enrolled in course | F13: Passed | G13: 45978 | H13: TuanCM | I13: Passed | J13: 45980 | K13: TuanCM | L13: Passed | M13: 45981 | N13: TuanCM

Sheet Email notification
A2: Feature | B2: Email notification | R2: Passed
A3: Test requirement | B3: <Brief description about requirements which are tested in this sheet> | R3: Failed
A4: Number of TCs | B4: =COUNTA(A12:A868) -> 4 | R4: Pending
A5: Testing Round | B5: Passed | C5: Failed | D5: Pending | E5: N/A | R5: N/A
A6: Round 1 | B6: =COUNTIF($F10:$F866,B5) -> 4 | C6: =COUNTIF($F10:$F866,C5) -> 0 | D6: =COUNTIF($F10:$F866,D5) -> 0 | E6: =COUNTIF($F10:$F866,E5) -> 0
A7: Round 2 | B7: =COUNTIF($F10:$F866,B5) -> 4 | C7: =COUNTIF($F10:$F866,C5) -> 0 | D7: =COUNTIF($F10:$F866,D5) -> 0 | E7: =COUNTIF($F10:$F866,E5) -> 0
A8: Round 3 | B8: =COUNTIF($F10:$F866,B5) -> 4 | C8: =COUNTIF($F10:$F866,C5) -> 0 | D8: =COUNTIF($F10:$F866,D5) -> 0 | E8: =COUNTIF($F10:$F866,E5) -> 0
A10: Test Case ID | B10: Test Case Description | C10: Test Case Procedure | D10: Expected Results | E10: Pre-conditions | F10: Round 1 | G10: Test date | H10: Tester | I10: Round 2 | J10: Test date | K10: Tester | L10: Round 3 | M10: Test date | N10: Tester | O10: Note
A11: Email notification
A12: [Email notification -1] | B12: Email - Successful registration welcome email | C12: 1. Register new account<br> 2. Complete registration<br> 3. Check email inbox | D12: - Welcome email received<br> - Email contains: Welcome message, platform intro, login link<br> - Professional format<br> - Sent from: noreply@skillup.com or similar<br> - Email delivered within 1-2 minutes | E12: - New user registration<br> - Valid email address<br> - Email service operational | F12: Passed | G12: 45978 | H12: TuanCM | I12: Passed | J12: 45980 | K12: TuanCM | L12: Passed | M12: 45981 | N12: TuanCM
A13: [Email notification -2] | B13: Email - Password reset email | C13: 1. Navigate to "Quên mật khẩu"<br> 2. Enter registered email<br> 3. Check inbox | D13: - Password reset email received<br> - Link format - Link works when clicked<br> - Email delivered quickly | E13: - User account exists<br> - Valid email entered<br> - Email service operational | F13: Passed | G13: 45978 | H13: TuanCM | I13: Passed | J13: 45980 | K13: TuanCM | L13: Passed | M13: 45981 | N13: TuanCM
A14: [Email notification -2] | B14: Email - Lecturer application approved | C14: 1. Content Moderator approves lecturer application<br> 2. System sends notification<br> 3. Check applicant's email | D14: - Approval email received<br> - Professional and welcoming tone<br> - Sent to applicant's email | E14: - Lecturer application submitted<br> - Moderator approved<br> - Email service operational | F14: Passed | G14: 45978 | H14: TuanCM | I14: Passed | J14: 45980 | K14: TuanCM | L14: Passed | M14: 45981 | N14: TuanCM
A15: [Email notification -2] | B15: Email - Lecturer application rejected | C15: 1. Moderator rejects lecturer application<br> 2. System sends notification<br> 3. Check applicant's email | D15: - Rejection email received<br> - Professional and constructive tone | E15: - Lecturer application submitted<br> - Moderator rejected<br> - Email service operational | F15: Passed | G15: 45978 | H15: TuanCM | I15: Passed | J15: 45980 | K15: TuanCM | L15: Passed | M15: 45981 | N15: TuanCM
