Workbook
Name ACTION: #REF!
Name ACTION: #REF!

Sheet Cover
B2: SYSTEM TEST REPORT DOCUMENT
A4: Project Name | B4: Online Learning Platform – SkillUp | E4: Creator | F4: TuanCM
A5: Project Code | B5: OLP-SkillUp | E5: Issue Date | F5: 45998
A6: Document Code | B6: =B5&"_"&"System_Test_Report"&"" -> OLP-SkillUp_System_Test_Report | E6: Version | F6: 1.0
A9: Record of change
A10: Effective Date | B10: Version | C10: Change Item | D10: *A,D,M | E10: Change description | F10: Reference
A11: 45998 | B11: 1.0 | D11: A | E11: Initialize System Test
A12: 45998 | B12: 1.0 | C12: Test Cases, Test Statistics | D12: A | E12: Implement test cases for Iteration 1.
A13: 46001 | B13: 1.0 | C13: Test Cases, Test Statistics | D13: M | E13: Implement test cases for Iteration 2.
A14: 46003 | B14: 1.0 | C14: Test Cases, Test Statistics | D14: M | E14: Implement test cases for Iteration 3.

Sheet Test Cases
D1: TEST CASE LIST
B3: Project Name | D3: Online Learning Platform – SkillUp
B4: Project Code | D4: OLP-SkillUp
B5: Test Environment Setup Description | D5: 1. Server 2. SQLServer 3.Google Chrome, Microsoft Edge 4. Microsoft Visual Studio
B8: No | C8: Function Name | D8: Sheet Name | E8: Description | F8: Pre-Condition
B9: 1 | C9: Authentication | D9: Authentication
B10: 2 | C10: Workflow of Student | D10: Workflow of Student
B11: 3 | C11: Workflow of Lecturer | D11: Workflow of Lecturer
B12: 4 | C12: Workflow of System Moderator | D12: Workflow of System Moderator
B13: 5 | C13: Workflow of Content Morderator | D13: Workflow of Content Morderator
B14: 6 | C14: Workflow of Admin | D14: Workflow of Admin
B15: 7 | C15: AI Assistant | D15: AI Assistant

Sheet Test Statistics
B1: TEST STATISTICS
B3: Project Name | C3: Online Learning Platform – SkillUp | E3: Creator | H3: TuanCM
B4: Project Code | C4: OLP-SkillUp | E4: Reviewer/Approver
B5: Document Code | C5: =C4&"_"&"System_Test_Report"&"" -> OLP-SkillUp_System_Test_Report | E5: Issue Date | H5: 45998
B6: Notes
B10: No | C10: Module code | D10: Passed | E10: Failed | F10: Pending | G10: N/A | H10: Number of test cases
B11: 1 | C11: =Authentication!B2 -> Authentication | D11: =Authentication!B8 -> 15 | E11: =Authentication!C8 -> 0 | F11: =Authentication!D6 -> 0 | G11: =Authentication!E6 -> 0 | H11: =Authentication!B4 -> 15
B12: 2 | C12: ='Workflow of System Moderator'!B2 -> Workflow of System Moderator | D12: ='Workflow of System Moderator'!B6 -> 15 | E12: ='Workflow of System Moderator'!C6 -> 0 | F12: ='Workflow of System Moderator'!D6 -> 0 | G12: ='Workflow of System Moderator'!E6 -> 0 | H12: ='Workflow of System Moderator'!B4 -> 15
B13: 3 | C13: ='Workflow of Content Morderator'!B2 -> Workflow of Content Moderator | D13: ='Workflow of Content Morderator'!B6 -> 32 | E13: ='Workflow of Content Morderator'!C6 -> 0 | F13: ='Workflow of Content Morderator'!D6 -> 0 | G13: ='Workflow of Content Morderator'!E6 -> 0 | H13: ='Workflow of Content Morderator'!B4 -> 32
B14: 4 | C14: ='Workflow of Lecturer'!B2 -> Workflow of Lecturer | D14: ='Workflow of Lecturer'!B6 -> 63 | E14: ='Workflow of Lecturer'!C6 -> 0 | F14: ='Workflow of Lecturer'!D6 -> 0 | G14: ='Workflow of Lecturer'!E6 -> 0 | H14: ='Workflow of Lecturer'!B4 -> 63
B15: 5 | C15: ='Workflow of Student'!B2 -> Workflow of Student | D15: ='Workflow of Student'!B6 -> 33 | E15: ='Workflow of Student'!C6 -> 0 | F15: ='Workflow of Student'!D6 -> 0 | G15: ='Workflow of Student'!E6 -> 0 | H15: ='Workflow of Student'!B4 -> 33
B16: 6 | C16: ='Workflow of Admin'!B2 -> Workflow of Admin | D16: ='Workflow of Admin'!B6 -> 16 | E16: ='Workflow of Admin'!C6 -> 0 | F16: ='Workflow of Admin'!D6 -> 0 | G16: ='Workflow of Admin'!E6 -> 0 | H16: ='Workflow of Admin'!B4 -> 16
B17: 7 | C17: ='AI Assistant'!B2 -> AI assistant | D17: ='AI Assistant'!B6 -> 5 | E17: ='AI Assistant'!C6 -> 0 | F17: ='AI Assistant'!D6 -> 0 | G17: ='AI Assistant'!E6 -> 0 | H17: ='AI Assistant'!B4 -> 5
C19: Sub total | D19: =SUM(D9:D16) -> 174 | E19: =SUM(E9:E16) -> 0 | F19: =SUM(F9:F16) -> 0 | G19: =SUM(G9:G16) -> 0 | H19: =SUM(H9:H16) -> 174
C21: Test coverage | E21: =(D19+E19)*100/(H19-G19) -> 100 | F21: %
C22: Test successful coverage | E22: =D19*100/(H19-G19) -> 100 | F22: %

Sheet Authentication
A2: Workflow | B2: Authentication | R2: Passed
A3: Test requirement | B3: Check if the functionalities of authentication feature work. | R3: Failed
A4: Number of TCs | B4: 15 | R4: Pending
A5: Testing Round | B5: Passed | C5: Failed | D5: Pending | E5: N/A | R5: N/A
A6: Round 1 | B6: =COUNTIF($F10:$F1008,B5) -> 14 | C6: =COUNTIF($F10:$F1008,C5) -> 1 | D6: =COUNTIF($F10:$F1008,D5) -> 0 | E6: =COUNTIF($F10:$F1008,E5) -> 0
A7: Round 2 | B7: =COUNTIF($I10:$I1008,B5) -> 15 | C7: =COUNTIF($I10:$I1008,C5) -> 0 | D7: =COUNTIF($F10:$F1008,D5) -> 0 | E7: =COUNTIF($F10:$F1008,E5) -> 0
A8: Round 3 | B8: =COUNTIF($L10:$L1008,B5) -> 15 | C8: =COUNTIF($L10:$L1008,C5) -> 0 | D8: =COUNTIF($F10:$F1008,D5) -> 0 | E8: =COUNTIF($F10:$F1008,E5) -> 0
A10: Test Case ID | B10: Test Case Description | C10: Test Case Procedure | D10: Expected Results | E10: Pre-conditions | F10: Round 1 | G10: Test date | H10: Tester | I10: Round 2 | J10: Test date | K10: Tester | L10: Round 3 | M10: Test date | N10: Tester | O10: Note
A11: Register
A12: [Authen - 1] | B12: Test registration with valid input : - Email - Password - Repassword - Full name | C12: 1. Enter "http://localhost:5173/" to navigate to the website. (Top-right corner of the screen) 2. Guest user click the “Đăng ký” button. 3. The site displays the registration form. 4. Guest user select a registration role: “Student” or “Lecturer.” 5. Enter the following valid information: - Email: student@gmail.com - Password: Student@123 - RePassword: Student@123 - Full Name: Nguyen Van A 6. Guest user click the “Đăng ký” button. 7. Guest user ou are redirected to the “Đăng nhập” screen. | D12: - The guest user successfully registered, is redirected to the login page and the user details are stored in the database. - Notification display system "Đăng ký thành công! Vui lòng kiểm tra email để xác thực tài khoản." - The system sends authentication to the registered user's email. | E12: Server must be work Guest user is not logged in and wants to create an account. | F12: Passed | G12: 45998 | H12: TuanCM | I12: Passed | J12: 46001 | K12: TuanCM | L12: Passed | M12: 46003 | N12: TuanCM
A13: [Authen - 2] | B13: Test registration with valid input : - Email - Password - Repassword - Full name | C13: 1. Enter "http://localhost:5173/" to navigate to the website. (Top-right corner of the screen) 2. Guest user clicks the “Đăng ký” button. 3. The site displays the registration form. 4. Guest user selects a registration role: “Student” or “Lecturer.” 5.Guest user enter invalid email form(e.g., quatbt.com) 6. Guest user clicks the “Đăng ký” button. 7. Website displays an error message for invaild email format 8. Guest user corrects the mail format and resubmits the form. | D13: System displays an error message for the empty fields and prevents registration until corrected. | E13: Server must be work Guest user is not logged in and wants to create an account. | F13: Passed | G13: 45998 | H13: TuanCM | I13: Passed | J13: 46001 | K13: TuanCM | L13: Passed | M13: 46003 | N13: TuanCM
A14: [Authen - 3] | B14: Test registration with valid input : - Email - Password - Repassword - Full name | C14: 1. Enter "http://localhost:5173/" to navigate to the website. (Top-right corner of the screen) 2. Guest user click the “Đăng ký” button. 3. The site displays the registration form. 4. Guest user select a registration role: “Student” or “Lecturer.” 5. Enter the following valid information: - Email: empty - Password: empty - RePassword: empty - Full Name: empty 6. The registration form displays the message "vui lòng điền vào trường này". 7. The guest user corrects the inputs so no field is left blank and the format is valid, then submits the form. | D14: System displays an error message for the empty fields and prevents registration until corrected. | E14: Server must be work Guest user is not logged in and wants to create an account. | F14: Passed | G14: 45998 | H14: TuanCM | I14: Passed | J14: 46001 | K14: TuanCM | L14: Passed | M14: 46003 | N14: TuanCM
A15: [Authen - 4] | B15: Test registration with password must be shorter than 6 characters | C15: 1. Enter "http://localhost:5173/" to navigate to the website. (Top-right corner of the screen) 2. Guest user click the “Đăng ký” button. 3. The site displays the registration form. 4. Guest user select a registration role: “Student” or “Lecturer.” 5. Guest user enters a Password shorter than 6 characters (e.g., pass2). 6. Website displays an error message indicating "Mật khẩu phải có ít nhất 6 ký tự" 7. Guest user corrects the Password and resubmits the form. | D15: Displays an error message indicating "Mật khẩu phải có ít nhất 6 ký tự" | E15: Server must be work Guest user is not logged in and wants to create an account. | F15: Passed | G15: 45998 | H15: TuanCM | I15: Passed | J15: 46001 | K15: TuanCM | L15: Passed | M15: 46003 | N15: TuanCM
A16: [Authen - 5] | B16: Test registration with valid input : - Email - Password - Repassword - Full name | C16: 1. Enter "http://localhost:5173/" to navigate to the website. (Top-right corner of the screen) 2. Guest user clicks the “Đăng ký” button. 3. The site displays the registration form. 4. Guest user selects a registration role: “Student” or “Lecturer.” 5.The guest user enters a confirmation password that does not match the password (e.g., Password: Student@123, Confirm Password: studenta12). 6. Guest user clicks the “Đăng ký” button. 7. The website displays the message "Mật khẩu không khớp". 8. The guest user corrects the confirm password and resubmits the form. | D16: Displays an error message indicating "Mật khẩu không khớp" | E16: Server must be work Guest user is not logged in and wants to create an account. | F16: Passed | G16: 45998 | H16: TuanCM | I16: Passed | J16: 46001 | K16: TuanCM | L16: Passed | M16: 46003 | N16: TuanCM
A17: [Authen - 6] | B17: Test registration with valid input : - Email - Password - Repassword - Full name | C17: 1. Enter "http://localhost:5173/" to navigate to the website. (Top-right corner of the screen) 2. Guest user clicks the “Đăng ký” button. 3. The site displays the registration form. 4. Guest user selects a registration role: “Student” or “Lecturer.” 5.Guest user enters an email address that already exists in the system. 6. Guest user clicks the “Đăng ký” button. 7. The website displays the message "Email đã tồn tại hoặc có lỗi xảy ra". 8. The guest user corrects the email and resubmits the form. | D17: Displays an error message indicating "Email đã tồn tại hoặc có lỗi xảy ra" | E17: Server must be work Guest user is not logged in and wants to create an account. | F17: Passed | G17: 45998 | H17: TuanCM | I17: Passed | J17: 46001 | K17: TuanCM | L17: Passed | M17: 46003 | N17: TuanCM
A18: Login by account
A19: [Authen - 7] | B19: Check if the user can successfully log in with a valid email and password. | C19: 1. Enter "http://localhost:5173/" to go to website 2. Location in the right corner of the screen: - Click on "Đăng nhập" button 3. Fill in information including: - Email: user@example.com - Password: String 4. Click "Đăng nhập" button | D19: System displays message "Đăng nhập thành công!" | E19: Server must be work Guest user is not logged in and wants to create an account. | F19: Passed | G19: 45998 | H19: TuanCM | I19: Passed | J19: 46001 | K19: TuanCM | L19: Passed | M19: 46003 | N19: TuanCM
A20: [Authen - 8] | B20: Check if the website handles an incorrect password. | C20: 1. Enter "http://localhost:5173/" to go to website 2. Location in the right corner of the screen: - Click on "Đăng nhập" button 3. Fill in information including: - Email: user@example.com - Password: String1111 4. Click "Đăng nhập" button | D20: System displays message "Email hoặc mật khẩu không đúng" | E20: Server must be work Guest user is not logged in and wants to create an account. | F20: Passed | G20: 45998 | H20: TuanCM | I20: Passed | J20: 46001 | K20: TuanCM | L20: Passed | M20: 46003 | N20: TuanCM
A21: [Authen - 9] | B21: Check if the website handles an unregistered email address. | C21: 1. Enter "http://localhost:5173/" to go to website 2. Location in the right corner of the screen: - Click on "Đăng nhập" button 3. Fill in information including: - Email: user11@example.com - Password: String 4. Click "Đăng nhập" button | D21: System displays message "Email hoặc mật khẩu không đúng" | E21: Server must be work Guest user is not logged in and wants to create an account. | F21: Passed | G21: 45998 | H21: TuanCM | I21: Passed | J21: 46001 | K21: TuanCM | L21: Passed | M21: 46003 | N21: TuanCM
A22: Login by google
A23: [Authen - 10] | B23: Check if the user can successfully log in using a valid Google account. | C23: 1. Enter "http://localhost:5173/" to navigate to the website. (Top-right corner of the screen) 2. Guest user click the “Đăng nhập” button. 3. Click on the "Tiếp tục sử dụng dịch vụ bằng google" button. 4. The system redirects to Google’s login page. 5. The system redirects back to the application, showing the user's dashboard or homepage". | D23: System displays message "Đăng nhập Google thành công" | E23: 1.Server must be work 2..Account must be in system | F23: Passed | G23: 45998 | H23: TuanCM | I23: Passed | J23: 46001 | K23: TuanCM | L23: Passed | M23: 46003 | N23: TuanCM
A24: Forgot password
A25: [Authen - 11] | B25: Verify if the user can request a password reset by entering a valid registered email address. | C25: 1. Enter "http://localhost:5173/" to navigate to the website. (Top-right corner of the screen) 2. Guest user click the “Đăng nhập” button. 3. Guest user clicks on link "Quên mật khẩu?". 4. The system displays a form asking the user to enter their registered email address. 5. The user enters their email address and clicks the "Gửi email khôi phục" button. 6. The system sends a password reset email with a reset link to the user’s registered email address. 7. Redirect to "Đặt lại mật khẩu" screen 6. User enter the following valid information: - Mật khẩu mới: Student@123 - Xác nhận mật khẩu mới: Student@123 7. Click on "Đặt lại mật khẩu" button | D25: System displays message "Đặt lại mật khẩu thành công" | E25: 1.Server must be work 2..Account must be in system | F25: Passed | G25: 45998 | H25: TuanCM | I25: Passed | J25: 46001 | K25: TuanCM | L25: Passed | M25: 46003 | N25: TuanCM
A26: [Authen - 12] | B26: Enter non-existent email | C26: 1. Enter "http://localhost:5173/" to navigate to the website. (Top-right corner of the screen) 2. Guest user click the “Đăng nhập” button. 3. Guest user clicks on link "Quên mật khẩu?". 4. The system displays a form asking the user to enter their registered email address. 5. User enters an email that is not registered in the system (e.g., nanhnanh07@gmail.com). 6. Clicks the "Gửi email khôi phục" button. | D26: System displays message "Email không tồn tại hoặc chưa xác thực" | E26: 1.Server must be work 2..Account must be in system | F26: Passed | G26: 45998 | H26: TuanCM | I26: Passed | J26: 46001 | K26: TuanCM | L26: Passed | M26: 46003 | N26: TuanCM
A27: Logout
A28: [Authen - 13] | B28: Check if the user can successfully log out from the website. | C28: 1. Enter "http://localhost:5173/" to go to website 2. Guest user login with system. 3.Click the avatar icon in top-right of website. 4. Click "Đăng xuất" button. | D28: - User is logged out and redirect home page. No user-specific data is accessible until the user logs in again. - Show message "Đăng xuất thành công!" | E28: 1.Server must be work 2..Account must be in system | F28: Passed | G28: 45998 | H28: TuanCM | I28: Passed | J28: 46001 | K28: TuanCM | L28: Passed | M28: 46003 | N28: TuanCM
A29: [Authen - 14] | B29: Check if a logged-out user is restricted from accessing pages meant for logged-in users. | C29: 1. Enter "http://localhost:5173/" to go to website 2. Guest user login with system. 3.Click the avatar icon in top-right of website. 4. Click "Đăng xuất" button. 5. After logging out, try to directly access the restricted page by entering the URL in the browser. | D29: The system redirects the user to the homepage when they try to access the restricted page. | E29: 1.Server must be work 2..Account must be in system | F29: Failed | G29: 45998 | H29: TuanCM | I29: Passed | J29: 46001 | K29: TuanCM | L29: Passed | M29: 46003 | N29: TuanCM | O29: Round 1, 07/12/2025: The system did not redirect the user to the homepage when they try to accesses the restricted page.
A30: [Authen - 15] | B30: Register to become a lecturer | C30: 1. Enter "http://localhost:5173/" to navigate to the website. (Top-right corner of the screen) 2. Guest user click the “Đăng ký” button. 3. The site displays the registration form. 4. Guest user select a registration role: “Student” or “Lecturer.” 5. Enter the following valid information: - Email: lecturer@gmail.com - Password: Lecturer@123 - RePassword: Lecturer@123 - Full Name: Nguyen Van A 6. Guest user click the “Đăng ký” button. 7. Guest user ou are redirected to the “Đăng nhập” screen. 8. The guest user logs into the system using the newly registered account. 9. The system redirects to the Lecturer Application submission page. 10. Enter the following valid information: - Chức danh: Senior - Chuyên môn: Web Developer - Mô tả kinh nghiệm: 5 years as a software engineer - Tải lên CV: PDF file - Tải lên ảnh bằng cấp: Image file (e.g., .png, .jpg...). 11. The user clicks the “Nộp đơn ứng tuyển” button. | D30: System displays message "Nộp CV thành công! Chúng tôi sẽ liên hệ với bạn sớm." | E30: 1.Server must be work 2..Account must be in system | F30: Passed | G30: 45998 | H30: TuanCM | I30: Passed | J30: 46001 | K30: TuanCM | L30: Passed | M30: 46003 | N30: TuanCM

Sheet Workflow of Student
A2: Workflow | B2: Workflow of Student | R2: Passed
A3: Test requirement | B3: Perform the functionalities of role Student | R3: Failed
A4: Number of TCs | B4: 33 | R4: Pending
A5: Testing Round | B5: Passed | C5: Failed | D5: Pending | E5: N/A | R5: N/A
A6: Round 1 | B6: =COUNTIF($F10:$F1025,B5) -> 33 | C6: =COUNTIF($F10:$F1025,C5) -> 0 | D6: =COUNTIF($F10:$F1025,D5) -> 0 | E6: =COUNTIF($F10:$F1025,E5) -> 0
A7: Round 2 | B7: =COUNTIF($F10:$F1025,B5) -> 33 | C7: =COUNTIF($F10:$F1025,C5) -> 0 | D7: =COUNTIF($F10:$F1025,D5) -> 0 | E7: =COUNTIF($F10:$F1025,E5) -> 0
A8: Round 3 | B8: =COUNTIF($F10:$F1025,B5) -> 33 | C8: =COUNTIF($F10:$F1025,C5) -> 0 | D8: =COUNTIF($F10:$F1025,D5) -> 0 | E8: =COUNTIF($F10:$F1025,E5) -> 0
A10: Test Case ID | B10: Test Case Description | C10: Test Case Procedure | D10: Expected Results | E10: Pre-conditions | F10: Round 1 | G10: Test date | H10: Tester | I10: Round 2 | J10: Test date | K10: Tester | L10: Round 3 | M10: Test date | N10: Tester | O10: Note
A11: Ticket Features
A12: [Ticket - 1] | B12: View ticket list for Students/Lecturer | C12: 1. Login the system with the Student/Lecturer Role. 2. Click the "Phiếu hỗ trợ" tab in the header menu. | D12: The ticket list is displayed correctly with the following informations: - Ticket filter - Create new Ticket button - The list of that user's submitted tickets along with view Details button for each | E12: - The server must be working - User role must be Student or Lecturer - The account status must be "Active" | F12: Passed | G12: 45998 | H12: TuanCM | I12: Passed | J12: 46001 | K12: TuanCM | L12: Passed | M12: 46003 | N12: TuanCM
A13: [Ticket - 2] | B13: Verify filter functionality of the View ticket list for Student/Lecturer screen | C13: 1. Login the system with the Student/Lecturer Role. 2. Click the "Phiếu hỗ trợ" tab in the header menu. 3. Click the "Phiếu đã duyệt", "Phiếu bị từ chối" or "Tất cả phiếu" in the filter menu on the left. | D13: The ticket list is displayed correctly corresponding to the selected filter with the following informations: - Ticket filter - Create new Ticket button - The list of that user's submitted tickets along with view Details button for each | E13: - The server must be working - User role must be Student or Lecturer - The account status must be "Active" | F13: Passed | G13: 45998 | H13: TuanCM | I13: Passed | J13: 46001 | K13: TuanCM | L13: Passed | M13: 46003 | N13: TuanCM
A14: [Ticket - 3] | B14: Verify the Create new Ticket feature | C14: 1. Login the system with the Student/Lecturer Role. 2. Click the "Phiếu hỗ trợ" tab in the header menu. 3. Click the "Tạo phiếu mới" button on the left. 4. Input the "Tiêu đề" and "Nội dung" field for Title and Content in the popup window. 5. Click the "Tạo phiếu" button. | D14: - Successfully create a new Ticket in the system, which can be found in the User's ticket list and System Moderator Ticket List. - The newly created Ticket display the inputted informations correctly. | E14: - The server must be working - User role must be Student or Lecturer - The account status must be "Active" | F14: Passed | G14: 45998 | H14: TuanCM | I14: Passed | J14: 46001 | K14: TuanCM | L14: Passed | M14: 46003 | N14: TuanCM
A15: [Ticket - 4] | B15: Test the Create new Ticket with empty Title. | C15: 1. Login the system with the Student/Lecturer Role. 2. Click the "Phiếu hỗ trợ" tab in the header menu. 3. Click the "Tạo phiếu mới" button on the left. 4. Leave the "Tiêu đề" input fields blank. 5. Click the "Tạo phiếu" button. | D15: - The system send out error message below the blank inputted field. - No new Ticket is created. | E15: - The server must be working - User role must be Student or Lecturer - The account status must be "Active" | F15: Passed | G15: 45998 | H15: TuanCM | I15: Passed | J15: 46001 | K15: TuanCM | L15: Passed | M15: 46003 | N15: TuanCM
A16: [Ticket - 5] | B16: Test the Create new Ticket with empty Content. | C16: 1. Login the system with the Student/Lecturer Role. 2. Click the "Phiếu hỗ trợ" tab in the header menu. 3. Click the "Tạo phiếu mới" button on the left. 4. Leave the "Nội dung" input fields blank. 5. Click the "Tạo phiếu" button. | D16: - The system send out error message below the blank inputted field. - No new Ticket is created. | E16: - The server must be working - User role must be Student or Lecturer - The account status must be "Active" | F16: Passed | G16: 45998 | H16: TuanCM | I16: Passed | J16: 46001 | K16: TuanCM | L16: Passed | M16: 46003 | N16: TuanCM
A17: [Ticket - 6] | B17: Verify the View Ticket Details feature. | C17: 1. Login the system with the Student/Lecturer Role. 2. Click the "Phiếu hỗ trợ" tab in the header menu. 3. Click the "Xem" button on the right of a ticket. | D17: The ticket details page is displayed correctly with the following informations: - User's name - Submitted date and time - Response of the System Moderator - Ticket's Code - Ticket's Status | E17: - The server must be working - User role must be Student or Lecturer - The account status must be "Active" | F17: Passed | G17: 45998 | H17: TuanCM | I17: Passed | J17: 46001 | K17: TuanCM | L17: Passed | M17: 46003 | N17: TuanCM
A18: [Ticket - 7] | B18: Verify the View Ticket Details feature. | C18: 1. Login the system with the Student/Lecturer Role. 2. Click the "Phiếu hỗ trợ" tab in the header menu. 3. Click the "Xem" button on the right of a ticket. | D18: The ticket details page is displayed correctly with the following informations: - User's name - Submitted date and time - Response of the System Moderator - Ticket's Code - Ticket's Status | E18: - The server must be working - User role must be Student or Lecturer - The account status must be "Active" | F18: Passed | G18: 45998 | H18: TuanCM | I18: Passed | J18: 46001 | K18: TuanCM | L18: Passed | M18: 46003 | N18: TuanCM
A19: [Ticket - 8] | B19: Verify the Update Ticket feature. | C19: 1. Login the system with the Student/Lecturer Role. 2. Click the "Phiếu hỗ trợ" tab in the header menu. 3. Click the "Xem" button on the right of a ticket. 4. Click the "Cập nhật phiếu" button on the right. 5. Edit the fields informations of the Ticket. 6. Click the "Lưu thay đổi" button | D19: - Successfully update the Ticket in the system. - The updated Ticket display the inputted informations correctly. | E19: - The server must be working - User role must be Student or Lecturer - The account status must be "Active" - The Ticket status must be "Pending" | F19: Passed | G19: 45998 | H19: TuanCM | I19: Passed | J19: 46001 | K19: TuanCM | L19: Passed | M19: 46003 | N19: TuanCM
A20: [Ticket - 9] | B20: Test the Update Ticket with empty Title. | C20: 1. Login the system with the Student/Lecturer Role. 2. Click the "Phiếu hỗ trợ" tab in the header menu. 3. Click the "Xem" button on the right of a ticket. 4. Click the "Cập nhật phiếu" button on the right. 5. Leave the "Tiêu đề" field blank . 6. Click the "Lưu thay đổi" button | D20: - The system send out error message below the blank inputted field. - No update is made. | E20: - The server must be working - User role must be Student or Lecturer - The account status must be "Active" - The Ticket status must be "Pending" | F20: Passed | G20: 45998 | H20: TuanCM | I20: Passed | J20: 46001 | K20: TuanCM | L20: Passed | M20: 46003 | N20: TuanCM
A21: [Ticket - 10] | B21: Test the Update Ticket with empty Content. | C21: 1. Login the system with the Student/Lecturer Role. 2. Click the "Phiếu hỗ trợ" tab in the header menu. 3. Click the "Xem" button on the right of a ticket. 4. Click the "Cập nhật phiếu" button on the right. 5. Leave the "Nội dung" field blank . 6. Click the "Lưu thay đổi" button | D21: - The system send out error message below the blank inputted field. - No update is made. | E21: - The server must be working - User role must be Student or Lecturer - The account status must be "Active" - The Ticket status must be "Pending" | F21: Passed | G21: 45998 | H21: TuanCM | I21: Passed | J21: 46001 | K21: TuanCM | L21: Passed | M21: 46003 | N21: TuanCM
A22: Buying Course
A23: [Buy - 1] | B23: Verify student can add a free course to cart | C23: 1. Login as Student 2. Navigate to Course Detail page for a free course 3. Click "Add to Cart" button 4. Verify cart count increases | D23: - Toast message: "Thêm vào giỏ hàng thành công" - Cart count badge updates (+1) - Course appears in cart | E23: - Student is logged in - Free course exists (price = 0) - Student not already enrolled | F23: Passed | G23: 45998 | H23: TuanCM | I23: Passed | J23: 46001 | K23: TuanCM | L23: Passed | M23: 46003 | N23: TuanCM
A24: [Buy - 2] | B24: Verify student can add a paid course to cart | C24: 1. Login as Student 2. Navigate to Course Detail page for paid course 3. Verify price is displayed correctly 4. Click "Add to Cart" button (Shopping Cart icon) 5. Check cart page | D24: - Success toast notification appears - Cart icon shows updated count - Course appears in cart with correct price | E24: - Student is logged in - Paid course exists (price > 0) - Course status = "Approved" | F24: Passed | G24: 45998 | H24: TuanCM | I24: Passed | J24: 46001 | K24: TuanCM | L24: Passed | M24: 46003 | N24: TuanCM
A25: [Buy - 3] | B25: Verify instant enrollment for free courses | C25: 1. Login as Student 2. Navigate to free course detail page 3. Click "Đăng ký miễn phí" button 4. Verify enrollment status | D25: -Success message: Course enrolled successfully - Course appears in "My Courses" page | E25: - Student logged in - Course price = 0 - Course is published and approved | F25: Passed | G25: 45998 | H25: TuanCM | I25: Passed | J25: 46001 | K25: TuanCM | L25: Passed | M25: 46003 | N25: TuanCM
A26: [Buy - 4] | B26: Verify payment flow for single course purchase | C26: 1. Login as Student 2. Navigate to paid course detail 3. Click "Mua ngay" button 4. Wait for PayOS redirect 5. Complete payment on PayOS gateway 6. Return to platform | D26: - PayOS payment page opens - After successful payment: redirect to success page - Course enrolled automatically - Transaction recorded in payment history | E26: - Valid PayOS configuration - Student has sufficient balance - Course price > 0 | F26: Passed | G26: 45998 | H26: TuanCM | I26: Passed | J26: 46001 | K26: TuanCM | L26: Passed | M26: 46003 | N26: TuanCM
A27: [Buy - 5] | B27: Verify voucher application reduces course price | C27: 1. Add course to cart 2. Navigate to cart 3. Enter valid voucher code for the course 4. Click "Apply" 5. Verify discount calculation | D27: - Discount amount displayed - Final price = Original price - Discount - Voucher badge shows on course item | E27: - Valid voucher exists for the course - Voucher not expired - Student meets voucher conditions | F27: Passed | G27: 45998 | H27: TuanCM | I27: Passed | J27: 46001 | K27: TuanCM | L27: Passed | M27: 46003 | N27: TuanCM
A28: [Buy - 6] | B28: Verify removing course from cart | C28: 1. Navigate to cart with items 2. Click remove/delete button on a course 3. Confirm removal 4. Check cart count | D28: - Course removed from cart list - Cart count decreases - Total amount recalculates | E28: - At least one course in cart | F28: Passed | G28: 45998 | H28: TuanCM | I28: Passed | J28: 46001 | K28: TuanCM | L28: Passed | M28: 46003 | N28: TuanCM
A29: [Buy - 7] | B29: Verify bulk purchase from cart | C29: 1. Add 2+ courses to cart 2. Apply vouchers (optional) 3. Click "Thanh toán" button 4. Complete PayOS payment 5. Verify enrollments | D29: - All courses enrolled after payment - Cart cleared after successful payment - All courses appear in "My Courses" - Single transaction created for bundle | E29: - Multiple courses in cart - Valid payment method | F29: Passed | G29: 45998 | H29: TuanCM | I29: Passed | J29: 46001 | K29: TuanCM | L29: Passed | M29: 46003 | N29: TuanCM
A30: [Buy - 8] | B30: Verify guest users can add courses to cart | C30: 1. Log out (guest mode) 2. Browse course catalog 3. Click "Add to Cart" on course 4. Check localStorage for cart data | D30: - Toast: "Vui lòng đăng nhập để mua khóa học" - Course stored in localStorage - Cart count shows from localStorage | E30: - Not logged in - Browser allows localStorage | F30: Passed | G30: 45998 | H30: TuanCM | I30: Passed | J30: 46001 | K30: TuanCM | L30: Passed | M30: 46003 | N30: TuanCM
A31: [Buy - 9] | B31: Verify system prevents buying already enrolled course | C31: 1. Login as Student 2. Navigate to already enrolled course 3. Check button state on course detail | D31: - "Học ngay" button displayed instead of "Mua ngay" - Add to cart button disabled - Clicking redirects to learning page | E31: - Student already enrolled in course | F31: Passed | G31: 45998 | H31: TuanCM | I31: Passed | J31: 46001 | K31: TuanCM | L31: Passed | M31: 46003 | N31: TuanCM
A32: [Buy - 10] | B32: Verify enrollment after successful payment | C32: 1. Complete payment flow (TC_BUY_004) 2. Navigate to /student/my-courses 3. Check enrollment API response | D32: - Course appears in enrolled courses list - Progress bar shows 0% initially | E32: - Payment completed successfully - Payment webhook processed | F32: Passed | G32: 45998 | H32: TuanCM | I32: Passed | J32: 46001 | K32: TuanCM | L32: Passed | M32: 46003 | N32: TuanCM
A33: Learning Course
A34: [Learning - 1] | B34: Verify student can access course learning page | C34: 1. Login as Student 2. Navigate to "My Courses" 3. Click on enrolled course 4. Verify redirect to /student/learn/{courseId} | D34: - Course overview page loads - Shows all sections and lessons - Progress indicators visible - No unauthorized access error | E34: - Student enrolled in course - Course has published content | F34: Passed | G34: 45998 | H34: TuanCM | I34: Passed | J34: 46001 | K34: TuanCM | L34: Passed | M34: 46003 | N34: TuanCM
A35: [Learning - 2] | B35: Verify course structure display | C35: 1. Access enrolled course learning page 2. Expand all sections 3. Count lessons, videos, quizzes | D35: - All sections listed - Each section shows: title, description, item count - Icons differentiate: Video, Text, Quiz - Completed items marked with checkmark | E35: - Course has ≥1 section - Section has ≥1 item | F35: Passed | G35: 45998 | H35: TuanCM | I35: Passed | J35: 46001 | K35: TuanCM | L35: Passed | M35: 46003 | N35: TuanCM
A36: [Learning - 3] | B36: Verify video lesson playback | C36: 1. Navigate to course learning 2. Click on video lesson 3. Wait for video player to load 4. Play video 5. Verify tracking | D36: - Video player loads (React Player component) - Video plays without errors - Video controls available (play, pause, fullscreen) | E36: - Lesson type = "Video" - Valid video URL - Student enrolled | F36: Passed | G36: 45998 | H36: TuanCM | I36: Passed | J36: 46001 | K36: TuanCM | L36: Passed | M36: 46003 | N36: TuanCM
A37: [Learning - 4] | B37: Verify text content lesson display | C37: 1. Access text-based lesson 2. Scroll through content 3. Verify formatting | D37: - Content renders correctly - PDF viewer displays (if PDF type) - Text is readable and formatted - Lesson marked as viewed | E37: - Lesson type = "Text" or "PDF" - Content exists | F37: Passed | G37: 45998 | H37: TuanCM | I37: Passed | J37: 46001 | K37: TuanCM | L37: Passed | M37: 46003 | N37: TuanCM
A38: [Learning - 5] | B38: Verify lesson completion functionality | C38: 1. Access any lesson 2. Complete watching/reading 3. Click "Mark as Complete" button 4. Check progress update | D38: - Lesson marked with checkmark - Section progress percentage increases - Overall course progress updates | E38: - Student in lesson view - Lesson not already completed | F38: Passed | G38: 45998 | H38: TuanCM | I38: Passed | J38: 46001 | K38: TuanCM | L38: Passed | M38: 46003 | N38: TuanCM
A39: [Learning - 6] | B39: Verify lesson navigation | C39: 1. Access any lesson in middle of section 2. Click "Next" button 3. Verify navigation to next lesson 4. Click "Previous" button 5. Verify navigation to previous lesson | D39: - Smooth transition animation - Correct lesson loads - CourseSidebar highlights current lesson | E39: - Section has ≥2 lessons | F39: Passed | G39: 45998 | H39: TuanCM | I39: Passed | J39: 46001 | K39: TuanCM | L39: Passed | M39: 46003 | N39: TuanCM
A40: [Learning - 7] | B40: Verify quiz taking functionality | C40: 1. Navigate to quiz item 2. Click "Start Quiz" 3. Answer all questions 4. Submit quiz 5. View results | D40: - Redirects to /student/quiz/{quizId}/take - Timer displays - Can select answers - Submit enabled only when all answered - Score calculated: must pass passPercent threshold | E40: - Quiz has ≥1 question - Student enrolled in course | F40: Passed | G40: 45998 | H40: TuanCM | I40: Passed | J40: 46001 | K40: TuanCM | L40: Passed | M40: 46003 | N40: TuanCM
A41: [Learning - 8] | B41: Verify progress calculation accuracy | C41: 1. Start new course (0% progress) 2. Complete 1 lesson 3. Check progress percentage 4. Complete entire section 5. Verify progress updates | D41: - Progress bar updates in real-time - CourseSidebar shows percentage | E41: - Course has countable items - Student enrolled | F41: Passed | G41: 45998 | H41: TuanCM | I41: Passed | J41: 46001 | K41: TuanCM | L41: Passed | M41: 46003 | N41: TuanCM
A42: [Learning - 9] | B42: Verify sidebar course navigation | C42: 1. Open learning page 2. Click different sections in sidebar 3. Jump to specific lesson 4. Verify responsive behavior (mobile) | D42: - Sidebar shows all sections - Current lesson highlighted - Clicking navigates correctly - Completed items show checkmark icon | E42: - Learning page loaded | F42: Passed | G42: 45998 | H42: TuanCM | I42: Passed | J42: 46001 | K42: TuanCM | L42: Passed | M42: 46003 | N42: TuanCM
A43: [Learning - 10] | B43: Verify enrollment validation | C43: 1. Login as Student A 2. Get courseId of course NOT enrolled 3. Manually navigate to /student/learn/{courseId} 4. Check response | D43: - Error message: "Bạn chưa đăng ký khóa học này" - Redirect to course detail or error page - No course content exposed | E43: - Student NOT enrolled in test course - Course exists and is published | F43: Passed | G43: 45998 | H43: TuanCM | I43: Passed | J43: 46001 | K43: TuanCM | L43: Passed | M43: 46003 | N43: TuanCM
A44: [Learning - 12] | B44: Verify section-specific view | C44: 1. Access /student/learn/{courseId}/section/{sectionId} 2. Verify section content display 3. View section description 4. Access lessons from section view | D44: - Section title and description shown - All section items listed - Progress for this section displayed - Can navigate to lessons | E44: - Valid sectionId - Section has content | F44: Passed | G44: 45998 | H44: TuanCM | I44: Passed | J44: 46001 | K44: TuanCM | L44: Passed | M44: 46003 | N44: TuanCM
A45: [Learning - 13] | B45: Verify course completion flow | C45: 1. Complete all lessons/quizzes 2. Complete final item 3. Check for rating modal 4. Submit rating | D45: - Progress reaches 100% - Rating modal appears (RatingModal component) - Can rate 1-5 stars - Can leave review text - Rating saved to database | E45: - All course items completable - Student completes all | F45: Passed | G45: 45998 | H45: TuanCM | I45: Passed | J45: 46001 | K45: TuanCM | L45: Passed | M45: 46003 | N45: TuanCM
A46: [Learning - 14] | B46: Verify bookmark functionality | C46: 1. Start lesson in section 2 2. Close browser/logout 3. Login again 4. Navigate to "My Courses" 5. Click course | D46: - System remembers last accessed lesson - "Continue Learning" button appears - Clicking resumes from last position | E46: - Student has started course previously - Progress tracking enabled | F46: Passed | G46: 45998 | H46: TuanCM | I46: Passed | J46: 46001 | K46: TuanCM | L46: Passed | M46: 46003 | N46: TuanCM

Sheet Workflow of Lecturer
A2: Workflow | B2: Workflow of Lecturer | R2: Passed
A3: Test requirement | B3: Perform the functionalities of role Lecturer | R3: Failed
A4: Number of TCs | B4: 63 | R4: Pending
A5: Testing Round | B5: Passed | C5: Failed | D5: Pending | E5: N/A | R5: N/A
A6: Round 1 | B6: =COUNTIF($F10:$F1060,B5) -> 63 | C6: =COUNTIF($F10:$F1060,C5) -> 0 | D6: =COUNTIF($F10:$F1060,D5) -> 0 | E6: =COUNTIF($F10:$F1060,E5) -> 0
A7: Round 2 | B7: =COUNTIF($F10:$F1060,B5) -> 63 | C7: =COUNTIF($F10:$F1060,C5) -> 0 | D7: =COUNTIF($F10:$F1060,D5) -> 0 | E7: =COUNTIF($F10:$F1060,E5) -> 0
A8: Round 3 | B8: =COUNTIF($F10:$F1060,B5) -> 63 | C8: =COUNTIF($F10:$F1060,C5) -> 0 | D8: =COUNTIF($F10:$F1060,D5) -> 0 | E8: =COUNTIF($F10:$F1060,E5) -> 0
A10: Test Case ID | B10: Test Case Description | C10: Test Case Procedure | D10: Expected Results | E10: Pre-conditions | F10: Round 1 | G10: Test date | H10: Tester | I10: Round 2 | J10: Test date | K10: Tester | L10: Round 3 | M10: Test date | N10: Tester | O10: Note
A11: Create Course
A12: [Create Course - 1] | B12: Test navigation to course creation page from side menu | C12: 1. Login to the system with approved Lecturer credentials 2. Locate "Khóa học" menu item in the left side menu 3. Click on "Khóa học" 4. Verify course management page loads 5. Locate "Tạo khóa học mới" button in the top right corner 6. Verify button is visible and enabled | D12: - "Khóa học" menu item is visible in side menu - "Khóa học" menu item is clickable - Course management page loads within 3 seconds - Page displays existing courses (if any) or empty state - "Tạo khóa học mới" button is visible in top right - "Tạo khóa học mới" button is enabled and clickable - No console errors occur - Course creation form appears as modal or new page | E12: - User has valid Lecturer account - User has logged into the system successfully - User's application to be Lecturer has been approved | F12: Passed | G12: 45998 | H12: TuanCM | I12: Passed | J12: 46001 | K12: TuanCM | L12: Passed | M12: 46003 | N12: TuanCM
A13: [Create Course - 2] | B13: Test course creation form display | C13: 1. Complete steps from [Course - 1] 2. Click "Tạo khóa học mới" button 3. Observe the form that appears 4. Verify all form fields are present 5. Verify form layout matches design | D13: - Form displays clearly with proper layout - All required fields are marked with asterisk (*) or "Required" label - Form includes fields for: Course title (required) * Course description (required) * Course category (required) - Form has "Tạo khóa học" button - Form has "Hủy" button to close | E13: - [Create Course - 1] passed successfully - User is on course management page | F13: Passed | G13: 45998 | H13: TuanCM | I13: Passed | J13: 46001 | K13: TuanCM | L13: Passed | M13: 46003 | N13: TuanCM
A14: [Create Course - 3] | B14: Test creating course with all required field filled correctly | C14: 1. Open course creation form (complete [Course - 2 ]) 2. Enter course title: "Kiểm thử phần mềm nâng cao" 3. Enter course description: "Khóa học chuyên sâu về các kỹ thuật kiểm thử phần mềm hiện đại, bao gồm kiểm thử tự động, course list or course kiểm thử hiệu năng và kiểm thử bảo mật" 4. Select category: "Học IT" 5. Select subcategory: "C++" 6. Upload an image 7. Click "Tạo khóa học" button 8. Wait for processing | D14: - All form fields accept input without errors - No validation errors appear - Form submits successfully - Success toast notification appears with message like "Tạo khóa học thành công" - Newest course appears on the top of the list - Course status is displayed as "Nháp" - Course shows "pen icon" for editing - Course shows "eye icon" for preview | E14: - [Create Course - 2] passed successfully - User has valid test data prepared | F14: Passed | G14: 45998 | H14: TuanCM | I14: Passed | J14: 46001 | K14: TuanCM | L14: Passed | M14: 46003 | N14: TuanCM
A15: [Create Course - 4] | B15: Test creating course with minimum valid length for text fields | C15: 1. Open course creation form 2. Enter course title with minimum allowed characters (test boundary: 5 characters): "Testing" 3. Enter course description with minimum allowed characters (test boundary: 20 characters): "Software testing intro" 4. Select valid category, subcategory 5. Click "Tạo khóa học" button | D15: - Form accepts minimum valid length - No validation errors for minimum boundary - Course is created successfully with "Nháp" status - Success notification appears - All entered data is saved correctly | E15: - [Create Course - 2] passed successfully | F15: Passed | G15: 45998 | H15: TuanCM | I15: Passed | J15: 46001 | K15: TuanCM | L15: Passed | M15: 46003 | N15: TuanCM
A16: [Create Course - 5] | B16: Test creating course with maximum valid length for text fields | C16: 1. Open course creation form 2. Enter course title at maximum allowed length (test boundary: assume 200 characters) 3. Enter course description at maximum allowed length (test boundary: assume 5000 characters) 4. Select valid category, subcategory 5. Fill other required fields 6. Click "Tạo khóa học" button | D16: - Form accepts maximum valid length without truncation - No validation errors - Course is created successfully - All text is saved completely without data loss | E16: - [Create Course - 2] passed successfully | F16: Passed | G16: 45998 | H16: TuanCM | I16: Passed | J16: 46001 | K16: TuanCM | L16: Passed | M16: 46003 | N16: TuanCM
A17: [Create Course - 6] | B17: Test creating course with special characters in allowed fields | C17: 1. Open course creation form 2. Enter course title with special characters: "Lập trình C++ & Python: From Zero to Hero!" 3. Enter description with special characters including: periods, commas, semicolons, quotes, parentheses, Vietnamese characters with diacritics 4. Fill other required fields 5. Click "Tạo khóa học" button | D17: - Form accepts valid special characters Vietnamese characters (á, à, ả, ã, ạ, ă, ắ, etc.) are handled correctly - Common punctuation marks are accepted - Course is created successfully - Special characters are displayed correctly (no encoding issues) - No XSS vulnerabilities (special characters are properly escaped) | E17: - [Create Course - 2] passed successfully | F17: Passed | G17: 45998 | H17: TuanCM | I17: Passed | J17: 46001 | K17: TuanCM | L17: Passed | M17: 46003 | N17: TuanCM
A18: [Create Course - 7] | B18: Test creating course with empty required field - Course Title | C18: 1. Open course creation form 2. Leave course title field EMPTY 3. Fill all other required fields with valid data 4. Click "Tạo khóa học" button 5. Observe validation behavior | D18: - Form does NOT submit - Validation error message appears near course title field - Error message is clear: "Tiêu đề khóa học là bắt buộc" or similar - User remains on the form - No course is created in database - Other field values are retained (not cleared) - Form does NOT submit | E18: - [Create Course - 2] passed successfully | F18: Passed | G18: 45998 | H18: TuanCM | I18: Passed | J18: 46001 | K18: TuanCM | L18: Passed | M18: 46003 | N18: TuanCM
A19: [Create Course - 8] | B19: Test creating course with empty required field - Course Description | C19: 1. Open course creation form 2. Fill course title with valid data 3. Leave course description field EMPTY 4. Fill all other required fields 5. Click "Tạo khóa học" button | D19: - Form does NOT submit - Validation error appears: "Mô tả khóa học là bắt buộc" - Description field is highlighted with error styling - User remains on form - No course is created - All entered data in other fields is preserved submit | E19: - [Create Course - 2] passed successfully | F19: Passed | G19: 45998 | H19: TuanCM | I19: Passed | J19: 46001 | K19: TuanCM | L19: Passed | M19: 46003 | N19: TuanCM
A20: [Create Course - 9] | B20: Test creating course with empty required field - Category | C20: 1. Open course creation form 2. Fill course title with valid data 3. Leave category selection empty 4. Fill all other required fields 5. Click "Tạo khóa học" button | D20: - Form does NOT submit - Validation error appears: "Mô tả khóa học là bắt buộc" - Description field is highlighted with error styling - User remains on form - No course is created - All entered data in other fields is preserved submit | E20: - [Create Course - 2] passed successfully | F20: Passed | G20: 45998 | H20: TuanCM | I20: Passed | J20: 46001 | K20: TuanCM | L20: Passed | M20: 46003 | N20: TuanCM
A21: [Create Course - 10] | B21: Test creating course with ALL required fields empty | C21: 1. Open course creation form 2. Fill course title with valid data 3. Leave category selection empty 4. Fill all other required fields 5. Click "Tạo khóa học" button | D21: - Each empty required field shows individual error message - All required fields are highlighted with error styling - Error messages are clear and specific to each field - No course is created - User can see all errors without scrolling (or form scrolls to first error) | E21: - [Create Course - 2] passed successfully | F21: Passed | G21: 45998 | H21: TuanCM | I21: Passed | J21: 46001 | K21: TuanCM | L21: Passed | M21: 46003 | N21: TuanCM
A22: Update course content
A23: [Update course - 1] | B23: Test accessing course edit mode via pen icon | C23: 1. Navigate to course list 2. Locate a draft course (e.g., "Khóa học dùng AI") 3. Click the pen (edit) icon | D23: - System navigates to course editing interface - URL changes to course edit page - Course editing page loads successfully | E23: - At least one draft course exists | F23: Passed | G23: 45998 | H23: TuanCM | I23: Passed | J23: 46001 | K23: TuanCM | L23: Passed | M23: 46003 | N23: TuanCM
A24: [Update course - 2] | B24: Test course editing interface layout | C24: 1. Access course edit page 2. Observe page structure and components | D24: - Page displays course name "System test" at top - Subtitle shows "Chỉnh sửa chi tiết khóa học" - Progress indicator shows "Tiến độ hoàn thành: 33%" in top right - Progress bar displays yellow color at 33% - "Quay lại khóa học" back button in top left - Left sidebar shows "QUẢN LÝ NỘI DUNG KHÓA HỌC" heading - Right content area shows current section content | E24: - User is on course edit page | F24: Passed | G24: 45998 | H24: TuanCM | I24: Passed | J24: 46001 | K24: TuanCM | L24: Passed | M24: 46003 | N24: TuanCM
A25: [Update course - 3] | B25: Test sidebar navigation menu structure | C25: 1. Access course edit page 2. Examine left sidebar menu items | D25: - Menu displays 4 main items in order: 1. "Trang giới thiệu" - with checkmark icon (green) and "Đã hoàn thành" status 2. "Khung chương trình" - with number "2" icon (yellow highlight) 3. "Giá khóa học" - with number "3" icon 4. "Phiếu giảm giá" - with tag icon and "(Tùy chọn)" label - Current section is highlighted in yellow - Completed sections show green checkmark icon - Incomplete sections show gray numbered icons | E25: - User is on course edit page | F25: Passed | G25: 45998 | H25: TuanCM | I25: Passed | J25: 46001 | K25: TuanCM | L25: Passed | M25: 46003 | N25: TuanCM
A26: [Update course - 4] | B26: Test progress overview section | C26: 1. Access course edit page 2. Locate "Tổng quan tiến độ" section in sidebar | D26: - Section displays "Tổng quan tiến độ" heading - Shows completion status: "Đã hoàn thành: 1/3 bước" - Text is in orange/yellow color - Clearly indicates only 1 out of 3 steps completed | E26: - User is on course edit page with basic info completed | F26: Passed | G26: 45998 | H26: TuanCM | I26: Passed | J26: 46001 | K26: TuanCM | L26: Passed | M26: 46003 | N26: TuanCM
A27: [Update course - 5] | B27: Test course publication readiness section | C27: 1. Access course edit page 2. Locate "Đề xuất khóa học" section at bottom of sidebar | D27: - Section displays paper plane icon - Shows text: "Đề xuất khóa học" - Shows requirement: "Hoàn thành 67% để đề xuất" - Section is grayed out/disabled when incomplete5. Indicates course cannot be submitted yet | E27: - Course is not yet complete (less than 100% progress) | F27: Passed | G27: 45998 | H27: TuanCM | I27: Passed | J27: 46001 | K27: TuanCM | L27: Passed | M27: 46003 | N27: TuanCM
A28: [Update course - 6] | B28: Test back navigation button | C28: 1. Access course edit page 2. Click "Quay lại khóa học" button 3. Observe navigation behavior | D28: - Button is clickable with left arrow icon - System navigates back to course list page - No unsaved changes are lost (or warning appears if changes exist) - User returns to "Quản lý khóa học" page | E28: - User is on course edit page | F28: Passed | G28: 45998 | H28: TuanCM | I28: Passed | J28: 46001 | K28: TuanCM | L28: Passed | M28: 46003 | N28: TuanCM
A29: [Update course - 7] | B29: Test editing course name | C29: 1. Navigate to "Trang giới thiệu" 2. Click on "Tên khóa học" field 3. Modify text to: "System test - Updated" 4. Click on "Mô tả khóa học" field 5. Modify description text 6. Click category dropdown 7. Select different category 8. Click category dropdown 9. Select different subcategory 10. Click "Chọn ảnh" or change image button 11. Select new image file 12. Click "Lưu" button | D29: - All fiedls are updated - Toast success show up | E29: - User is on introduction page | F29: Passed | G29: 45998 | H29: TuanCM | I29: Passed | J29: 46001 | K29: TuanCM | L29: Passed | M29: 46003 | N29: TuanCM
A30: [Update course - 8] | B30: Test accessing course structure page | C30: 1. Access course edit page 2. Click "Khung chương trình" in sidebar | D30: - Course structure page displays - Heading shows "Nội dung khóa học" - Shows "0 chương" count - "Chương mới" button visible in top right - Menu item "Khung chương trình" is highlighted | E30: - User is on introduction page | F30: Passed | G30: 45998 | H30: TuanCM | I30: Passed | J30: 46001 | K30: TuanCM | L30: Passed | M30: 46003 | N30: TuanCM
A31: [Update course - 9] | B31: Test empty state for course sections | C31: 1. Access "Khung chương trình" page 2. Observe empty state when no sections exist | D31: - Empty state message displays: - Document icon shown - Text: "Chưa có chương nào" - Subtitle: "Bắt đầu tạo chương đầu tiên" - "Tạo chương" button displayed in dashed border area - Clear call-to-action to create first section | E31: - User is on introduction page | F31: Passed | G31: 45998 | H31: TuanCM | I31: Passed | J31: 46001 | K31: TuanCM | L31: Passed | M31: 46003 | N31: TuanCM
A32: [Update course - 10] | B32: Test opening create section dialog | C32: 1. Access "Khung chương trình" page 2. Click "+ Tạo chương" button | D32: - Create section dialog/form appears - Form contains: + "Tên bài học" input field + "Mô tả bài học" textarea + "Thêm bài học" button + "Hủy" button | E32: - User is on introduction page | F32: Passed | G32: 45998 | H32: TuanCM | I32: Passed | J32: 46001 | K32: TuanCM | L32: Passed | M32: 46003 | N32: TuanCM
A33: [Update course - 11] | B33: Test section creation validation - empty title | C33: 1. Open create section dialog 2. Leave "Tên chương" field empty 3. Enter optional description 4. Click "Lưu" button | D33: -Form does not submit - Validation error appears for "Tên chương" - Error message indicates title is required - Dialog remains open | E33: - User is on introduction page | F33: Passed | G33: 45998 | H33: TuanCM | I33: Passed | J33: 46001 | K33: TuanCM | L33: Passed | M33: 46003 | N33: TuanCM
A34: [Update course - 12] | B34: Test section creation - valid data | C34: 1. Open create section dialog 2. Enter "Tên chương": "Chương 1: Hello world" 3. Leave description empty (optional) 4. Click "Lưu" button | D34: - Form validates successfully - Dialog closes - Section is created and appears in course structure - Success toast notification appears - Empty state disappears | E34: - User is on introduction page | F34: Passed | G34: 45998 | H34: TuanCM | I34: Passed | J34: 46001 | K34: TuanCM | L34: Passed | M34: 46003 | N34: TuanCM
... A44: [Update course - 22] | B44: Test quiz form validation - empty fields | C44: 1. Open quiz creation form 2. Leave all fields empty 3. Click "Tạo quiz" | D44: - Form does not submit - Validation errors appear for required fields - Error messages are clear | E44: - Quiz form is open | F44: Passed | G44: 45998 | H44: TuanCM | I44: Passed | J44: 46001 | K44: TuanCM | L44: Passed | M44: 46003 | N44: TuanCM
A45: [Update course - 23] | B45: Test creating quiz successfully | C45: 1. Open quiz creation form 2. Fill all required fields with valid data 3. Click "Tạo quiz" | D45: - Form validates successfully - Quiz is created - Success notification appears - Quiz appears in section - Section shows updated item count | E45: - All fields filled correctly | F45: Passed | G45: 45998 | H45: TuanCM | I45: Passed | J45: 46001 | K45: TuanCM | L45: Passed | M45: 46003 | N45: TuanCM | O45: Question addition is separate workflow
A46: [Update course - 24] | B46: Test initial pricing status display | C46: 1. Access pricing page for course without price set 2. Observe "Giá hiện tại" section | D46: - Status section shows: + Green dollar sign icon + "Giá hiện tại" heading + "Khóa học chưa được định giá" message in green - Guidelines displayed: + "Khóa học trả phí nên có giá trị rõ ràng và nội dung chất lượng" + "Bạn có thể thay đổi giá sau khi xuất bán" | E46: - Course has no price set | F46: Passed | G46: 45998 | H46: TuanCM | I46: Passed | J46: 46001 | K46: TuanCM | L46: Passed | M46: 46003 | N46: TuanCM
A47: [Update course - 25] | B47: Test pricing type options display | C47: 1. Access pricing page 2. Locate "Loại giá" section | D47: - Section displays with red asterisk (required) - Two radio button options: + "Miễn phí" with subtitle "Không yêu cầu thanh toán" + "Trả phí" with subtitle "Yêu cầu thanh toán" - One option can be selected at a time | E47: - Pricing page displayed | F47: Passed | G47: 45998 | H47: TuanCM | I47: Passed | J47: 46001 | K47: TuanCM | L47: Passed | M47: 46003 | N47: TuanCM
A48: [Update course - 26] | B48: Test selecting "Miễn phí" option | C48: 1. Access pricing page 2. Click "Miễn phí" radio button 3. Observe form changes | D48: - "Miễn phí" option is selected - Price input field is disabled or hidden - Warning message appears: "Bạn chưa lưu giá khóa học. Nhấn nút bên dưới để lưu thay đổi." - "Lưu thay đổi" button remains enabled | E48: - Pricing page displayed | F48: Passed | G48: 45998 | H48: TuanCM | I48: Passed | J48: 46001 | K48: TuanCM | L48: Passed | M48: 46003 | N48: TuanCM
A49: [Update course - 27] | B49: Test selecting "Trả phí" option | C49: 1. Access pricing page 2. Click "Trả phí" radio button 3. Observe form changes | D49: - "Trả phí" option is selected - "Giá khóa học (VNĐ)" input field appears/enables - Placeholder text: "Nhập giá khóa học (ví dụ: 100000)" - Suggested price buttons appear: 99,000đ, 199,000đ, 299,000đ, 499,000đ, 999,000đ5. "Gợi ý mức giá phổ biến:" label shown | E49: - Pricing page displayed | F49: Passed | G49: 45998 | H49: TuanCM | I49: Passed | J49: 46001 | K49: TuanCM | L49: Passed | M49: 46003 | N49: TuanCM
A50: [Update course - 28] | B50: Test saving free pricing | C50: 1. Select "Miễn phí" option 2. Click "Lưu thay đổi" button | D50: - Form submits successfully - Success toast appears: "Cập nhật giá khóa học thành công!" or similar - "Giá hiện tại" section updates to show: + "Miễn phí" + "Học viên có thể đăng ký miễn phí" - Warning message disappears5. Progress may update | E50: - "Miễn phí" selected | F50: Passed | G50: 45998 | H50: TuanCM | I50: Passed | J50: 46001 | K50: TuanCM | L50: Passed | M50: 46003 | N50: TuanCM
A51: [Update course - 29] | B51: Test saving paid pricing with valid price | C51: 1. Select "Trả phí" option 2. Enter valid price: "100000" or use suggested price 3. Click "Lưu thay đổi" | D51: - Form submits successfully - Success toast appears: "Cập nhật giá khóa học thành công!" - "Giá hiện tại" section updates to show the set price - Warning message disappears - Price is saved and displayed - Progress indicator may update | E51: - Valid price entered | F51: Passed | G51: 45998 | H51: TuanCM | I51: Passed | J51: 46001 | K51: TuanCM | L51: Passed | M51: 46003 | N51: TuanCM
A52: [Update course - 30] | B52: Test editing existing section | C52: 1. Navigate to course structure 2. Locate existing section 3. Click edit (pen) icon on section | D52: - Section edit form opens - Current section data is pre-filled - Title and description can be modified - Changes can be saved5. Section updates successfully | E52: - Course with at least one section exists | F52: Passed | G52: 45998 | H52: TuanCM | I52: Passed | J52: 46001 | K52: TuanCM | L52: Passed | M52: 46003 | N52: TuanCM
A53: [Update course - 29] | B53: Test deleting section | C53: 1. Navigate to course structure 2. Locate section to delete 3. Click delete (trash) icon on section | D53: - Confirmation dialog appears - Warning about deleting all content in section - Can confirm or cancel deletion - If confirmed, section and all lessons are deleted - Section count updates - Success notification appears | E53: - Course with at least one section exists | F53: Passed | G53: 45998 | H53: TuanCM | I53: Passed | J53: 46001 | K53: TuanCM | L53: Passed | M53: 46003 | N53: TuanCM
A54: [Update course - 29] | B54: Test editing existing lesson | C54: 1. Navigate to section with lessons 2. Click edit icon on lesson 3. Modify lesson content 4. Save changes | D54: - Navigate to section with lessons - Click edit icon on lesson - Modify lesson content - Save changes | E54: - Section with at least one lesson exists | F54: Passed | G54: 45998 | H54: TuanCM | I54: Passed | J54: 46001 | K54: TuanCM | L54: Passed | M54: 46003 | N54: TuanCM
A55: [Update course - 30] | B55: Test deleting lesson | C55: 1. Navigate to section with lessons 2. Click delete icon on lesson 3. Confirm deletion | D55: 1. Confirmation dialog appears 2. Lesson is deleted after confirmation 3. Section item count decreases 4. Success notification appears5. Lesson is removed from view | E55: - Section with at least one lesson exists | F55: Passed | G55: 45998 | H55: TuanCM | I55: Passed | J55: 46001 | K55: TuanCM | L55: Passed | M55: 46003 | N55: TuanCM
A56: [Update course - 31] | B56: Test unpublish course | C56: 1. Navigate to course list 2. Locate draft course 3. Click delete (trash) icon 4. Confirm deletion | D56: - Confirmation dialog appears - Warning about permanent deletion - Course is deleted after confirmation - Course removed from list - Course statistics update - Success notification appears | E56: - At least one publish course exists | F56: Passed | G56: 45998 | H56: TuanCM | I56: Passed | J56: 46001 | K56: TuanCM | L56: Passed | M56: 46003 | N56: TuanCM
A57: Course Progress Tracking and Completion
A58: [Progress Tracking - 1] | B58: Test "Đề xuất khóa học" button enabled at 100% | C58: 1. Complete all course requirements (100%) 2. Locate "Đề xuất khóa học" section | D58: - Button changes to enabled state - Green background color - Text: "Đề xuất khóa học" - Button is clickable5. Hover state shows interaction possibility | E58: - 100% progress achieved | F58: Passed | G58: 45998 | H58: TuanCM | I58: Passed | J58: 46001 | K58: TuanCM | L58: Passed | M58: 46003 | N58: TuanCM
A59: [Progress Tracking - 2] | B59: Test submitting course for approval | C59: 1. Complete course to 100% 2. Click "Đề xuất khóa học" button 3. Confirm submission if dialog appears | D59: - Confirmation dialog may appear - Course status changes from "Nháp" to "Chờ duyệt" - Success notification appears - Course can no longer be edited (or editing is restricted) - Submission is recorded - User is redirected or stays on page with updated status | E59: - "Đề xuất khóa học" clicked | F59: Passed | G59: 45998 | H59: TuanCM | I59: Passed | J59: 46001 | K59: TuanCM | L59: Passed | M59: 46003 | N59: TuanCM
A60: [Progress Tracking - 3] | B60: Test "Đề xuất khóa học" button state when incomplete | C60: 1. Create course with less than 100% completion 2. Locate "Đề xuất khóa học" section | D60: - Button/section shows disabled state - Text displays: "Hoàn thành 100% để đề xuất" - Gray color indicates unavailable - Button cannot be clicked - Clear indication that more completion required | E60: - Progress less than 100% | F60: Passed | G60: 45998 | H60: TuanCM | I60: Passed | J60: 46001 | K60: TuanCM | L60: Passed | M60: 46003 | N60: TuanCM
A61: [Progress Tracking - 4] | B61: Test submitting course for approval | C61: 1. Complete course to 100% 2. Click "Đề xuất khóa học" button | D61: - Confirmation dialog may appear - Course status changes from "Nháp" to "Chờ duyệt" - Success notification appears - Course can no longer be edited (editing is restricted) - Submission is recorded - User is redirected to the course list | E61: - "Đề xuất khóa học" clicked | F61: Passed | G61: 45998 | H61: TuanCM | I61: Passed | J61: 46001 | K61: TuanCM | L61: Passed | M61: 46003 | N61: TuanCM
A62: Unpublish course
A63: [Unpublish course - 31] | B63: Test unpublish course | C63: 1. Navigate to course list 2. Locate draft course 3. Click delete (trash) icon 4. Confirm deletion | D63: - Confirmation dialog appears - Warning about permanent deletion - Course is deleted after confirmation - Course removed from list - Course statistics update - Success notification appears | E63: - At least one publish course exists | F63: Passed | G63: 45998 | H63: TuanCM | I63: Passed | J63: 46001 | K63: TuanCM | L63: Passed | M63: 46003 | N63: TuanCM
A64: Quiz Question Management
A65: [Quiz - 1] | B65: Test accessing question management from quiz | C65: 1. Navigate to course structure page 2. Locate an existing quiz (e.g., "quiz 1") 3. Click "+ Thêm câu hỏi" button on the quiz | D65: - Question bank drawer opens from right side - Drawer displays heading "Ngân hàng câu hỏi" - Shows summary: "1 chương • 9 câu hỏi" - "Tạo mới thủ công" button visible in top right (yellow) - Search box "Tìm kiếm câu hỏi..." is displayed - "Quay lại" back button visible | E65: - Quiz exists in section - Quiz created with title, pass percentage (70%), and timer (15 phút) | F65: Passed | G65: 45998 | H65: TuanCM | I65: Passed | J65: 46001 | K65: TuanCM | L65: Passed | M65: 46003 | N65: TuanCM
A66: [Quiz - 2] | B66: Test empty question bank state | C66: 1. Create new quiz in empty course 2. Click "+ Thêm câu hỏi" 3. Observe empty state display | D66: - Question bank drawer opens - Shows "0 chương • 0 câu hỏi" - Empty state message displays: + "Chưa có câu hỏi nào" + Prompt to create first question - "Tạo mới thủ công" button is primary action - No question list displayed | E66: - Quiz exists but no questions created yet - Question bank is empty | F66: Passed | G66: 45998 | H66: TuanCM | I66: Passed | J66: 46001 | K66: TuanCM | L66: Passed | M66: 46003 | N66: TuanCM
A67: Quick Selection Tools
A68: [Question Select - 1] | B68: Test "Tất cả" selection button | C68: 1. Open question bank 2. Click "Tất cả (9)" button in "Chọn cơ bản" | D68: - All questions in the list are selected automatically - Checkboxes for all questions become checked - Selected questions highlight (blue background) - Count indicator updates - "Thêm câu hỏi" button shows total count in parentheses | E68: - Question bank has questions | F68: Passed | G68: 45998 | H68: TuanCM | I68: Passed | J68: 46001 | K68: TuanCM | L68: Passed | M68: 46003 | N68: TuanCM
A69: [Question Select - 2] | B69: Test "Chọn nhanh theo số lượng" quick quantity selection | C69: 1. Open question bank 2. Locate "Chọn nhanh theo số lượng" section 3. Observe quantity buttons | D69: - Section displays number buttons: - "5", "10", "15", "20", "25" - Custom number input field shows default "5" - Two mode buttons below: + "Đầu tiên" with checkmark + "Ngẫu nhiên" with shuffle icon | E69: - Question bank has questions | F69: Passed | G69: 45998 | H69: TuanCM | I69: Passed | J69: 46001 | K69: TuanCM | L69: Passed | M69: 46003 | N69: TuanCM
A70: [Question Select - 3] | B70: Test custom quantity input | C70: 1. Open question bank 2. Click in custom number input field 3. Enter custom number (e.g., "7") 4. Press Enter | D70: - Input field accepts numeric value - Value appears in field - Corresponding number of questions are selected - Selection follows current mode (Đầu tiên/Ngẫu nhiên) | E70: - Question bank has sufficient questions | F70: Passed | G70: 45998 | H70: TuanCM | I70: Passed | J70: 46001 | K70: TuanCM | L70: Passed | M70: 46003 | N70: TuanCM
A71: [Question Select - 4] | B71: Test "Đầu tiên" (first) selection mode | C71: 1. Open question bank 2. Select "Đầu tiên" mode button 3. Choose quantity (e.g., "10") | D71: - "Đầu tiên" button shows active/selected state - First 10 questions from top of list are selected - Questions selected in sequential order - Selection follows question numbering (#1, #2, #3...) | E71: - Question bank has questions | F71: Passed | G71: 45998 | H71: TuanCM | I71: Passed | J71: 46001 | K71: TuanCM | L71: Passed | M71: 46003 | N71: TuanCM
A72: [Question Select - 5] | B72: Test "Ngẫu nhiên" (random) selection mode | C72: 1. Open question bank 2. Select "Ngẫu nhiên" mode button 3. Choose quantity (e.g., "10") 4. Observe selection pattern | D72: - "Ngẫu nhiên" button shows active state - 10 questions are selected randomly - Selection order is not sequential - Random questions from different positions are selected - Exact questions may vary on repeated attempts | E72: - Question bank has questions | F72: Passed | G72: 45998 | H72: TuanCM | I72: Passed | J72: 46001 | K72: TuanCM | L72: Passed | M72: 46003 | N72: TuanCM
A73: Manual Question Creation
A74: [Manual - 1] | B74: Test opening manual question creation form | C74: 1. Open question bank drawer 2. Click "Tạo mới thủ công" button (yellow button in top right) | D74: - Manual question creation form appears - Drawer transitions to creation form - Form displays title "Tạo câu hỏi mới" - Close (X) button visible in top right - Form shows all required fields | E74: - Question bank drawer open | F74: Passed | G74: 45998 | H74: TuanCM | I74: Passed | J74: 46001 | K74: TuanCM | L74: Passed | M74: 46003 | N74: TuanCM
A75: [Manual - 2] | B75: Test question text editor | C75: 1. Open manual creation form 2. Click in "Câu hỏi" editor 3. Type question text | D75: - Rich text editor displays with toolbar - Placeholder: "Nhập câu hỏi của bạn..." - Text can be formatted | E75: - Form is open | F75: Passed | G75: 45998 | H75: TuanCM | I75: Passed | J75: 46001 | K75: TuanCM | L75: Passed | M75: 46003 | N75: TuanCM
A76: [Manual - 3] | B76: Test successful single choice question creation | C76: 1. Enter question text in editor 2. Select "Một đáp án đúng" 3. Enter answers A and B 4. Select answer A as correct 5. Click "Tạo câu hỏi" | D76: - Form validates successfully - Question is created - Success toast appears: "Thêm câu hỏi thành công" - Second toast: "Câu hỏi đã được thêm!" - Form closes - Question appears in question bank - Question is automatically added to current quiz | E76: - All required fields filled correctly | F76: Passed | G76: 45998 | H76: TuanCM | I76: Passed | J76: 46001 | K76: TuanCM | L76: Passed | M76: 46003 | N76: TuanCM
A77: [Manual - 4] | B77: Test successful multiple choice question creation | C77: 1. Enter question text 2. Select "Nhiều đáp án đúng" 3. Enter 4 answers 4. Mark 2 answers as correct 5. Click "Tạo câu hỏi" | D77: - Form validates successfully (2 correct answers) - Question is created3. Success toast: "Thêm câu hỏi thành công" - Second toast: "Câu hỏi đã được thêm!" - Form closes - Question added to question bank - Question added to current quiz | E77: - Multiple choice with 2+ correct answers | F77: Passed | G77: 45998 | H77: TuanCM | I77: Passed | J77: 46001 | K77: TuanCM | L77: Passed | M77: 46003 | N77: TuanCM
A78: Question Management
A79: [Question Management - 1] | B79: Test editing question from quiz | C79: 1. Have quiz with questions 2. Click edit (pencil) icon on a question 3. Modify question 4. Save changes | D79: - Edit form opens with question data - All fields are editable - Changes can be saved - Updated question displays in quiz - Changes reflect in question bank | E79: - Questions exist in quiz | F79: Passed | G79: 45998 | H79: TuanCM | I79: Passed | J79: 46001 | K79: TuanCM | L79: Passed | M79: 46003 | N79: TuanCM
A80: [Question Management - 2] | B80: Test deleting question from quiz | C80: 1. Have quiz with questions 2. Click delete (trash) icon 3. Confirm deletion | D80: - Confirmation dialog appears - Warning about removing question - Question removed from quiz after confirmation - Quiz question count decreases - Question may remain in question bank | E80: - Questions exist in quiz | F80: Passed | G80: 45998 | H80: TuanCM | I80: Passed | J80: 46001 | K80: TuanCM | L80: Passed | M80: 46003 | N80: TuanCM
A81: [Question Management - 3] | B81: Test viewing question details in quiz | C81: 1. Have quiz with added questions 2. Locate a question card 3. Click eye (view) icon | D81: 1. View/preview modal 2. Shows complete question details 3. Can close preview 4. Read-only view | E81: - Questions exist in quiz | F81: Passed | G81: 45998 | H81: TuanCM | I81: Passed | J81: 46001 | K81: TuanCM | L81: Passed | M81: 46003 | N81: TuanCM

Sheet AI Assistant
A2: Workflow | B2: AI assistant | R2: Passed
A3: Test requirement | B3: Perform of AI assistant for student learning | R3: Failed
A4: Number of TCs | B4: 5 | R4: Pending
A5: Testing Round | B5: Passed | C5: Failed | D5: Pending | E5: N/A | R5: N/A
A6: Round 1 | B6: =COUNTIF($F10:$F867,B5) -> 5 | C6: =COUNTIF($F10:$F867,C5) -> 0 | D6: =COUNTIF($F10:$F867,D5) -> 0 | E6: =COUNTIF($F10:$F867,E5) -> 0
A7: Round 2 | B7: =COUNTIF($F10:$F867,B5) -> 5 | C7: =COUNTIF($F10:$F867,C5) -> 0 | D7: =COUNTIF($F10:$F867,D5) -> 0 | E7: =COUNTIF($F10:$F867,E5) -> 0
A8: Round 3 | B8: =COUNTIF($F10:$F867,B5) -> 5 | C8: =COUNTIF($F10:$F867,C5) -> 0 | D8: =COUNTIF($F10:$F867,D5) -> 0 | E8: =COUNTIF($F10:$F867,E5) -> 0
A10: Test Case ID | B10: Test Case Description | C10: Test Case Procedure | D10: Expected Results | E10: Pre-conditions | F10: Round 1 | G10: Test date | H10: Tester | I10: Round 2 | J10: Test date | K10: Tester | L10: Round 3 | M10: Test date | N10: Tester | O10: Note
A11: AI response
A12: [AI -1] | B12: Verify AI response to video content summary request | C12: 1. Open chat with AI assistant 2. Type: "Nội dung của video này là gì?" 3. Send message4. Observe response | D12: - AI provides comprehensive summary of video content- Response includes main topics: null, undefined in JavaScript - Mentions 4 cases when undefined appears - Mentions null vs undefined comparison - Mentions Symbol data type - Response in Vietnamese | E12: - Login as Student - Own a course that has AI assist | F12: Passed | G12: 45998 | H12: TuanCM | I12: Passed | J12: 46001 | K12: TuanCM | L12: Passed | M12: 46003 | N12: TuanCM
A13: [AI -1] | B13: Verify AI response to irrelevant/nonsense input | C13: 1. Open chat with AI assistant 2. Type: "123" 3. Send message 4. Observe response | D13: - AI recognizes irrelevant input - Polite message indicating question is not related to lesson content - Suggests asking different question about the subtitle content - Response format: "Chào bạn, câu hỏi '123' không phải là một câu hỏi liên quan..." | E13: - Login as Student - Own a course that has AI assist | F13: Passed | G13: 45998 | H13: TuanCM | I13: Passed | J13: 46001 | K13: TuanCM | L13: Passed | M13: 46003 | N13: TuanCM
A14: [AI -1] | B14: Verify AI response to explicit summary request | C14: 1. Type: "Bạn có thể tóm tắt nội dung của video trên?" 2. Send message 3. Observe response | D14: - AI provides detailed summary - Greeting: "Chào bạn, SkillUp đây" - Summary covers all main points systematically - Mentions undefined cases clearly - Mentions null vs undefined comparison - Includes Symbol characteristics | E14: - Login as Student - Own a course that has AI assist | F14: Passed | G14: 45998 | H14: TuanCM | I14: Passed | J14: 46001 | K14: TuanCM | L14: Passed | M14: 46003 | N14: TuanCM
A15: [AI -1] | B15: Verify AI response to request for specific examples | C15: 1. Type: "Bạn có thể cung cấp 1 ví dụ cụ thể không?" 2. Send message 3. Observe response | D15: - AI acknowledges the request politely - Explains that subtitle content describes cases but doesn't provide code examples - States lesson focuses on theory and definitions - Response starts with "Chào bạn, SkillUp rất vui được hỗ trợ bạn" - Honest about content limitations | E15: Previous conversation exists | F15: Passed | G15: 45998 | H15: TuanCM | I15: Passed | J15: 46001 | K15: TuanCM | L15: Passed | M15: 46003 | N15: TuanCM
A16: [AI -1] | B16: Verify multilingualism | C16: 1. Type: "Can you summary this video ?" 2. Send message 3. Observe response | D16: - AI provides comprehensive summary of video content- Response includes main topics: null, undefined in JavaScript - Mentions 4 cases when undefined appears - Mentions null vs undefined comparison - Mentions Symbol data type - Response in Vietnamese" | E16: - Login as Student - Own a course that has AI assist | F16: Passed | G16: 45998 | H16: TuanCM | I16: Passed | J16: 46001 | K16: TuanCM | L16: Passed | M16: 46003 | N16: TuanCM

Sheet Workflow of System Moderator
A2: Workflow | B2: Workflow of System Moderator | R2: Passed
A3: Test requirement | B3: Check if the functionalities of System Moderator role work well. | R3: Failed
A4: Number of TCs | B4: 15 | R4: Pending
A5: Testing Round | B5: Passed | C5: Failed | D5: Pending | E5: N/A | R5: N/A
A6: Round 1 | B6: =COUNTIF($F10:$F1015,B5) -> 15 | C6: =COUNTIF($F10:$F1015,C5) -> 0 | D6: =COUNTIF($F10:$F1015,D5) -> 0 | E6: =COUNTIF($F10:$F1015,E5) -> 0
A7: Round 2 | B7: =COUNTIF($F10:$F1015,B5) -> 15 | C7: =COUNTIF($F10:$F1015,C5) -> 0 | D7: =COUNTIF($F10:$F1015,D5) -> 0 | E7: =COUNTIF($F10:$F1015,E5) -> 0
A8: Round 3 | B8: =COUNTIF($F10:$F1015,B5) -> 15 | C8: =COUNTIF($F10:$F1015,C5) -> 0 | D8: =COUNTIF($F10:$F1015,D5) -> 0 | E8: =COUNTIF($F10:$F1015,E5) -> 0
A10: Test Case ID | B10: Test Case Description | C10: Test Case Procedure | D10: Expected Results | E10: Pre-conditions | F10: Round 1 | G10: Test date | H10: Tester | I10: Round 2 | J10: Test date | K10: Tester | L10: Round 3 | M10: Test date | N10: Tester | O10: Note
A11: Ticket Features
A12: [Ticket - 1] | B12: View ticket list for Students/Lecturer | C12: 1. Login the system with the Student/Lecturer Role. 2. Click the "Phiếu hỗ trợ" tab in the header menu. | D12: The ticket list is displayed correctly with the following informations: - Ticket filter - Create new Ticket button - The list of that user's submitted tickets along with view Details button for each | E12: - The server must be working - User role must be Student or Lecturer - The account status must be "Active" | F12: Passed | G12: 45998 | H12: TuanCM | I12: Passed | J12: 46001 | K12: TuanCM | L12: Passed | M12: 46003 | N12: TuanCM
A13: [Ticket - 2] | B13: Verify filter functionality of the View ticket list for Student/Lecturer screen | C13: 1. Login the system with the Student/Lecturer Role. 2. Click the "Phiếu hỗ trợ" tab in the header menu. 3. Click the "Phiếu đã duyệt", "Phiếu bị từ chối" or "Tất cả phiếu" in the filter menu on the left. | D13: The ticket list is displayed correctly corresponding to the selected filter with the following informations: - Ticket filter - Create new Ticket button - The list of that user's submitted tickets along with view Details button for each | E13: - The server must be working - User role must be Student or Lecturer - The account status must be "Active" | F13: Passed | G13: 45998 | H13: TuanCM | I13: Passed | J13: 46001 | K13: TuanCM | L13: Passed | M13: 46003 | N13: TuanCM
A14: [Ticket - 3] | B14: Verify the Create new Ticket feature | C14: 1. Login the system with the Student/Lecturer Role. 2. Click the "Phiếu hỗ trợ" tab in the header menu. 3. Click the "Tạo phiếu mới" button on the left. 4. Input the "Tiêu đề" and "Nội dung" field for Title and Content in the popup window. 5. Click the "Tạo phiếu" button. | D14: - Successfully create a new Ticket in the system, which can be found in the User's ticket list and System Moderator Ticket List. - The newly created Ticket display the inputted informations correctly. | E14: - The server must be working - User role must be Student or Lecturer - The account status must be "Active" | F14: Passed | G14: 45998 | H14: TuanCM | I14: Passed | J14: 46001 | K14: TuanCM | L14: Passed | M14: 46003 | N14: TuanCM
A15: [Ticket - 4] | B15: Test the Create new Ticket with empty Title. | C15: 1. Login the system with the Student/Lecturer Role. 2. Click the "Phiếu hỗ trợ" tab in the header menu. 3. Click the "Tạo phiếu mới" button on the left. 4. Leave the "Tiêu đề" input fields blank. 5. Click the "Tạo phiếu" button. | D15: - The system send out error message below the blank inputted field. - No new Ticket is created. | E15: - The server must be working - User role must be Student or Lecturer - The account status must be "Active" | F15: Passed | G15: 45998 | H15: TuanCM | I15: Passed | J15: 46001 | K15: TuanCM | L15: Passed | M15: 46003 | N15: TuanCM
A16: [Ticket - 5] | B16: Test the Create new Ticket with empty Content. | C16: 1. Login the system with the Student/Lecturer Role. 2. Click the "Phiếu hỗ trợ" tab in the header menu. 3. Click the "Tạo phiếu mới" button on the left. 4. Leave the "Nội dung" input fields blank. 5. Click the "Tạo phiếu" button. | D16: - The system send out error message below the blank inputted field. - No new Ticket is created. | E16: - The server must be working - User role must be Student or Lecturer - The account status must be "Active" | F16: Passed | G16: 45998 | H16: TuanCM | I16: Passed | J16: 46001 | K16: TuanCM | L16: Passed | M16: 46003 | N16: TuanCM
A17: [Ticket - 6] | B17: Verify the View Ticket Details feature. | C17: 1. Login the system with the Student/Lecturer Role. 2. Click the "Phiếu hỗ trợ" tab in the header menu. 3. Click the "Xem" button on the right of a ticket. | D17: The ticket details page is displayed correctly with the following informations: - User's name - Submitted date and time - Response of the System Moderator - Ticket's Code - Ticket's Status | E17: - The server must be working - User role must be Student or Lecturer - The account status must be "Active" | F17: Passed | G17: 45998 | H17: TuanCM | I17: Passed | J17: 46001 | K17: TuanCM | L17: Passed | M17: 46003 | N17: TuanCM
A18: [Ticket - 7] | B18: Verify the View Ticket Details feature. | C18: 1. Login the system with the Student/Lecturer Role. 2. Click the "Phiếu hỗ trợ" tab in the header menu. 3. Click the "Xem" button on the right of a ticket. | D18: The ticket details page is displayed correctly with the following informations: - User's name - Submitted date and time - Response of the System Moderator - Ticket's Code - Ticket's Status | E18: - The server must be working - User role must be Student or Lecturer - The account status must be "Active" | F18: Passed | G18: 45998 | H18: TuanCM | I18: Passed | J18: 46001 | K18: TuanCM | L18: Passed | M18: 46003 | N18: TuanCM
A19: [Ticket - 8] | B19: Verify the Update Ticket feature. | C19: 1. Login the system with the Student/Lecturer Role. 2. Click the "Phiếu hỗ trợ" tab in the header menu. 3. Click the "Xem" button on the right of a ticket. 4. Click the "Cập nhật phiếu" button on the right. 5. Edit the fields informations of the Ticket. 6. Click the "Lưu thay đổi" button | D19: - Successfully update the Ticket in the system. - The updated Ticket display the inputted informations correctly. | E19: - The server must be working - User role must be Student or Lecturer - The account status must be "Active" - The Ticket status must be "Pending" | F19: Passed | G19: 45998 | H19: TuanCM | I19: Passed | J19: 46001 | K19: TuanCM | L19: Passed | M19: 46003 | N19: TuanCM
A20: [Ticket - 9] | B20: Test the Update Ticket with empty Title. | C20: 1. Login the system with the Student/Lecturer Role. 2. Click the "Phiếu hỗ trợ" tab in the header menu. 3. Click the "Xem" button on the right of a ticket. 4. Click the "Cập nhật phiếu" button on the right. 5. Leave the "Tiêu đề" field blank . 6. Click the "Lưu thay đổi" button | D20: - The system send out error message below the blank inputted field. - No update is made. | E20: - The server must be working - User role must be Student or Lecturer - The account status must be "Active" - The Ticket status must be "Pending" | F20: Passed | G20: 45998 | H20: TuanCM | I20: Passed | J20: 46001 | K20: TuanCM | L20: Passed | M20: 46003 | N20: TuanCM
A21: [Ticket - 10] | B21: Test the Update Ticket with empty Content. | C21: 1. Login the system with the Student/Lecturer Role. 2. Click the "Phiếu hỗ trợ" tab in the header menu. 3. Click the "Xem" button on the right of a ticket. 4. Click the "Cập nhật phiếu" button on the right. 5. Leave the "Nội dung" field blank . 6. Click the "Lưu thay đổi" button | D21: - The system send out error message below the blank inputted field. - No update is made. | E21: - The server must be working - User role must be Student or Lecturer - The account status must be "Active" - The Ticket status must be "Pending" | F21: Passed | G21: 45998 | H21: TuanCM | I21: Passed | J21: 46001 | K21: TuanCM | L21: Passed | M21: 46003 | N21: TuanCM
A22: View Lecturer Applications
A23: [View Applications - 1] | B23: Verify application management interface | C23: 1. Login as Content Moderator with valid credentials 2. Navigate to "Quản lý ứng tuyển " 3. Observe page layout and content | D23: - Page loads without errors - Page title displays: "Quản lý đơn ứng tuyển giảng viên" - Application list table visible with columns: Name, Email, Phone, Status, Actions - Status badges display correctly | E23: - Valid moderator account exists - User has "Content Moderator" role assigned | F23: Passed | G23: 45998 | H23: TuanCM | I23: Passed | J23: 46001 | K23: TuanCM | L23: Passed | M23: 46003 | N23: TuanCM
A24: [View Applications - 2] | B24: Verify pending lecturer applications display in list | C24: 1. Access Lecturer Application Management page 2. Observe applications with "Pending" status 3. Count visible pending applications 4. Verify action buttons present | D24: - Pending applications show amber/yellow "Chờ xử lý" badge - Each pending row displays two action buttons: "Duyệt" (green) and "Từ chối" (red) - All applicant information visible: Name, Email, Phone, Submission date | E24: - At least one pending lecturer application exists - Lecturer has submitted registration form | F24: Passed | G24: 45998 | H24: TuanCM | I24: Passed | J24: 46001 | K24: TuanCM | L24: Passed | M24: 46003 | N24: TuanCM
A25: [View Applications - 3] | B25: Verify uploaded documents are accessible in detail view | C25: 1. Open application detail modal 2. Locate "Tài liệu chứng nhận" section 3. Observe document list 4. Click on document to view/download | D25: - Document section displays list of uploaded files - Each file shows: filename, file type icon, file size - Download button or link available for each file - Clicking opens document in new tab or downloads - PDF files preview or download correctly - Image files display thumbnail or preview | E25: Applicant uploaded qualification documents during registration | F25: Passed | G25: 45998 | H25: TuanCM | I25: Passed | J25: 46001 | K25: TuanCM | L25: Passed | M25: 46003 | N25: TuanCM
A26: Resovle Lecturer Applications
A27: [Resovle - 1] | B27: Verify approval with optional feedback message | C27: 1. Open approve confirmation modal 2. Type feedback: "Hồ sơ đầy đủ, đạt yêu cầu" 3. Click "Xác nhận phê duyệt" 4. Observe completion | D27: - Text input accepted in textarea - Submit button processes request - Loading state displayed - Success toast: "Phê duyệt giảng viên thành công!" - Modal closes - Application status changes to "Đã Chấp nhận" | E27: - Approve modal open | F27: Passed | G27: 45998 | H27: TuanCM | I27: Passed | J27: 46001 | K27: TuanCM | L27: Passed | M27: 46003 | N27: TuanCM
A28: [Resovle - 2] | B28: Verify rejection submission with valid reason | C28: 1. Open reject modal 2. Enter valid rejection reason: "Kinh nghiệm giảng dạy chưa đủ 2 năm" 3. Click "Xác nhận từ chối" 4. Observe UI feedback | D28: - Button shows loading state: spinner and "Đang xử lý..." - After completion: - Success toast: "Từ chối đơn đăng ký thành công!" - Toast has red/orange background - Modal closes automatically - Application status updates to "Từ chối" (red badge) - Application moves to rejected section/filter - List refreshes showing updated status | E28: Valid rejection reason entered | F28: Passed | G28: 45998 | H28: TuanCM | I28: Passed | J28: 46001 | K28: TuanCM | L28: Passed | M28: 46003 | N28: TuanCM

Sheet Workflow of Content Morderator
A2: Workflow | B2: Workflow of Content Moderator | R2: Passed
A3: Test requirement | B3: Check if the functionalities of Content Moderator role work well. | R3: Failed
A4: Number of TCs | B4: 32 | R4: Pending
A5: Testing Round | B5: Passed | C5: Failed | D5: Pending | E5: N/A | R5: N/A
A6: Round 1 | B6: =COUNTIF($F10:$F1008,B5) -> 32 | C6: =COUNTIF($F10:$F1008,C5) -> 0 | D6: =COUNTIF($F10:$F1008,D5) -> 0 | E6: =COUNTIF($F10:$F1008,E5) -> 0
A7: Round 2 | B7: =COUNTIF($F10:$F1008,B5) -> 32 | C7: =COUNTIF($F10:$F1008,C5) -> 0 | D7: =COUNTIF($F10:$F1008,D5) -> 0 | E7: =COUNTIF($F10:$F1008,E5) -> 0
A8: Round 3 | B8: =COUNTIF($F10:$F1008,B5) -> 32 | C8: =COUNTIF($F10:$F1008,C5) -> 0 | D8: =COUNTIF($F10:$F1008,D5) -> 0 | E8: =COUNTIF($F10:$F1008,E5) -> 0
A10: Test Case ID | B10: Test Case Description | C10: Test Case Procedure | D10: Expected Results | E10: Pre-conditions | F10: Round 1 | G10: Test date | H10: Tester | I10: Round 2 | J10: Test date | K10: Tester | L10: Round 3 | M10: Test date | N10: Tester | O10: Note
A11: Manage News Features
A12: [News - 1] | B12: View news management list | C12: 1. Log in as Content Moderator. 2. Navigate to "Quản lý tin tức". | D12: 1. The system displays a paginated table of news items. 2. The table must show columns for "Tiêu đề", "Email Tác giả", and "Ngày đăng", "Hành động". | E12: 1. User must be logged in with a 'Content Moderator' account. 2. User must navigate to the 'News Management' section/page. 3. The system must have existing news data (created by various authors at different dates) for sorting, searching, updating, and deleting test cases. 4. Content Moderator account exists. | F12: Passed | G12: 45998 | H12: TuanCM | I12: Passed | J12: 46001 | K12: TuanCM | L12: Passed | M12: 46003 | N12: TuanCM
A13: [News - 2] | B13: Creating a new news item - Happy Path | C13: 1. Click the "Thêm tin tức" button. 2. Fill in a valid Title. 3. Fill in the Content (text). 4. Upload one or more valid Images (e.g., .jpg, .png). 5. Click "Tạo". | D13: 1. The news item is successfully created. 2. The system redirects back to the news list. 3. The newly created item appears at the top of the list (assuming default sort is 'newest first'). | E13: Content Moderator account has 'Create' permissions. | F13: Passed | G13: 45998 | H13: TuanCM | I13: Passed | J13: 46001 | K13: TuanCM | L13: Passed | M13: 46003 | N13: TuanCM
A14: [News -3] | B14: Validation on Create (Missing Title) | C14: 1. Click the "Thêm tin tức" button. 2. Leave the Title blank. 3. Fill in the Content (text). 4. Upload one or more valid Images (e.g., .jpg, .png). 5. Click "Tạo". | D14: 1. An toast validation warning ("Hãy điền đủ thông tin") appears. 2. The news item is not created. | F14: Passed | G14: 45998 | H14: TuanCM | I14: Passed | J14: 46001 | K14: TuanCM | L14: Passed | M14: 46003 | N14: TuanCM
A15: [News - 4] | B15: Editing an existing news item | C15: 1. From the table, find a news item and click "Sửa". 2. Change the Title. 3. Modify the Content text. 4. Remove one image and add a new one. 5. Click "Lưu". | D15: 1. The changes are saved successfully. 2. When viewing the list and the details, the new Title, Content, and Images are displayed. | E15: At least one news item exists to edit. | F15: Passed | G15: 45998 | H15: TuanCM | I15: Passed | J15: 46001 | K15: TuanCM | L15: Passed | M15: 46003 | N15: TuanCM
A16: [News - 5] | B16: Deleting a news item | C16: 1. From the list, find a news item and click "Xóa". 2. A confirmation modal appears ("Bạn có chắc chắn muốn xóa tin tức này không?"). 3. Click "Xóa". | D16: 1. The item is removed from the database. 2. The item disappears from the news list. | E16: At least one news item exists to delete. | F16: Passed | G16: 45998 | H16: TuanCM | I16: Passed | J16: 46001 | K16: TuanCM | L16: Passed | M16: 46003 | N16: TuanCM
A17: [News - 6] | B17: Canceling a deletion | C17: 1. From the list, find a news item and click "Xóa". 2. A confirmation modal appears ("Bạn có chắc chắn muốn xóa tin tức này không?"). 3. Click "Hủy". | D17: 1. The confirmation model closes. 2. The news item remains visible in the list. | F17: Passed | G17: 45998 | H17: TuanCM | I17: Passed | J17: 46001 | K17: TuanCM | L17: Passed | M17: 46003 | N17: TuanCM
A18: [News - 7] | B18: Search by Title (Results Found) | C18: 1. Identify the title of an existing news item ("test"). 2. Enter "test" into the search bar. | D18: The list refreshes to show only the news item(s) matching that title. | E18: A news item with the title "test" exists. | F18: Passed | G18: 45998 | H18: TuanCM | I18: Passed | J18: 46001 | K18: TuanCM | L18: Passed | M18: 46003 | N18: TuanCM
A19: [News - 8] | B19: Search by Title (No Results) | C19: 1. Enter a random string (e.g., "XYZ123ABC") into the search bar. | D19: 1. The list becomes empty. 2. A "Không tìm thấy dữ liệu" text is displayed in the table. | F19: Passed | G19: 45998 | H19: TuanCM | I19: Passed | J19: 46001 | K19: TuanCM | L19: Passed | M19: 46003 | N19: TuanCM
A20: [News - 9] | B20: Search by Email Author (Results Found) | C20: 1. Identify an existing author email ("user@example.com"). 2. Enter "user@example.com" into the search bar. | D20: The list refreshes to show only news items created by that specific email address. | E20: News items from "author@example.com" exist. | F20: Passed | G20: 45998 | H20: TuanCM | I20: Passed | J20: 46001 | K20: TuanCM | L20: Passed | M20: 46003 | N20: TuanCM
A21: [News - 10] | B21: Filter by Date Range | C21: 1. Click the Date Filter dropdown. 2. Select the "7 ngày trước" option. | D21: The list updates to show only news items with a Created Date within the last 7 days (inclusive of today). | E21: Must have news items created within the last 7 days AND before the last 7 days. | F21: Passed | G21: 45998 | H21: TuanCM | I21: Passed | J21: 46001 | K21: TuanCM | L21: Passed | M21: 46003 | N21: TuanCM
A22: [News - 11] | B22: Sort by Date (Newest First) | C22: 1. Click the "Ngày đăng" column header. | D22: The list re-orders to show the most recently created news item at the top. | E22: At least 3 news items with different creation dates exist. | F22: Passed | G22: 45998 | H22: TuanCM | I22: Passed | J22: 46001 | K22: TuanCM | L22: Passed | M22: 46003 | N22: TuanCM
A23: [News - 12] | B23: Sort by Date (Oldest First) | C23: 1. Click the "Ngày đăng" column header. | D23: The list re-orders to show the oldest created news item at the top. | E23: At least 3 news items with different creation dates exist. | F23: Passed | G23: 45998 | H23: TuanCM | I23: Passed | J23: 46001 | K23: TuanCM | L23: Passed | M23: 46003 | N23: TuanCM
A24: [News - 13] | B24: View news details | C24: 1. On the news list, click on the Title of any news item. | D24: 1. A detail view (page or modal) opens. 2. All fields are displayed correctly: Title, Email Author, Created Date, Content (Text), and rendered Images. | E24: At least one news item exists. | F24: Passed | G24: 45998 | H24: TuanCM | I24: Passed | J24: 46001 | K24: TuanCM | L24: Passed | M24: 46003 | N24: TuanCM
A25: Course Manage
A26: [Course Manage - 1] | B26: Verify content moderator can access pending courses awaiting approval | C26: 1. Login as Content Moderator 2. Navigate to Course Management page 3. Click "Đang chờ duyệt" (Pending) tab 4. Verify course list displays | D26: 1. Pending tab shows badge count 2. List displays only courses with status = "Pending" 3. Each course shows: title, lecturer name, category, price, submission date 4. No "Draft" or "Public" courses visible in this tab. | E26: 1. Moderator is logged in 2. At least 1 course with status = "Pending" exists 3. Lecturer has submitted course for review | F26: Passed | G26: 45998 | H26: TuanCM | I26: Passed | J26: 46001 | K26: TuanCM | L26: Passed | M26: 46003 | N26: TuanCM
A27: [Course Manage - 2] | B27: Verify content moderator can approve course and publish it | C27: 1. Navigate to Pending courses 2. Select a course to approve 3. Click "Duyệt" (Approve) button 4. Enter optional feedback in modal 5. Click "Xác nhận duyệt" | D27: 1. Success toast: "Duyệt khóa học thành công!" 2. Course moves from "Pending" to "Public" tab 3. Course status changes to "Public" 4. Course becomes visible to students in catalog 5. API call: PUT /Course/Approve-Course/{courseId}? decision=true&reason={feedback} Lecturer receives notification (if implemented) | E27: 1. Course status = "Pending" 2. Course meets quality standards 3. Moderator has approval permissions | F27: Passed | G27: 45998 | H27: TuanCM | I27: Passed | J27: 46001 | K27: TuanCM | L27: Passed | M27: 46003 | N27: TuanCM
A28: [Course Manage - 3] | B28: Verify moderator can reject course with required reason | C28: 1. Navigate to Pending courses 2. Select a course to reject 3. Click "Từ chối" (Reject) button 4. Modal opens - DO NOT enter feedback 5. Try to submit 6. Enter valid rejection reason 7. Click "Từ chối" | D28: 1. Step 5: Error message "Vui lòng nhập lý do từ chối khóa học" 2. Step 7: Success toast "Từ chối khóa học thành công!" 3. Course moves to "Nháp" tab 4. Course status changes to "Draft" 5. Feedback saved and visible to lecturer | E28: 1. Course status = "Pending" 2. Course has quality issues or policy violations | F28: Passed | G28: 45998 | H28: TuanCM | I28: Passed | J28: 46001 | K28: TuanCM | L28: Passed | M28: 46003 | N28: TuanCM
A29: [Course Manage - 4] | B29: Verify content moderator can ban/suspend a course | C29: 1. Navigate to Public courses tab 2. Find course with "Hoạt động" (Active) status 3. Click "Cấm" (Ban) button 4. Wait for confirmation 5. Verify status change | D29: 1.Course isActive field changes to false 2. Status badge changes to "Bị cấm" (red) 3. Action button changes to "Bỏ Cấm" (Unban) 4. Success toast: "Cấm khóa học thành công!" 5. Course hidden from student catalog 6. Course remains in Public tab | E29: Course status = "Public" | F29: Passed | G29: 45998 | H29: TuanCM | I29: Passed | J29: 46001 | K29: TuanCM | L29: Passed | M29: 46003 | N29: TuanCM
A30: [Course Manage - 5] | B30: Verify content moderator can restore banned course | C30: 1. Navigate to Public courses tab 2. Filter or find course with "Bị cấm" (Banned) status 3. Click "Bỏ Cấm" (Unban) button 4. Verify status restoration | D30: 1. Course isActive field changes to true 2. Status badge changes to "Hoạt động" (green) 3. Action button changes to "Cấm" (Ban) 4. Success toast: "Bỏ cấm khóa học thành công!" 5. Course visible again in student catalog | E30: Course was previously banned | F30: Passed | G30: 45998 | H30: TuanCM | I30: Passed | J30: 46001 | K30: TuanCM | L30: Passed | M30: 46003 | N30: TuanCM
A31: Category Features
A32: [Category- 1] | B32: Test viewing list category | C32: 1. Login the system with Content Moderator role. 2. Click "Quản lý danh mục" in the left menu. | D32: - The "Quản lý danh mục" page is displayed with the title"Quản lý danh mục". - The list of categories and subcategory is loaded and displayed correctly. | E32: - The server must be working - User must exist in the system with the role "Content Moderator". - At least 1 Category and 1 SubCategory must exist in the database. | F32: Passed | G32: 45998 | H32: TuanCM | I32: Passed | J32: 46001 | K32: TuanCM | L32: Passed | M32: 46003 | N32: TuanCM
A33: [Category- 2] | B33: Test the Create new Category with empty Name. | C33: 1. Login the system with Content Moderator role. 2. Click "Quản lý danh mục" in the left menu. 3. Click button "Thêm danh mục" 4. Click "Lưu" | D33: - The system send out error message "Xin hãy nhập tên danh mục" | E33: - The server must be working - User role must be Content Moderator - The account status must be "Active" | F33: Passed | G33: 45998 | H33: TuanCM | I33: Passed | J33: 46001 | K33: TuanCM | L33: Passed | M33: 46003 | N33: TuanCM
A34: [Category- 3] | B34: Test the Create new Category already exists. | C34: 1. Login the system with Content Moderator role. 2. Click "Quản lý danh mục" in the left menu. 3. Enter the name of an existing category. 4. Click button "Thêm danh mục" 5. Click "Lưu" | D34: - The system send out error message "Tên danh mục đã tồn tại" | E34: - The server must be working - User role must be Content Moderator - The account status must be "Active" | F34: Passed | G34: 45998 | H34: TuanCM | I34: Passed | J34: 46001 | K34: TuanCM | L34: Passed | M34: 46003 | N34: TuanCM
A35: [Category - 4] | B35: Test the Create new Category - Happy Path | C35: 1. Login the system with Content Moderator role. 2. Click "Quản lý danh mục" in the left menu. 3. Enter the name of new category. 4. Click button "Thêm danh mục" 5. Click "Lưu" | D35: - The system send out error message "Tạo danh mục mới thành công" | E35: - The server must be working - User role must be Content Moderator - The account status must be "Active" | F35: Passed | G35: 45998 | H35: TuanCM | I35: Passed | J35: 46001 | K35: TuanCM | L35: Passed | M35: 46003 | N35: TuanCM
A36: [Category - 5] | B36: Test update the Category with empty Name | C36: 1. Login the system with Content Moderator role. 2. Click "Quản lý danh mục" in the left menu. 3. Remove Name . 4. Click button "Thêm danh mục" 5. Click "Lưu" | D36: - The system send out error message "Xin hãy nhập tên danh mục" | E36: - The server must be working - User role must be Content Moderator - The account status must be "Active" | F36: Passed | G36: 45998 | H36: TuanCM | I36: Passed | J36: 46001 | K36: TuanCM | L36: Passed | M36: 46003 | N36: TuanCM
A37: [Category - 6] | B37: Test update the Category with exist Name | C37: 1. Login the system with Content Moderator role. 2. Click "Quản lý danh mục" in the left menu. 3. Enter empty Name . 4. Click button "Thêm danh mục" 5. Click "Lưu" | D37: - The system send out error message "Tên danh mục đã tồn tại" | E37: - The server must be working - User role must be Content Moderator - The account status must be "Active" | F37: Passed | G37: 45998 | H37: TuanCM | I37: Passed | J37: 46001 | K37: TuanCM | L37: Passed | M37: 46003 | N37: TuanCM
A38: [Category - 7] | B38: Test the update Category - Happy Path | C38: 1. Login the system with Content Moderator role. 2. Click "Quản lý danh mục" in the left menu. 3. Remove name and enter new name of category 4. Click button "Thêm danh mục" 5. Click "Lưu" | D38: - The system send out error message "Tạo danh mục mới thành công" | E38: - The server must be working - User role must be Content Moderator - The account status must be "Active" | F38: Passed | G38: 45998 | H38: TuanCM | I38: Passed | J38: 46001 | K38: TuanCM | L38: Passed | M38: 46003 | N38: TuanCM
A39: [Category - 8] | B39: Test delete Category - Happy Path | C39: 1. Login the system with Content Moderator role. 2. Click "Quản lý danh mục" in the left menu. 3. Click icon "⋮" . 4. Click button "Xóa" | D39: - The system send out error message "Xóa danh mục thành công". - Category is removed from list category | E39: - The server must be working - User role must be Content Moderator - The account status must be "Active" | F39: Passed | G39: 45998 | H39: TuanCM | I39: Passed | J39: 46001 | K39: TuanCM | L39: Passed | M39: 46003 | N39: TuanCM
A40: [Category - 9] | B40: Test delete Category with ID does not exist | C40: 1. Login the system with Content Moderator role. 2. Click "Quản lý danh mục" in the left menu. 3. Click icon "⋮" . 4. Click button "Xóa" | D40: - The system send out error message "Không tìm thấy danh mục.". - Category cannot be deleted from list category | E40: - The server must be working - User role must be Content Moderator - The account status must be "Active" | F40: Passed | G40: 45998 | H40: TuanCM | I40: Passed | J40: 46001 | K40: TuanCM | L40: Passed | M40: 46003 | N40: TuanCM
A41: [Category - 10] | B41: Test viewing list category if there is no category in the data | C41: 1. Login the system with Content Moderator role. 2. Click "Quản lý danh mục" in the left menu. | D41: - The system send out error message "Danh mục đang trống". | E41: - The server must be working - User role must be Content Moderator - The account status must be "Active" | F41: Passed | G41: 45998 | H41: TuanCM | I41: Passed | J41: 46001 | K41: TuanCM | L41: Passed | M41: 46003 | N41: TuanCM
A42: [Category - 11] | B42: Test delete Category have subcategory | C42: 1. Login the system with Content Moderator role. 2. Click "Quản lý danh mục" in the left menu. 3. Click icon "⋮" . 4. Click button "Xóa" | D42: - The system send out error message "Không thể xóa danh mục chứa danh mục con.Vui lòng xóa các danh mục con trước". | E42: - The server must be working - User role must be Content Moderator - The account status must be "Active" | F42: Passed | G42: 45998 | H42: TuanCM | I42: Passed | J42: 46001 | K42: TuanCM | L42: Passed | M42: 46003 | N42: TuanCM
A43: [SubCategory - 10] | B43: Test viewing list sub category | C43: 1. Login the system with Content Moderator role. 2. Click "Quản lý danh mục" in the left menu. | D43: - The "Quản lý danh mục" page is displayed with the title"Quản lý danh mục". - The list of categories and subcategory is loaded and displayed correctly. | E43: - The server must be working - User role must be Content Moderator - The account status must be "Active" | F43: Passed | G43: 45998 | H43: TuanCM | I43: Passed | J43: 46001 | K43: TuanCM | L43: Passed | M43: 46003 | N43: TuanCM
... A45: [SubCategory - 12] | B45: Test viewing list category if there is no category in the data | C45: 1. Login the system with Content Moderator role. 2. Click "Quản lý danh mục" in the left menu. | D45: - The "Quản lý danh mục" page is displayed with the title"Quản lý danh mục". - The list of categories and subcategory is loaded and displayed correctly. | E45: - The server must be working - User role must be Content Moderator - The account status must be "Active" | F45: Passed | G45: 45998 | H45: TuanCM | I45: Passed | J45: 46001 | K45: TuanCM | L45: Passed | M45: 46003 | N45: TuanCM

Sheet Workflow of Admin
A2: Workflow | B2: Workflow of Admin | R2: Passed
A3: Test requirement | B3: Check if the functionalities of Admin role work well. | R3: Failed
A4: Number of TCs | B4: 16 | R4: Pending
A5: Testing Round | B5: Passed | C5: Failed | D5: Pending | E5: N/A | R5: N/A
A6: Round 1 | B6: =COUNTIF($F10:$F1007,B5) -> 16 | C6: =COUNTIF($F10:$F1007,C5) -> 0 | D6: =COUNTIF($F10:$F1007,D5) -> 0 | E6: =COUNTIF($F10:$F1007,E5) -> 0
A7: Round 2 | B7: =COUNTIF($F10:$F1007,B5) -> 16 | C7: =COUNTIF($F10:$F1007,C5) -> 0 | D7: =COUNTIF($F10:$F1007,D5) -> 0 | E7: =COUNTIF($F10:$F1007,E5) -> 0
A8: Round 3 | B8: =COUNTIF($F10:$F1007,B5) -> 16 | C8: =COUNTIF($F10:$F1007,C5) -> 0 | D8: =COUNTIF($F10:$F1007,D5) -> 0 | E8: =COUNTIF($F10:$F1007,E5) -> 0
A10: Test Case ID | B10: Test Case Description | C10: Test Case Procedure | D10: Expected Results | E10: Pre-conditions | F10: Round 1 | G10: Test date | H10: Tester | I10: Round 2 | J10: Test date | K10: Tester | L10: Round 3 | M10: Test date | N10: Tester | O10: Note
A11: Moderator Manage
A12: [Moderator Manage -1 ] | B12: Verify moderator list displays correctly | C12: 1. Login as Admin 2. Navigate to "Quản lý quản trị viên" 3. Observe the moderator list | D12: - All moderators display with: Avatar, Full name, ID, Email, Role badge, Status badge, Action buttons - Table shows pagination if > 5 records- Role badges show correct colors (purple for System, blue for Content) | E12: Admin logged in with valid credentials | F12: Passed | G12: 45998 | H12: TuanCM | I12: Passed | J12: 46001 | K12: TuanCM | L12: Passed | M12: 46003 | N12: TuanCM
A13: [Moderator Manage -2 ] | B13: Verify adding new Content Moderator | C13: 1. Click "Thêm quản trị viên mới" button 2. Fill in: Fullname, Email, Password (min 6 chars), select "Content Moderator" role 3. Click "Add Moderator" | D13: - Modal opens with empty form - Form validates all required fields - Success message displays - Modal closes - New moderator appears in list with "Content Moderator" badge and "Active" status | E13: Admin logged in, on moderator management page | F13: Passed | G13: 45998 | H13: TuanCM | I13: Passed | J13: 46001 | K13: TuanCM | L13: Passed | M13: 46003 | N13: TuanCM
A14: [Moderator Manage -3 ] | B14: Verify adding new System Moderator | C14: 1. Click "Thêm quản trị viên mới" button 2. Fill in: Fullname, Email, Password, select "System Moderator" role 3. Click "Add Moderator" | D14: - Form accepts System Moderator selection - New moderator created with purple "System Moderator" badge - Status defaults to "Active" | E14: Admin logged in, on moderator management page | F14: Passed | G14: 45998 | H14: TuanCM | I14: Passed | J14: 46001 | K14: TuanCM | L14: Passed | M14: 46003 | N14: TuanCM
A15: [Moderator Manage -4 ] | B15: Verify form validation on add moderator | C15: 1. Click "Thêm quản trị viên mới" 2. Leave fields empty and click "Add Moderator" 3. Enter invalid email format 4. Enter password < 6 characters | D15: - Error message "Please input the full name!" - Error message "Please input the email!" - Error message "Please enter a valid email!" - Error message "Password must be at least 6 characters!" - Form does not submit | E15: Admin logged in | F15: Passed | G15: 45998 | H15: TuanCM | I15: Passed | J15: 46001 | K15: TuanCM | L15: Passed | M15: 46003 | N15: TuanCM
A16: [Moderator Manage -5] | B16: Verify activating inactive moderator | C16: 1. Locate moderator with "Ngừng hoạt động" status 2. Click the toggle switch 3. Click "Yes" in confirmation popup | D16: - Confirmation popup displays asking to activate - Switch turns green/blue - Status badge changes to green "Hoạt động" - Moderator record updated in table | E16: At least one inactive moderator exists | F16: Passed | G16: 45998 | H16: TuanCM | I16: Passed | J16: 46001 | K16: TuanCM | L16: Passed | M16: 46003 | N16: TuanCM
A17: [Moderator Manage -6] | B17: Verify deactivating active moderator | C17: 1. Locate moderator with "Hoạt động" status 2. Click the toggle switch 3. Click "Yes" in confirmation popup | D17: - Confirmation popup displays asking to deactivate - Switch turns gray - Status badge changes to red "Ngừng hoạt động" - Moderator record updated | E17: At least one active moderator exists | F17: Passed | G17: 45998 | H17: TuanCM | I17: Passed | J17: 46001 | K17: TuanCM | L17: Passed | M17: 46003 | N17: TuanCM
A18: [Moderator Manage -7 ] | B18: Verify duplicate email prevention | C18: 1. Click "Thêm quản trị viên mới" 2. Enter email that already exists in system 3. Fill other required fields 4. Click "Add Moderator" | D18: - Error message displays - Moderator not created - Email field highlights error | E18: Existing moderator email known | F18: Passed | G18: 45998 | H18: TuanCM | I18: Passed | J18: 46001 | K18: TuanCM | L18: Passed | M18: 46003 | N18: TuanCM
A19: Salary Report
A20: [Salary - 1] | B20: Verify salary report loads for current month | C20: 1. Login as Admin 2. Navigate to "Báo cáo tài chính" 3. Observe default report display | D20: - Report loads with current month/year selected - Summary cards display: Tổng doanh thu, Phí nền tảng (40%), Thu nhập ròng, Giảng viên có thu nhập - Data table shows lecturer records - All currency formatted as VND | E20: Admin logged in with valid credentials | F20: Passed | G20: 45998 | H20: TuanCM | I20: Passed | J20: 46001 | K20: TuanCM | L20: Passed | M20: 46003 | N20: TuanCM
A21: [Salary - 2] | B21: Verify selecting different month | C21: 1. On salary report page 2. Click month dropdown 3. Select different month (e.g., "Tháng 11") 4. Verify data updates | D21: - Dropdown shows all 12 months - Summary cards update with new data - Table refreshes with selected month data - Data reflects selected month | E21: Admin on salary report page | F21: Passed | G21: 45998 | H21: TuanCM | I21: Passed | J21: 46001 | K21: TuanCM | L21: Passed | M21: 46003 | N21: TuanCM
A22: [Salary - 3] | B22: Verify selecting different year | C22: 1. Click year dropdown 2. Select different year 3. Verify data updates | D22: - Dropdown shows 6 years (current and 5 previous) - All data refreshes for selected year - Summary totals recalculate | E22: Admin on salary report page | F22: Passed | G22: 45998 | H22: TuanCM | I22: Passed | J22: 46001 | K22: TuanCM | L22: Passed | M22: 46003 | N22: TuanCM
A23: [Salary - 4] | B23: Verify month and year combination | C23: 1. Select specific month (e.g., Tháng 3) 2. Select specific year (e.g., 2024) 3. Verify report accuracy | D23: - Report displays data for March 2024 only - Summary cards show correct totals for that period | E23: Admin on salary report page | F23: Passed | G23: 45998 | H23: TuanCM | I23: Passed | J23: 46001 | K23: TuanCM | L23: Passed | M23: 46003 | N23: TuanCM
A24: [Salary - 5] | B24: Verify summary card calculations | C24: 1. Load report with data 2. Verify each summary card calculation | D24: - Tổng doanh thu = sum of all totalRevenue - Phí nền tảng (40%) = sum of all platformFee - Thu nhập ròng = sum of all netIncome- Giảng viên có thu nhập = count where totalRevenue > 0 - All formatted as VND currency | E24: Report loaded with multiple lecturers | F24: Passed | G24: 45998 | H24: TuanCM | I24: Passed | J24: 46001 | K24: TuanCM | L24: Passed | M24: 46003 | N24: TuanCM
A25: [Salary - 6] | B25: Verify lecturer with complete bank info display | C25: 1. Locate lecturer row with bank information 2. Verify "THÔNG TIN NHẬN TIỀN" column | D25: Shows receiver name with user icon - Shows bank name with building icon - Shows bank account number in monospace font - All three pieces of info clearly visible | E25: Lecturer with complete bank info exists | F25: Passed | G25: 45998 | H25: TuanCM | I25: Passed | J25: 46001 | K25: TuanCM | L25: Passed | M25: 46003 | N25: TuanCM
A26: [Salary - 7] | B26: Verify lecturer without bank info display | C26: 1. Locate lecturer row without bank information 2. Verify "THÔNG TIN NHẬN TIỀN" column | D26: - Shows amber warning badge - Text reads "Chưa cập nhật thông tin" - Badge has pulsing dot animation - Styled with amber-50 background | E26: Lecturer without bank info exists | F26: Passed | G26: 45998 | H26: TuanCM | I26: Passed | J26: 46001 | K26: TuanCM | L26: Passed | M26: 46003 | N26: TuanCM
A27: [Salary - 8] | B27: Verify lecturer with zero revenue display | C27: 1. Locate lecturer with totalRevenue = 0 2. Verify row styling and values | D27: - Row has reduced opacity (opacity-50) - Revenue shows 0₫ in gray - Platform fee shows 0₫ - Net income shows 0₫ in gray - Still counted in total lecturer count | E27: Lecturer with no revenue exists | F27: Passed | G27: 45998 | H27: TuanCM | I27: Passed | J27: 46001 | K27: TuanCM | L27: Passed | M27: 46003 | N27: TuanCM
A28: [Salary - 9] | B28: Verify export button disabled when no data | C28: 1. Select month with no data 2. Attempt to click "Xuất Excel" button | D28: - Open window to save CSV file - Toast success "Xuất báo cáo thành công" - File saved with data with current month/ year on table | E28: Report has data loaded | F28: Passed | G28: 45998 | H28: TuanCM | I28: Passed | J28: 46001 | K28: TuanCM | L28: Passed | M28: 46003 | N28: TuanCM

Sheet Test Category
A2: Workflow | B2: Test category | R2: Passed
A3: Test requirement | B3: Check if the functionalities of System Moderator role work well. | R3: Failed
A4: Number of TCs | B4: =COUNTA(A12:A1015) -> 23 | R4: Pending
A5: Testing Round | B5: Passed | C5: Failed | D5: Pending | E5: N/A | R5: N/A
A6: Round 1 | B6: =COUNTIF($F10:$F1013,B5) -> 11 | C6: =COUNTIF($F10:$F1013,C5) -> 0 | D6: =COUNTIF($F10:$F1013,D5) -> 5 | E6: =COUNTIF($F10:$F1013,E5) -> 0
A7: Round 2 | B7: =COUNTIF($F10:$F1013,B5) -> 11 | C7: =COUNTIF($F10:$F1013,C5) -> 0 | D7: =COUNTIF($F10:$F1013,D5) -> 5 | E7: =COUNTIF($F10:$F1013,E5) -> 0
A8: Round 3 | B8: =COUNTIF($F10:$F1013,B5) -> 11 | C8: =COUNTIF($F10:$F1013,C5) -> 0 | D8: =COUNTIF($F10:$F1013,D5) -> 5 | E8: =COUNTIF($F10:$F1013,E5) -> 0
A10: Test Case ID | B10: Test Case Description | C10: Test Case Procedure | D10: Expected Results | E10: Pre-conditions | F10: Round 1 | G10: Test date | H10: Tester | I10: Round 2 | J10: Test date | K10: Tester | L10: Round 3 | M10: Test date | N10: Tester | O10: Note
A11: Scenario A
A12: <ID1> | B12: <Brief description of this case: what is tested?> Ex: Test viewing "Company" form. | C12: <Describe steps to perform this case> Ex: 1. Login the system with Manager role. 2. Click "Company" tab in the left menu. | D12: <Describe results which meet customer's requirement> Ex: The "Company" view form is displayed with the folowing informations: - Company name - Company address - Phone - Fax | E12: <List all test cases or conditions that must be done before performing this case> | F12: Pending | I12: Pending | L12: Pending
A13: <ID2> | B13: <Test case 2> | F13: Pending | I13: Pending | L13: Pending
A14: <ID3> | B14: <Test case 3> | F14: Pending | I14: Pending | L14: Pending
A15: Category Features
A16: [Category- 1] | B16: Test viewing list category | C16: 1. Login the system with Content Moderator role. 2. Click "Quản lý danh mục" in the left menu. | D16: - The "Quản lý danh mục" page is displayed with the title"Quản lý danh mục". - The list of categories and subcategory is loaded and displayed correctly. | E16: - The server must be working - User must exist in the system with the role "Content Moderator". - At least 1 Category and 1 SubCategory must exist in the database. | F16: Passed | G16: 45966 | H16: BinhTB | I16: Pending | L16: Pending
A17: [Category- 2] | B17: Test the Create new Category with empty Name. | C17: 1. Login the system with Content Moderator role. 2. Click "Quản lý danh mục" in the left menu. 3. Click button "Thêm danh mục" 4. Click "Lưu" | D17: - The system send out error message "Xin hãy nhập tên danh mục" | E17: - The server must be working - User role must be Content Moderator - The account status must be "Active" | F17: Passed | G17: 45966 | H17: BinhTB | I17: Pending | L17: Pending
A18: [Category- 3] | B18: Test the Create new Category already exists. | C18: 1. Login the system with Content Moderator role. 2. Click "Quản lý danh mục" in the left menu. 3. Enter the name of an existing category. 4. Click button "Thêm danh mục" 5. Click "Lưu" | D18: - The system send out error message "Tên danh mục đã tồn tại" | E18: - The server must be working - User role must be Content Moderator - The account status must be "Active" | F18: Passed | G18: 45966 | H18: BinhTB | I18: Pending | L18: Pending
A19: [Category - 4] | B19: Test the Create new Category - Happy Path | C19: 1. Login the system with Content Moderator role. 2. Click "Quản lý danh mục" in the left menu. 3. Enter the name of new category. 4. Click button "Thêm danh mục" 5. Click "Lưu" | D19: - The system send out error message "Tạo danh mục mới thành công" | E19: - The server must be working - User role must be Content Moderator - The account status must be "Active" | F19: Passed | G19: 45966 | H19: BinhTB | I19: Pending | L19: Pending
A20: [Category - 5] | B20: Test update the Category with empty Name | C20: 1. Login the system with Content Moderator role. 2. Click "Quản lý danh mục" in the left menu. 3. Remove Name . 4. Click button "Thêm danh mục" 5. Click "Lưu" | D20: - The system send out error message "Xin hãy nhập tên danh mục" | E20: - The server must be working - User role must be Content Moderator - The account status must be "Active" | F20: Passed | G20: 45966 | H20: BinhTB | I20: Pending | L20: Pending
A21: [Category - 6] | B21: Test update the Category with exist Name | C21: 1. Login the system with Content Moderator role. 2. Click "Quản lý danh mục" in the left menu. 3. Enter empty Name . 4. Click button "Thêm danh mục" 5. Click "Lưu" | D21: - The system send out error message "Tên danh mục đã tồn tại" | E21: - The server must be working - User role must be Content Moderator - The account status must be "Active" | F21: Passed | G21: 45966 | H21: BinhTB | I21: Pending | L21: Pending
A22: [Category - 7] | B22: Test the update Category - Happy Path | C22: 1. Login the system with Content Moderator role. 2. Click "Quản lý danh mục" in the left menu. 3. Remove name and enter new name of category 4. Click button "Thêm danh mục" 5. Click "Lưu" | D22: - The system send out error message "Tạo danh mục mới thành công" | E22: - The server must be working - User role must be Content Moderator - The account status must be "Active" | F22: Passed | G22: 45966 | H22: BinhTB | I22: Pending | L22: Pending
A23: [Category - 8] | B23: Test delete Category - Happy Path | C23: 1. Login the system with Content Moderator role. 2. Click "Quản lý danh mục" in the left menu. 3. Click icon "⋮" . 4. Click button "Xóa" | D23: - The system send out error message "Xóa danh mục thành công". - Category is removed from list category | E23: - The server must be working - User role must be Content Moderator - The account status must be "Active" | F23: Passed | G23: 45966 | H23: BinhTB | I23: Pending | L23: Pending
A24: [Category - 9] | B24: Test delete Category with ID does not exist | C24: 1. Login the system with Content Moderator role. 2. Click "Quản lý danh mục" in the left menu. 3. Click icon "⋮" . 4. Click button "Xóa" | D24: - The system send out error message "Không tìm thấy danh mục.". - Category cannot be deleted from list category | E24: - The server must be working - User role must be Content Moderator - The account status must be "Active" | F24: Passed | G24: 45966 | H24: BinhTB | I24: Pending | L24: Pending
A25: [Category - 10] | B25: Test viewing list category if there is no category in the data | C25: 1. Login the system with Content Moderator role. 2. Click "Quản lý danh mục" in the left menu. | D25: - The system send out error message "Danh mục đang trống". | E25: - The server must be working - User role must be Content Moderator - The account status must be "Active" | F25: Pending | G25: 45966 | H25: BinhTB | I25: Pending | L25: Pending
A26: [Category - 11] | B26: Test delete Category have subcategory | C26: 1. Login the system with Content Moderator role. 2. Click "Quản lý danh mục" in the left menu. 3. Click icon "⋮" . 4. Click button "Xóa" | D26: - The system send out error message "Không thể xóa danh mục chứa danh mục con.Vui lòng xóa các danh mục con trước". | E26: - The server must be working - User role must be Content Moderator - The account status must be "Active" | F26: Passed | G26: 45966 | H26: BinhTB
A27: [SubCategory - 10] | B27: Test viewing list sub category | C27: 1. Login the system with Content Moderator role. 2. Click "Quản lý danh mục" in the left menu. | D27: - The "Quản lý danh mục" page is displayed with the title"Quản lý danh mục". - The list of categories and subcategory is loaded and displayed correctly. | E27: - The server must be working - User role must be Content Moderator - The account status must be "Active" | F27: Passed | G27: 45966 | H27: BinhTB
A28: [SubCategory - 11] | B28: Test viewing list sub category if there is no sub category in the data | C28: 1. Login the system with Content Moderator role. 2. Click "Quản lý danh mục" in the left menu. | D28: - The "Quản lý danh mục" page is displayed with the title"Quản lý danh mục". - The list of categories and subcategory is loaded and displayed correctly. | E28: - The server must be working - User role must be Content Moderator - The account status must be "Active"
A29: [SubCategory - 12] | B29: Test viewing list category if there is no category in the data | C29: 1. Login the system with Content Moderator role. 2. Click "Quản lý danh mục" in the left menu. | D29: - The "Quản lý danh mục" page is displayed with the title"Quản lý danh mục". - The list of categories and subcategory is loaded and displayed correctly. | E29: - The server must be working - User role must be Content Moderator - The account status must be "Active"
A30: [SubCategory - 13] | B30: Test viewing list category if there is no category in the data
A31: [SubCategory - 14] | B31: Test viewing list category if there is no category in the data
A32: [SubCategory - 15] | B32: Test viewing list category if there is no category in the data
A33: Scenario C
A34: <ID6> | B34: <Test case 6> | F34: Pending | I34: Pending | L34: Pending
